Workbook
Name Identificacao: Dashboard!$A$3:$X$3
Name Exames: Gastos!$B$3:$H$2999
Name Exames: Exames!$B$3:$I$2999
Name FormasPagamentos: 'Parâmetros'!$L$4:$L$995
Name TiposExames: 'Parâmetros'!$B$3:$D$995
Name SlicerCache_Table_1_Col_1: #N/A
Name SlicerCache_Table_1_Col_3: #N/A
Name SlicerCache_Table_2_Col_13: #N/A
Name SlicerCache_Table_2_Col_14: #N/A

Sheet Dashboard
C1: CONTROLE DE EXAMES DE IMAGENS VETERINÁRIOS
D3: Nome: | E3: Inserir Nome | T3: Faixa: | U3: ='Dashboard-Dados'!$AF$17 -> Branca
C5: Receita | G5: Despesa | K5: Lucro | O5: Exames Totais | S5: Máx. Exames x Mês
C6: ='Dashboard-Dados'!AF1 -> 0 | G6: ='Dashboard-Dados'!AF2 -> 0 | K6: ='Dashboard-Dados'!AF3 -> 0 | O6: ='Dashboard-Dados'!AF5 -> 0 | S6: ='Dashboard-Dados'!AG5 -> 0
Z7: FORMATAÇÃO
B8: Receita Total x Despesa Total | Z8: =IFERROR(__xludf.DUMMYFUNCTION("QUERY({'Dashboard-Dados'!AE7:AI14},""Select Col1, Col5"")"),"Faixas Cor") -> Faixas Cor | AA8: =IFERROR(__xludf.DUMMYFUNCTION("""COMPUTED_VALUE""")," Alvo") -> Alvo
D9: =IFERROR(__xludf.DUMMYFUNCTION("SPARKLINE(C17,{""charttype"",""column"";""ymin"", 0; ""ymax"",MAX(C17:G17);""firstcolor"",""#93c47d""})"),"") | H9: =IFERROR(__xludf.DUMMYFUNCTION("SPARKLINE(G17,{""charttype"",""column"";""ymin"", 0; ""ymax"",MAX(C17:G17);""firstcolor"",""#ea4335""})"),"") | Z9: =IFERROR(__xludf.DUMMYFUNCTION("""COMPUTED_VALUE"""),"31") -> 31
Z10: =IFERROR(__xludf.DUMMYFUNCTION("""COMPUTED_VALUE"""),"Branca") -> Branca | AA10: =IFERROR(__xludf.DUMMYFUNCTION("""COMPUTED_VALUE"""),TRUE) -> TRUE
Z11: =IFERROR(__xludf.DUMMYFUNCTION("""COMPUTED_VALUE"""),"Amarela") -> Amarela | AA11: =IFERROR(__xludf.DUMMYFUNCTION("""COMPUTED_VALUE"""),FALSE) -> FALSE
Z12: =IFERROR(__xludf.DUMMYFUNCTION("""COMPUTED_VALUE"""),"Roxa") -> Roxa | AA12: =IFERROR(__xludf.DUMMYFUNCTION("""COMPUTED_VALUE"""),FALSE) -> FALSE
Z13: =IFERROR(__xludf.DUMMYFUNCTION("""COMPUTED_VALUE"""),"Marrom") -> Marrom | AA13: =IFERROR(__xludf.DUMMYFUNCTION("""COMPUTED_VALUE"""),FALSE) -> FALSE
Z14: =IFERROR(__xludf.DUMMYFUNCTION("""COMPUTED_VALUE"""),"Preta") -> Preta | AA14: =IFERROR(__xludf.DUMMYFUNCTION("""COMPUTED_VALUE"""),FALSE) -> FALSE
D16: Receita | H16: Despesa
C17: =IF(ISBLANK('Dashboard-Dados'!AF1),0,'Dashboard-Dados'!AF1) -> 0 | G17: =IF(ISBLANK('Dashboard-Dados'!AF2),0,'Dashboard-Dados'!AF2) -> 0
AK48: SUM de | AL48: SUM de | AM48: SUM de | AN48: SUM de | AO48: MAX de
AK49: 0 | AL49: 0 | AM49: 0 | AN49: 0 | AO49: 0

Sheet Exames
B1: CONTROLE DE EXAMES DE IMAGENS VETERINÁRIOS
B3: Data Exame | C3: Vet Solicitante | D3: Clínica | E3: Animal | F3: Tipo de Exame | G3: Exame Específico | H3: Valor Exame | I3: Forma Pagamento | K3: Exame | L3: Valor Recebido | M3: Mês-N | N3: Mês | O3: Ano
F4: Ultrassonografia | H4: 120 | I4: Boleto | K4: =IFERROR(__xludf.DUMMYFUNCTION("IF(ISBLANK(B4),"""",IF(ISDATE(B4),""X"",""""))"),"") | L4: =IFERROR(__xludf.DUMMYFUNCTION("IF(ISBLANK(B4),"""",IF(Or(I4=""Em Aberto"",ISBLANK(I4),NOT(ISDATE(B4))),"""",H4))"),"") | M4: =IFERROR(__xludf.DUMMYFUNCTION("IF(ISBLANK(B4),"""",IF(ISDATE(B4),TEXT(B4,""m""),""""))"),"") | N4: =IFERROR(__xludf.DUMMYFUNCTION("IF(M4="""","""",QUERY({'Dashboard-Dados'!$Y$2:$AA$13},""Select Col2 Where Col1=""&M4))"),"") | O4: =IFERROR(__xludf.DUMMYFUNCTION("IF(ISBLANK(B4),"""",IF(ISDATE(B4),TEXT(B4,""yyyy""),""""))"),"")
K5: =IFERROR(__xludf.DUMMYFUNCTION("IF(ISBLANK(B5),"""",IF(ISDATE(B5),""X"",""""))"),"") | L5: =IFERROR(__xludf.DUMMYFUNCTION("IF(ISBLANK(B5),"""",IF(Or(I5=""Em Aberto"",ISBLANK(I5),NOT(ISDATE(B5))),"""",H5))"),"") | M5: =IFERROR(__xludf.DUMMYFUNCTION("IF(ISBLANK(B5),"""",IF(ISDATE(B5),TEXT(B5,""m""),""""))"),"") | N5: =IFERROR(__xludf.DUMMYFUNCTION("IF(M5="""","""",QUERY({'Dashboard-Dados'!$Y$2:$AA$13},""Select Col2 Where Col1=""&M5))"),"") | O5: =IFERROR(__xludf.DUMMYFUNCTION("IF(ISBLANK(B5),"""",IF(ISDATE(B5),TEXT(B5,""yyyy""),""""))"),"")
K6: =IFERROR(__xludf.DUMMYFUNCTION("IF(ISBLANK(B6),"""",IF(ISDATE(B6),""X"",""""))"),"") | L6: =IFERROR(__xludf.DUMMYFUNCTION("IF(ISBLANK(B6),"""",IF(Or(I6=""Em Aberto"",ISBLANK(I6),NOT(ISDATE(B6))),"""",H6))"),"") | M6: =IFERROR(__xludf.DUMMYFUNCTION("IF(ISBLANK(B6),"""",IF(ISDATE(B6),TEXT(B6,""m""),""""))"),"") | N6: =IFERROR(__xludf.DUMMYFUNCTION("IF(M6="""","""",QUERY({'Dashboard-Dados'!$Y$2:$AA$13},""Select Col2 Where Col1=""&M6))"),"") | O6: =IFERROR(__xludf.DUMMYFUNCTION("IF(ISBLANK(B6),"""",IF(ISDATE(B6),TEXT(B6,""yyyy""),""""))"),"")
K7: =IFERROR(__xludf.DUMMYFUNCTION("IF(ISBLANK(B7),"""",IF(ISDATE(B7),""X"",""""))"),"") | L7: =IFERROR(__xludf.DUMMYFUNCTION("IF(ISBLANK(B7),"""",IF(Or(I7=""Em Aberto"",ISBLANK(I7),NOT(ISDATE(B7))),"""",H7))"),"") | M7: =IFERROR(__xludf.DUMMYFUNCTION("IF(ISBLANK(B7),"""",IF(ISDATE(B7),TEXT(B7,""m""),""""))"),"") | N7: =IFERROR(__xludf.DUMMYFUNCTION("IF(M7="""","""",QUERY({'Dashboard-Dados'!$Y$2:$AA$13},""Select Col2 Where Col1=""&M7))"),"") | O7: =IFERROR(__xludf.DUMMYFUNCTION("IF(ISBLANK(B7),"""",IF(ISDATE(B7),TEXT(B7,""yyyy""),""""))"),"")
K8: =IFERROR(__xludf.DUMMYFUNCTION("IF(ISBLANK(B8),"""",IF(ISDATE(B8),""X"",""""))"),"") | L8: =IFERROR(__xludf.DUMMYFUNCTION("IF(ISBLANK(B8),"""",IF(Or(I8=""Em Aberto"",ISBLANK(I8),NOT(ISDATE(B8))),"""",H8))"),"") | M8: =IFERROR(__xludf.DUMMYFUNCTION("IF(ISBLANK(B8),"""",IF(ISDATE(B8),TEXT(B8,""m""),""""))"),"") | N8: =IFERROR(__xludf.DUMMYFUNCTION("IF(M8="""","""",QUERY({'Dashboard-Dados'!$Y$2:$AA$13},""Select Col2 Where Col1=""&M8))"),"") | O8: =IFERROR(__xludf.DUMMYFUNCTION("IF(ISBLANK(B8),"""",IF(ISDATE(B8),TEXT(B8,""yyyy""),""""))"),"")
K9: =IFERROR(__xludf.DUMMYFUNCTION("IF(ISBLANK(B9),"""",IF(ISDATE(B9),""X"",""""))"),"") | L9: =IFERROR(__xludf.DUMMYFUNCTION("IF(ISBLANK(B9),"""",IF(Or(I9=""Em Aberto"",ISBLANK(I9),NOT(ISDATE(B9))),"""",H9))"),"") | M9: =IFERROR(__xludf.DUMMYFUNCTION("IF(ISBLANK(B9),"""",IF(ISDATE(B9),TEXT(B9,""m""),""""))"),"") | N9: =IFERROR(__xludf.DUMMYFUNCTION("IF(M9="""","""",QUERY({'Dashboard-Dados'!$Y$2:$AA$13},""Select Col2 Where Col1=""&M9))"),"") | O9: =IFERROR(__xludf.DUMMYFUNCTION("IF(ISBLANK(B9),"""",IF(ISDATE(B9),TEXT(B9,""yyyy""),""""))"),"")
K10: =IFERROR(__xludf.DUMMYFUNCTION("IF(ISBLANK(B10),"""",IF(ISDATE(B10),""X"",""""))"),"") | L10: =IFERROR(__xludf.DUMMYFUNCTION("IF(ISBLANK(B10),"""",IF(Or(I10=""Em Aberto"",ISBLANK(I10),NOT(ISDATE(B10))),"""",H10))"),"") | M10: =IFERROR(__xludf.DUMMYFUNCTION("IF(ISBLANK(B10),"""",IF(ISDATE(B10),TEXT(B10,""m""),""""))"),"") | N10: =IFERROR(__xludf.DUMMYFUNCTION("IF(M10="""","""",QUERY({'Dashboard-Dados'!$Y$2:$AA$13},""Select Col2 Where Col1=""&M10))"),"") | O10: =IFERROR(__xludf.DUMMYFUNCTION("IF(ISBLANK(B10),"""",IF(ISDATE(B10),TEXT(B10,""yyyy""),""""))"),"")
K11: =IFERROR(__xludf.DUMMYFUNCTION("IF(ISBLANK(B11),"""",IF(ISDATE(B11),""X"",""""))"),"") | L11: =IFERROR(__xludf.DUMMYFUNCTION("IF(ISBLANK(B11),"""",IF(Or(I11=""Em Aberto"",ISBLANK(I11),NOT(ISDATE(B11))),"""",H11))"),"") | M11: =IFERROR(__xludf.DUMMYFUNCTION("IF(ISBLANK(B11),"""",IF(ISDATE(B11),TEXT(B11,""m""),""""))"),"") | N11: =IFERROR(__xludf.DUMMYFUNCTION("IF(M11="""","""",QUERY({'Dashboard-Dados'!$Y$2:$AA$13},""Select Col2 Where Col1=""&M11))"),"") | O11: =IFERROR(__xludf.DUMMYFUNCTION("IF(ISBLANK(B11),"""",IF(ISDATE(B11),TEXT(B11,""yyyy""),""""))"),"")
K12: =IFERROR(__xludf.DUMMYFUNCTION("IF(ISBLANK(B12),"""",IF(ISDATE(B12),""X"",""""))"),"") | L12: =IFERROR(__xludf.DUMMYFUNCTION("IF(ISBLANK(B12),"""",IF(Or(I12=""Em Aberto"",ISBLANK(I12),NOT(ISDATE(B12))),"""",H12))"),"") | M12: =IFERROR(__xludf.DUMMYFUNCTION("IF(ISBLANK(B12),"""",IF(ISDATE(B12),TEXT(B12,""m""),""""))"),"") | N12: =IFERROR(__xludf.DUMMYFUNCTION("IF(M12="""","""",QUERY({'Dashboard-Dados'!$Y$2:$AA$13},""Select Col2 Where Col1=""&M12))"),"") | O12: =IFERROR(__xludf.DUMMYFUNCTION("IF(ISBLANK(B12),"""",IF(ISDATE(B12),TEXT(B12,""yyyy""),""""))"),"")
K13: =IFERROR(__xludf.DUMMYFUNCTION("IF(ISBLANK(B13),"""",IF(ISDATE(B13),""X"",""""))"),"") | L13: =IFERROR(__xludf.DUMMYFUNCTION("IF(ISBLANK(B13),"""",IF(Or(I13=""Em Aberto"",ISBLANK(I13),NOT(ISDATE(B13))),"""",H13))"),"") | M13: =IFERROR(__xludf.DUMMYFUNCTION("IF(ISBLANK(B13),"""",IF(ISDATE(B13),TEXT(B13,""m""),""""))"),"") | N13: =IFERROR(__xludf.DUMMYFUNCTION("IF(M13="""","""",QUERY({'Dashboard-Dados'!$Y$2:$AA$13},""Select Col2 Where Col1=""&M13))"),"") | O13: =IFERROR(__xludf.DUMMYFUNCTION("IF(ISBLANK(B13),"""",IF(ISDATE(B13),TEXT(B13,""yyyy""),""""))"),"")
K14: =IFERROR(__xludf.DUMMYFUNCTION("IF(ISBLANK(B14),"""",IF(ISDATE(B14),""X"",""""))"),"") | L14: =IFERROR(__xludf.DUMMYFUNCTION("IF(ISBLANK(B14),"""",IF(Or(I14=""Em Aberto"",ISBLANK(I14),NOT(ISDATE(B14))),"""",H14))"),"") | M14: =IFERROR(__xludf.DUMMYFUNCTION("IF(ISBLANK(B14),"""",IF(ISDATE(B14),TEXT(B14,""m""),""""))"),"") | N14: =IFERROR(__xludf.DUMMYFUNCTION("IF(M14="""","""",QUERY({'Dashboard-Dados'!$Y$2:$AA$13},""Select Col2 Where Col1=""&M14))"),"") | O14: =IFERROR(__xludf.DUMMYFUNCTION("IF(ISBLANK(B14),"""",IF(ISDATE(B14),TEXT(B14,""yyyy""),""""))"),"")
K15: =IFERROR(__xludf.DUMMYFUNCTION("IF(ISBLANK(B15),"""",IF(ISDATE(B15),""X"",""""))"),"") | L15: =IFERROR(__xludf.DUMMYFUNCTION("IF(ISBLANK(B15),"""",IF(Or(I15=""Em Aberto"",ISBLANK(I15),NOT(ISDATE(B15))),"""",H15))"),"") | M15: =IFERROR(__xludf.DUMMYFUNCTION("IF(ISBLANK(B15),"""",IF(ISDATE(B15),TEXT(B15,""m""),""""))"),"") | N15: =IFERROR(__xludf.DUMMYFUNCTION("IF(M15="""","""",QUERY({'Dashboard-Dados'!$Y$2:$AA$13},""Select Col2 Where Col1=""&M15))"),"") | O15: =IFERROR(__xludf.DUMMYFUNCTION("IF(ISBLANK(B15),"""",IF(ISDATE(B15),TEXT(B15,""yyyy""),""""))"),"")
K16: =IFERROR(__xludf.DUMMYFUNCTION("IF(ISBLANK(B16),"""",IF(ISDATE(B16),""X"",""""))"),"") | L16: =IFERROR(__xludf.DUMMYFUNCTION("IF(ISBLANK(B16),"""",IF(Or(I16=""Em Aberto"",ISBLANK(I16),NOT(ISDATE(B16))),"""",H16))"),"") | M16: =IFERROR(__xludf.DUMMYFUNCTION("IF(ISBLANK(B16),"""",IF(ISDATE(B16),TEXT(B16,""m""),""""))"),"") | N16: =IFERROR(__xludf.DUMMYFUNCTION("IF(M16="""","""",QUERY({'Dashboard-Dados'!$Y$2:$AA$13},""Select Col2 Where Col1=""&M16))"),"") | O16: =IFERROR(__xludf.DUMMYFUNCTION("IF(ISBLANK(B16),"""",IF(ISDATE(B16),TEXT(B16,""yyyy""),""""))"),"")
K17: =IFERROR(__xludf.DUMMYFUNCTION("IF(ISBLANK(B17),"""",IF(ISDATE(B17),""X"",""""))"),"") | L17: =IFERROR(__xludf.DUMMYFUNCTION("IF(ISBLANK(B17),"""",IF(Or(I17=""Em Aberto"",ISBLANK(I17),NOT(ISDATE(B17))),"""",H17))"),"") | M17: =IFERROR(__xludf.DUMMYFUNCTION("IF(ISBLANK(B17),"""",IF(ISDATE(B17),TEXT(B17,""m""),""""))"),"") | N17: =IFERROR(__xludf.DUMMYFUNCTION("IF(M17="""","""",QUERY({'Dashboard-Dados'!$Y$2:$AA$13},""Select Col2 Where Col1=""&M17))"),"") | O17: =IFERROR(__xludf.DUMMYFUNCTION("IF(ISBLANK(B17),"""",IF(ISDATE(B17),TEXT(B17,""yyyy""),""""))"),"")
K18: =IFERROR(__xludf.DUMMYFUNCTION("IF(ISBLANK(B18),"""",IF(ISDATE(B18),""X"",""""))"),"") | L18: =IFERROR(__xludf.DUMMYFUNCTION("IF(ISBLANK(B18),"""",IF(Or(I18=""Em Aberto"",ISBLANK(I18),NOT(ISDATE(B18))),"""",H18))"),"") | M18: =IFERROR(__xludf.DUMMYFUNCTION("IF(ISBLANK(B18),"""",IF(ISDATE(B18),TEXT(B18,""m""),""""))"),"") | N18: =IFERROR(__xludf.DUMMYFUNCTION("IF(M18="""","""",QUERY({'Dashboard-Dados'!$Y$2:$AA$13},""Select Col2 Where Col1=""&M18))"),"") | O18: =IFERROR(__xludf.DUMMYFUNCTION("IF(ISBLANK(B18),"""",IF(ISDATE(B18),TEXT(B18,""yyyy""),""""))"),"")
K19: =IFERROR(__xludf.DUMMYFUNCTION("IF(ISBLANK(B19),"""",IF(ISDATE(B19),""X"",""""))"),"") | L19: =IFERROR(__xludf.DUMMYFUNCTION("IF(ISBLANK(B19),"""",IF(Or(I19=""Em Aberto"",ISBLANK(I19),NOT(ISDATE(B19))),"""",H19))"),"") | M19: =IFERROR(__xludf.DUMMYFUNCTION("IF(ISBLANK(B19),"""",IF(ISDATE(B19),TEXT(B19,""m""),""""))"),"") | N19: =IFERROR(__xludf.DUMMYFUNCTION("IF(M19="""","""",QUERY({'Dashboard-Dados'!$Y$2:$AA$13},""Select Col2 Where Col1=""&M19))"),"") | O19: =IFERROR(__xludf.DUMMYFUNCTION("IF(ISBLANK(B19),"""",IF(ISDATE(B19),TEXT(B19,""yyyy""),""""))"),"")
K20: =IFERROR(__xludf.DUMMYFUNCTION("IF(ISBLANK(B20),"""",IF(ISDATE(B20),""X"",""""))"),"") | L20: =IFERROR(__xludf.DUMMYFUNCTION("IF(ISBLANK(B20),"""",IF(Or(I20=""Em Aberto"",ISBLANK(I20),NOT(ISDATE(B20))),"""",H20))"),"") | M20: =IFERROR(__xludf.DUMMYFUNCTION("IF(ISBLANK(B20),"""",IF(ISDATE(B20),TEXT(B20,""m""),""""))"),"") | N20: =IFERROR(__xludf.DUMMYFUNCTION("IF(M20="""","""",QUERY({'Dashboard-Dados'!$Y$2:$AA$13},""Select Col2 Where Col1=""&M20))"),"") | O20: =IFERROR(__xludf.DUMMYFUNCTION("IF(ISBLANK(B20),"""",IF(ISDATE(B20),TEXT(B20,""yyyy""),""""))"),"")
K21: =IFERROR(__xludf.DUMMYFUNCTION("IF(ISBLANK(B21),"""",IF(ISDATE(B21),""X"",""""))"),"") | L21: =IFERROR(__xludf.DUMMYFUNCTION("IF(ISBLANK(B21),"""",IF(Or(I21=""Em Aberto"",ISBLANK(I21),NOT(ISDATE(B21))),"""",H21))"),"") | M21: =IFERROR(__xludf.DUMMYFUNCTION("IF(ISBLANK(B21),"""",IF(ISDATE(B21),TEXT(B21,""m""),""""))"),"") | N21: =IFERROR(__xludf.DUMMYFUNCTION("IF(M21="""","""",QUERY({'Dashboard-Dados'!$Y$2:$AA$13},""Select Col2 Where Col1=""&M21))"),"") | O21: =IFERROR(__xludf.DUMMYFUNCTION("IF(ISBLANK(B21),"""",IF(ISDATE(B21),TEXT(B21,""yyyy""),""""))"),"")
K22: =IFERROR(__xludf.DUMMYFUNCTION("IF(ISBLANK(B22),"""",IF(ISDATE(B22),""X"",""""))"),"") | L22: =IFERROR(__xludf.DUMMYFUNCTION("IF(ISBLANK(B22),"""",IF(Or(I22=""Em Aberto"",ISBLANK(I22),NOT(ISDATE(B22))),"""",H22))"),"") | M22: =IFERROR(__xludf.DUMMYFUNCTION("IF(ISBLANK(B22),"""",IF(ISDATE(B22),TEXT(B22,""m""),""""))"),"") | N22: =IFERROR(__xludf.DUMMYFUNCTION("IF(M22="""","""",QUERY({'Dashboard-Dados'!$Y$2:$AA$13},""Select Col2 Where Col1=""&M22))"),"") | O22: =IFERROR(__xludf.DUMMYFUNCTION("IF(ISBLANK(B22),"""",IF(ISDATE(B22),TEXT(B22,""yyyy""),""""))"),"")
K23: =IFERROR(__xludf.DUMMYFUNCTION("IF(ISBLANK(B23),"""",IF(ISDATE(B23),""X"",""""))"),"") | L23: =IFERROR(__xludf.DUMMYFUNCTION("IF(ISBLANK(B23),"""",IF(Or(I23=""Em Aberto"",ISBLANK(I23),NOT(ISDATE(B23))),"""",H23))"),"") | M23: =IFERROR(__xludf.DUMMYFUNCTION("IF(ISBLANK(B23),"""",IF(ISDATE(B23),TEXT(B23,""m""),""""))"),"") | N23: =IFERROR(__xludf.DUMMYFUNCTION("IF(M23="""","""",QUERY({'Dashboard-Dados'!$Y$2:$AA$13},""Select Col2 Where Col1=""&M23))"),"") | O23: =IFERROR(__xludf.DUMMYFUNCTION("IF(ISBLANK(B23),"""",IF(ISDATE(B23),TEXT(B23,""yyyy""),""""))"),"")
K24: =IFERROR(__xludf.DUMMYFUNCTION("IF(ISBLANK(B24),"""",IF(ISDATE(B24),""X"",""""))"),"") | L24: =IFERROR(__xludf.DUMMYFUNCTION("IF(ISBLANK(B24),"""",IF(Or(I24=""Em Aberto"",ISBLANK(I24),NOT(ISDATE(B24))),"""",H24))"),"") | M24: =IFERROR(__xludf.DUMMYFUNCTION("IF(ISBLANK(B24),"""",IF(ISDATE(B24),TEXT(B24,""m""),""""))"),"") | N24: =IFERROR(__xludf.DUMMYFUNCTION("IF(M24="""","""",QUERY({'Dashboard-Dados'!$Y$2:$AA$13},""Select Col2 Where Col1=""&M24))"),"") | O24: =IFERROR(__xludf.DUMMYFUNCTION("IF(ISBLANK(B24),"""",IF(ISDATE(B24),TEXT(B24,""yyyy""),""""))"),"")
K25: =IFERROR(__xludf.DUMMYFUNCTION("IF(ISBLANK(B25),"""",IF(ISDATE(B25),""X"",""""))"),"") | L25: =IFERROR(__xludf.DUMMYFUNCTION("IF(ISBLANK(B25),"""",IF(Or(I25=""Em Aberto"",ISBLANK(I25),NOT(ISDATE(B25))),"""",H25))"),"") | M25: =IFERROR(__xludf.DUMMYFUNCTION("IF(ISBLANK(B25),"""",IF(ISDATE(B25),TEXT(B25,""m""),""""))"),"") | N25: =IFERROR(__xludf.DUMMYFUNCTION("IF(M25="""","""",QUERY({'Dashboard-Dados'!$Y$2:$AA$13},""Select Col2 Where Col1=""&M25))"),"") | O25: =IFERROR(__xludf.DUMMYFUNCTION("IF(ISBLANK(B25),"""",IF(ISDATE(B25),TEXT(B25,""yyyy""),""""))"),"")
K26: =IFERROR(__xludf.DUMMYFUNCTION("IF(ISBLANK(B26),"""",IF(ISDATE(B26),""X"",""""))"),"") | L26: =IFERROR(__xludf.DUMMYFUNCTION("IF(ISBLANK(B26),"""",IF(Or(I26=""Em Aberto"",ISBLANK(I26),NOT(ISDATE(B26))),"""",H26))"),"") | M26: =IFERROR(__xludf.DUMMYFUNCTION("IF(ISBLANK(B26),"""",IF(ISDATE(B26),TEXT(B26,""m""),""""))"),"") | N26: =IFERROR(__xludf.DUMMYFUNCTION("IF(M26="""","""",QUERY({'Dashboard-Dados'!$Y$2:$AA$13},""Select Col2 Where Col1=""&M26))"),"") | O26: =IFERROR(__xludf.DUMMYFUNCTION("IF(ISBLANK(B26),"""",IF(ISDATE(B26),TEXT(B26,""yyyy""),""""))"),"")
K27: =IFERROR(__xludf.DUMMYFUNCTION("IF(ISBLANK(B27),"""",IF(ISDATE(B27),""X"",""""))"),"") | L27: =IFERROR(__xludf.DUMMYFUNCTION("IF(ISBLANK(B27),"""",IF(Or(I27=""Em Aberto"",ISBLANK(I27),NOT(ISDATE(B27))),"""",H27))"),"") | M27: =IFERROR(__xludf.DUMMYFUNCTION("IF(ISBLANK(B27),"""",IF(ISDATE(B27),TEXT(B27,""m""),""""))"),"") | N27: =IFERROR(__xludf.DUMMYFUNCTION("IF(M27="""","""",QUERY({'Dashboard-Dados'!$Y$2:$AA$13},""Select Col2 Where Col1=""&M27))"),"") | O27: =IFERROR(__xludf.DUMMYFUNCTION("IF(ISBLANK(B27),"""",IF(ISDATE(B27),TEXT(B27,""yyyy""),""""))"),"")
K28: =IFERROR(__xludf.DUMMYFUNCTION("IF(ISBLANK(B28),"""",IF(ISDATE(B28),""X"",""""))"),"") | L28: =IFERROR(__xludf.DUMMYFUNCTION("IF(ISBLANK(B28),"""",IF(Or(I28=""Em Aberto"",ISBLANK(I28),NOT(ISDATE(B28))),"""",H28))"),"") | M28: =IFERROR(__xludf.DUMMYFUNCTION("IF(ISBLANK(B28),"""",IF(ISDATE(B28),TEXT(B28,""m""),""""))"),"") | N28: =IFERROR(__xludf.DUMMYFUNCTION("IF(M28="""","""",QUERY({'Dashboard-Dados'!$Y$2:$AA$13},""Select Col2 Where Col1=""&M28))"),"") | O28: =IFERROR(__xludf.DUMMYFUNCTION("IF(ISBLANK(B28),"""",IF(ISDATE(B28),TEXT(B28,""yyyy""),""""))"),"")
K29: =IFERROR(__xludf.DUMMYFUNCTION("IF(ISBLANK(B29),"""",IF(ISDATE(B29),""X"",""""))"),"") | L29: =IFERROR(__xludf.DUMMYFUNCTION("IF(ISBLANK(B29),"""",IF(Or(I29=""Em Aberto"",ISBLANK(I29),NOT(ISDATE(B29))),"""",H29))"),"") | M29: =IFERROR(__xludf.DUMMYFUNCTION("IF(ISBLANK(B29),"""",IF(ISDATE(B29),TEXT(B29,""m""),""""))"),"") | N29: =IFERROR(__xludf.DUMMYFUNCTION("IF(M29="""","""",QUERY({'Dashboard-Dados'!$Y$2:$AA$13},""Select Col2 Where Col1=""&M29))"),"") | O29: =IFERROR(__xludf.DUMMYFUNCTION("IF(ISBLANK(B29),"""",IF(ISDATE(B29),TEXT(B29,""yyyy""),""""))"),"")
K30: =IFERROR(__xludf.DUMMYFUNCTION("IF(ISBLANK(B30),"""",IF(ISDATE(B30),""X"",""""))"),"") | L30: =IFERROR(__xludf.DUMMYFUNCTION("IF(ISBLANK(B30),"""",IF(Or(I30=""Em Aberto"",ISBLANK(I30),NOT(ISDATE(B30))),"""",H30))"),"") | M30: =IFERROR(__xludf.DUMMYFUNCTION("IF(ISBLANK(B30),"""",IF(ISDATE(B30),TEXT(B30,""m""),""""))"),"") | N30: =IFERROR(__xludf.DUMMYFUNCTION("IF(M30="""","""",QUERY({'Dashboard-Dados'!$Y$2:$AA$13},""Select Col2 Where Col1=""&M30))"),"") | O30: =IFERROR(__xludf.DUMMYFUNCTION("IF(ISBLANK(B30),"""",IF(ISDATE(B30),TEXT(B30,""yyyy""),""""))"),"")
K31: =IFERROR(__xludf.DUMMYFUNCTION("IF(ISBLANK(B31),"""",IF(ISDATE(B31),""X"",""""))"),"") | L31: =IFERROR(__xludf.DUMMYFUNCTION("IF(ISBLANK(B31),"""",IF(Or(I31=""Em Aberto"",ISBLANK(I31),NOT(ISDATE(B31))),"""",H31))"),"") | M31: =IFERROR(__xludf.DUMMYFUNCTION("IF(ISBLANK(B31),"""",IF(ISDATE(B31),TEXT(B31,""m""),""""))"),"") | N31: =IFERROR(__xludf.DUMMYFUNCTION("IF(M31="""","""",QUERY({'Dashboard-Dados'!$Y$2:$AA$13},""Select Col2 Where Col1=""&M31))"),"") | O31: =IFERROR(__xludf.DUMMYFUNCTION("IF(ISBLANK(B31),"""",IF(ISDATE(B31),TEXT(B31,""yyyy""),""""))"),"")
K32: =IFERROR(__xludf.DUMMYFUNCTION("IF(ISBLANK(B32),"""",IF(ISDATE(B32),""X"",""""))"),"") | L32: =IFERROR(__xludf.DUMMYFUNCTION("IF(ISBLANK(B32),"""",IF(Or(I32=""Em Aberto"",ISBLANK(I32),NOT(ISDATE(B32))),"""",H32))"),"") | M32: =IFERROR(__xludf.DUMMYFUNCTION("IF(ISBLANK(B32),"""",IF(ISDATE(B32),TEXT(B32,""m""),""""))"),"") | N32: =IFERROR(__xludf.DUMMYFUNCTION("IF(M32="""","""",QUERY({'Dashboard-Dados'!$Y$2:$AA$13},""Select Col2 Where Col1=""&M32))"),"") | O32: =IFERROR(__xludf.DUMMYFUNCTION("IF(ISBLANK(B32),"""",IF(ISDATE(B32),TEXT(B32,""yyyy""),""""))"),"")
K33: =IFERROR(__xludf.DUMMYFUNCTION("IF(ISBLANK(B33),"""",IF(ISDATE(B33),""X"",""""))"),"") | L33: =IFERROR(__xludf.DUMMYFUNCTION("IF(ISBLANK(B33),"""",IF(Or(I33=""Em Aberto"",ISBLANK(I33),NOT(ISDATE(B33))),"""",H33))"),"") | M33: =IFERROR(__xludf.DUMMYFUNCTION("IF(ISBLANK(B33),"""",IF(ISDATE(B33),TEXT(B33,""m""),""""))"),"") | N33: =IFERROR(__xludf.DUMMYFUNCTION("IF(M33="""","""",QUERY({'Dashboard-Dados'!$Y$2:$AA$13},""Select Col2 Where Col1=""&M33))"),"") | O33: =IFERROR(__xludf.DUMMYFUNCTION("IF(ISBLANK(B33),"""",IF(ISDATE(B33),TEXT(B33,""yyyy""),""""))"),"")
K34: =IFERROR(__xludf.DUMMYFUNCTION("IF(ISBLANK(B34),"""",IF(ISDATE(B34),""X"",""""))"),"") | L34: =IFERROR(__xludf.DUMMYFUNCTION("IF(ISBLANK(B34),"""",IF(Or(I34=""Em Aberto"",ISBLANK(I34),NOT(ISDATE(B34))),"""",H34))"),"") | M34: =IFERROR(__xludf.DUMMYFUNCTION("IF(ISBLANK(B34),"""",IF(ISDATE(B34),TEXT(B34,""m""),""""))"),"") | N34: =IFERROR(__xludf.DUMMYFUNCTION("IF(M34="""","""",QUERY({'Dashboard-Dados'!$Y$2:$AA$13},""Select Col2 Where Col1=""&M34))"),"") | O34: =IFERROR(__xludf.DUMMYFUNCTION("IF(ISBLANK(B34),"""",IF(ISDATE(B34),TEXT(B34,""yyyy""),""""))"),"")
K35: =IFERROR(__xludf.DUMMYFUNCTION("IF(ISBLANK(B35),"""",IF(ISDATE(B35),""X"",""""))"),"") | L35: =IFERROR(__xludf.DUMMYFUNCTION("IF(ISBLANK(B35),"""",IF(Or(I35=""Em Aberto"",ISBLANK(I35),NOT(ISDATE(B35))),"""",H35))"),"") | M35: =IFERROR(__xludf.DUMMYFUNCTION("IF(ISBLANK(B35),"""",IF(ISDATE(B35),TEXT(B35,""m""),""""))"),"") | N35: =IFERROR(__xludf.DUMMYFUNCTION("IF(M35="""","""",QUERY({'Dashboard-Dados'!$Y$2:$AA$13},""Select Col2 Where Col1=""&M35))"),"") | O35: =IFERROR(__xludf.DUMMYFUNCTION("IF(ISBLANK(B35),"""",IF(ISDATE(B35),TEXT(B35,""yyyy""),""""))"),"")
K36: =IFERROR(__xludf.DUMMYFUNCTION("IF(ISBLANK(B36),"""",IF(ISDATE(B36),""X"",""""))"),"") | L36: =IFERROR(__xludf.DUMMYFUNCTION("IF(ISBLANK(B36),"""",IF(Or(I36=""Em Aberto"",ISBLANK(I36),NOT(ISDATE(B36))),"""",H36))"),"") | M36: =IFERROR(__xludf.DUMMYFUNCTION("IF(ISBLANK(B36),"""",IF(ISDATE(B36),TEXT(B36,""m""),""""))"),"") | N36: =IFERROR(__xludf.DUMMYFUNCTION("IF(M36="""","""",QUERY({'Dashboard-Dados'!$Y$2:$AA$13},""Select Col2 Where Col1=""&M36))"),"") | O36: =IFERROR(__xludf.DUMMYFUNCTION("IF(ISBLANK(B36),"""",IF(ISDATE(B36),TEXT(B36,""yyyy""),""""))"),"")
K37: =IFERROR(__xludf.DUMMYFUNCTION("IF(ISBLANK(B37),"""",IF(ISDATE(B37),""X"",""""))"),"") | L37: =IFERROR(__xludf.DUMMYFUNCTION("IF(ISBLANK(B37),"""",IF(Or(I37=""Em Aberto"",ISBLANK(I37),NOT(ISDATE(B37))),"""",H37))"),"") | M37: =IFERROR(__xludf.DUMMYFUNCTION("IF(ISBLANK(B37),"""",IF(ISDATE(B37),TEXT(B37,""m""),""""))"),"") | N37: =IFERROR(__xludf.DUMMYFUNCTION("IF(M37="""","""",QUERY({'Dashboard-Dados'!$Y$2:$AA$13},""Select Col2 Where Col1=""&M37))"),"") | O37: =IFERROR(__xludf.DUMMYFUNCTION("IF(ISBLANK(B37),"""",IF(ISDATE(B37),TEXT(B37,""yyyy""),""""))"),"")
K38: =IFERROR(__xludf.DUMMYFUNCTION("IF(ISBLANK(B38),"""",IF(ISDATE(B38),""X"",""""))"),"") | L38: =IFERROR(__xludf.DUMMYFUNCTION("IF(ISBLANK(B38),"""",IF(Or(I38=""Em Aberto"",ISBLANK(I38),NOT(ISDATE(B38))),"""",H38))"),"") | M38: =IFERROR(__xludf.DUMMYFUNCTION("IF(ISBLANK(B38),"""",IF(ISDATE(B38),TEXT(B38,""m""),""""))"),"") | N38: =IFERROR(__xludf.DUMMYFUNCTION("IF(M38="""","""",QUERY({'Dashboard-Dados'!$Y$2:$AA$13},""Select Col2 Where Col1=""&M38))"),"") | O38: =IFERROR(__xludf.DUMMYFUNCTION("IF(ISBLANK(B38),"""",IF(ISDATE(B38),TEXT(B38,""yyyy""),""""))"),"")
K39: =IFERROR(__xludf.DUMMYFUNCTION("IF(ISBLANK(B39),"""",IF(ISDATE(B39),""X"",""""))"),"") | L39: =IFERROR(__xludf.DUMMYFUNCTION("IF(ISBLANK(B39),"""",IF(Or(I39=""Em Aberto"",ISBLANK(I39),NOT(ISDATE(B39))),"""",H39))"),"") | M39: =IFERROR(__xludf.DUMMYFUNCTION("IF(ISBLANK(B39),"""",IF(ISDATE(B39),TEXT(B39,""m""),""""))"),"") | N39: =IFERROR(__xludf.DUMMYFUNCTION("IF(M39="""","""",QUERY({'Dashboard-Dados'!$Y$2:$AA$13},""Select Col2 Where Col1=""&M39))"),"") | O39: =IFERROR(__xludf.DUMMYFUNCTION("IF(ISBLANK(B39),"""",IF(ISDATE(B39),TEXT(B39,""yyyy""),""""))"),"")
K40: =IFERROR(__xludf.DUMMYFUNCTION("IF(ISBLANK(B40),"""",IF(ISDATE(B40),""X"",""""))"),"") | L40: =IFERROR(__xludf.DUMMYFUNCTION("IF(ISBLANK(B40),"""",IF(Or(I40=""Em Aberto"",ISBLANK(I40),NOT(ISDATE(B40))),"""",H40))"),"") | M40: =IFERROR(__xludf.DUMMYFUNCTION("IF(ISBLANK(B40),"""",IF(ISDATE(B40),TEXT(B40,""m""),""""))"),"") | N40: =IFERROR(__xludf.DUMMYFUNCTION("IF(M40="""","""",QUERY({'Dashboard-Dados'!$Y$2:$AA$13},""Select Col2 Where Col1=""&M40))"),"") | O40: =IFERROR(__xludf.DUMMYFUNCTION("IF(ISBLANK(B40),"""",IF(ISDATE(B40),TEXT(B40,""yyyy""),""""))"),"")
K41: =IFERROR(__xludf.DUMMYFUNCTION("IF(ISBLANK(B41),"""",IF(ISDATE(B41),""X"",""""))"),"") | L41: =IFERROR(__xludf.DUMMYFUNCTION("IF(ISBLANK(B41),"""",IF(Or(I41=""Em Aberto"",ISBLANK(I41),NOT(ISDATE(B41))),"""",H41))"),"") | M41: =IFERROR(__xludf.DUMMYFUNCTION("IF(ISBLANK(B41),"""",IF(ISDATE(B41),TEXT(B41,""m""),""""))"),"") | N41: =IFERROR(__xludf.DUMMYFUNCTION("IF(M41="""","""",QUERY({'Dashboard-Dados'!$Y$2:$AA$13},""Select Col2 Where Col1=""&M41))"),"") | O41: =IFERROR(__xludf.DUMMYFUNCTION("IF(ISBLANK(B41),"""",IF(ISDATE(B41),TEXT(B41,""yyyy""),""""))"),"")
K42: =IFERROR(__xludf.DUMMYFUNCTION("IF(ISBLANK(B42),"""",IF(ISDATE(B42),""X"",""""))"),"") | L42: =IFERROR(__xludf.DUMMYFUNCTION("IF(ISBLANK(B42),"""",IF(Or(I42=""Em Aberto"",ISBLANK(I42),NOT(ISDATE(B42))),"""",H42))"),"") | M42: =IFERROR(__xludf.DUMMYFUNCTION("IF(ISBLANK(B42),"""",IF(ISDATE(B42),TEXT(B42,""m""),""""))"),"") | N42: =IFERROR(__xludf.DUMMYFUNCTION("IF(M42="""","""",QUERY({'Dashboard-Dados'!$Y$2:$AA$13},""Select Col2 Where Col1=""&M42))"),"") | O42: =IFERROR(__xludf.DUMMYFUNCTION("IF(ISBLANK(B42),"""",IF(ISDATE(B42),TEXT(B42,""yyyy""),""""))"),"")
K43: =IFERROR(__xludf.DUMMYFUNCTION("IF(ISBLANK(B43),"""",IF(ISDATE(B43),""X"",""""))"),"") | L43: =IFERROR(__xludf.DUMMYFUNCTION("IF(ISBLANK(B43),"""",IF(Or(I43=""Em Aberto"",ISBLANK(I43),NOT(ISDATE(B43))),"""",H43))"),"") | M43: =IFERROR(__xludf.DUMMYFUNCTION("IF(ISBLANK(B43),"""",IF(ISDATE(B43),TEXT(B43,""m""),""""))"),"") | N43: =IFERROR(__xludf.DUMMYFUNCTION("IF(M43="""","""",QUERY({'Dashboard-Dados'!$Y$2:$AA$13},""Select Col2 Where Col1=""&M43))"),"") | O43: =IFERROR(__xludf.DUMMYFUNCTION("IF(ISBLANK(B43),"""",IF(ISDATE(B43),TEXT(B43,""yyyy""),""""))"),"")
K44: =IFERROR(__xludf.DUMMYFUNCTION("IF(ISBLANK(B44),"""",IF(ISDATE(B44),""X"",""""))"),"") | L44: =IFERROR(__xludf.DUMMYFUNCTION("IF(ISBLANK(B44),"""",IF(Or(I44=""Em Aberto"",ISBLANK(I44),NOT(ISDATE(B44))),"""",H44))"),"") | M44: =IFERROR(__xludf.DUMMYFUNCTION("IF(ISBLANK(B44),"""",IF(ISDATE(B44),TEXT(B44,""m""),""""))"),"") | N44: =IFERROR(__xludf.DUMMYFUNCTION("IF(M44="""","""",QUERY({'Dashboard-Dados'!$Y$2:$AA$13},""Select Col2 Where Col1=""&M44))"),"") | O44: =IFERROR(__xludf.DUMMYFUNCTION("IF(ISBLANK(B44),"""",IF(ISDATE(B44),TEXT(B44,""yyyy""),""""))"),"")
K45: =IFERROR(__xludf.DUMMYFUNCTION("IF(ISBLANK(B45),"""",IF(ISDATE(B45),""X"",""""))"),"") | L45: =IFERROR(__xludf.DUMMYFUNCTION("IF(ISBLANK(B45),"""",IF(Or(I45=""Em Aberto"",ISBLANK(I45),NOT(ISDATE(B45))),"""",H45))"),"") | M45: =IFERROR(__xludf.DUMMYFUNCTION("IF(ISBLANK(B45),"""",IF(ISDATE(B45),TEXT(B45,""m""),""""))"),"") | N45: =IFERROR(__xludf.DUMMYFUNCTION("IF(M45="""","""",QUERY({'Dashboard-Dados'!$Y$2:$AA$13},""Select Col2 Where Col1=""&M45))"),"") | O45: =IFERROR(__xludf.DUMMYFUNCTION("IF(ISBLANK(B45),"""",IF(ISDATE(B45),TEXT(B45,""yyyy""),""""))"),"")
K46: =IFERROR(__xludf.DUMMYFUNCTION("IF(ISBLANK(B46),"""",IF(ISDATE(B46),""X"",""""))"),"") | L46: =IFERROR(__xludf.DUMMYFUNCTION("IF(ISBLANK(B46),"""",IF(Or(I46=""Em Aberto"",ISBLANK(I46),NOT(ISDATE(B46))),"""",H46))"),"") | M46: =IFERROR(__xludf.DUMMYFUNCTION("IF(ISBLANK(B46),"""",IF(ISDATE(B46),TEXT(B46,""m""),""""))"),"") | N46: =IFERROR(__xludf.DUMMYFUNCTION("IF(M46="""","""",QUERY({'Dashboard-Dados'!$Y$2:$AA$13},""Select Col2 Where Col1=""&M46))"),"") | O46: =IFERROR(__xludf.DUMMYFUNCTION("IF(ISBLANK(B46),"""",IF(ISDATE(B46),TEXT(B46,""yyyy""),""""))"),"")
K47: =IFERROR(__xludf.DUMMYFUNCTION("IF(ISBLANK(B47),"""",IF(ISDATE(B47),""X"",""""))"),"") | L47: =IFERROR(__xludf.DUMMYFUNCTION("IF(ISBLANK(B47),"""",IF(Or(I47=""Em Aberto"",ISBLANK(I47),NOT(ISDATE(B47))),"""",H47))"),"") | M47: =IFERROR(__xludf.DUMMYFUNCTION("IF(ISBLANK(B47),"""",IF(ISDATE(B47),TEXT(B47,""m""),""""))"),"") | N47: =IFERROR(__xludf.DUMMYFUNCTION("IF(M47="""","""",QUERY({'Dashboard-Dados'!$Y$2:$AA$13},""Select Col2 Where Col1=""&M47))"),"") | O47: =IFERROR(__xludf.DUMMYFUNCTION("IF(ISBLANK(B47),"""",IF(ISDATE(B47),TEXT(B47,""yyyy""),""""))"),"")
K48: =IFERROR(__xludf.DUMMYFUNCTION("IF(ISBLANK(B48),"""",IF(ISDATE(B48),""X"",""""))"),"") | L48: =IFERROR(__xludf.DUMMYFUNCTION("IF(ISBLANK(B48),"""",IF(Or(I48=""Em Aberto"",ISBLANK(I48),NOT(ISDATE(B48))),"""",H48))"),"") | M48: =IFERROR(__xludf.DUMMYFUNCTION("IF(ISBLANK(B48),"""",IF(ISDATE(B48),TEXT(B48,""m""),""""))"),"") | N48: =IFERROR(__xludf.DUMMYFUNCTION("IF(M48="""","""",QUERY({'Dashboard-Dados'!$Y$2:$AA$13},""Select Col2 Where Col1=""&M48))"),"") | O48: =IFERROR(__xludf.DUMMYFUNCTION("IF(ISBLANK(B48),"""",IF(ISDATE(B48),TEXT(B48,""yyyy""),""""))"),"")
K49: =IFERROR(__xludf.DUMMYFUNCTION("IF(ISBLANK(B49),"""",IF(ISDATE(B49),""X"",""""))"),"") | L49: =IFERROR(__xludf.DUMMYFUNCTION("IF(ISBLANK(B49),"""",IF(Or(I49=""Em Aberto"",ISBLANK(I49),NOT(ISDATE(B49))),"""",H49))"),"") | M49: =IFERROR(__xludf.DUMMYFUNCTION("IF(ISBLANK(B49),"""",IF(ISDATE(B49),TEXT(B49,""m""),""""))"),"") | N49: =IFERROR(__xludf.DUMMYFUNCTION("IF(M49="""","""",QUERY({'Dashboard-Dados'!$Y$2:$AA$13},""Select Col2 Where Col1=""&M49))"),"") | O49: =IFERROR(__xludf.DUMMYFUNCTION("IF(ISBLANK(B49),"""",IF(ISDATE(B49),TEXT(B49,""yyyy""),""""))"),"")
K50: =IFERROR(__xludf.DUMMYFUNCTION("IF(ISBLANK(B50),"""",IF(ISDATE(B50),""X"",""""))"),"") | L50: =IFERROR(__xludf.DUMMYFUNCTION("IF(ISBLANK(B50),"""",IF(Or(I50=""Em Aberto"",ISBLANK(I50),NOT(ISDATE(B50))),"""",H50))"),"") | M50: =IFERROR(__xludf.DUMMYFUNCTION("IF(ISBLANK(B50),"""",IF(ISDATE(B50),TEXT(B50,""m""),""""))"),"") | N50: =IFERROR(__xludf.DUMMYFUNCTION("IF(M50="""","""",QUERY({'Dashboard-Dados'!$Y$2:$AA$13},""Select Col2 Where Col1=""&M50))"),"") | O50: =IFERROR(__xludf.DUMMYFUNCTION("IF(ISBLANK(B50),"""",IF(ISDATE(B50),TEXT(B50,""yyyy""),""""))"),"")
K51: =IFERROR(__xludf.DUMMYFUNCTION("IF(ISBLANK(B51),"""",IF(ISDATE(B51),""X"",""""))"),"") | L51: =IFERROR(__xludf.DUMMYFUNCTION("IF(ISBLANK(B51),"""",IF(Or(I51=""Em Aberto"",ISBLANK(I51),NOT(ISDATE(B51))),"""",H51))"),"") | M51: =IFERROR(__xludf.DUMMYFUNCTION("IF(ISBLANK(B51),"""",IF(ISDATE(B51),TEXT(B51,""m""),""""))"),"") | N51: =IFERROR(__xludf.DUMMYFUNCTION("IF(M51="""","""",QUERY({'Dashboard-Dados'!$Y$2:$AA$13},""Select Col2 Where Col1=""&M51))"),"") | O51: =IFERROR(__xludf.DUMMYFUNCTION("IF(ISBLANK(B51),"""",IF(ISDATE(B51),TEXT(B51,""yyyy""),""""))"),"")
K52: =IFERROR(__xludf.DUMMYFUNCTION("IF(ISBLANK(B52),"""",IF(ISDATE(B52),""X"",""""))"),"") | L52: =IFERROR(__xludf.DUMMYFUNCTION("IF(ISBLANK(B52),"""",IF(Or(I52=""Em Aberto"",ISBLANK(I52),NOT(ISDATE(B52))),"""",H52))"),"") | M52: =IFERROR(__xludf.DUMMYFUNCTION("IF(ISBLANK(B52),"""",IF(ISDATE(B52),TEXT(B52,""m""),""""))"),"") | N52: =IFERROR(__xludf.DUMMYFUNCTION("IF(M52="""","""",QUERY({'Dashboard-Dados'!$Y$2:$AA$13},""Select Col2 Where Col1=""&M52))"),"") | O52: =IFERROR(__xludf.DUMMYFUNCTION("IF(ISBLANK(B52),"""",IF(ISDATE(B52),TEXT(B52,""yyyy""),""""))"),"")
K53: =IFERROR(__xludf.DUMMYFUNCTION("IF(ISBLANK(B53),"""",IF(ISDATE(B53),""X"",""""))"),"") | L53: =IFERROR(__xludf.DUMMYFUNCTION("IF(ISBLANK(B53),"""",IF(Or(I53=""Em Aberto"",ISBLANK(I53),NOT(ISDATE(B53))),"""",H53))"),"") | M53: =IFERROR(__xludf.DUMMYFUNCTION("IF(ISBLANK(B53),"""",IF(ISDATE(B53),TEXT(B53,""m""),""""))"),"") | N53: =IFERROR(__xludf.DUMMYFUNCTION("IF(M53="""","""",QUERY({'Dashboard-Dados'!$Y$2:$AA$13},""Select Col2 Where Col1=""&M53))"),"") | O53: =IFERROR(__xludf.DUMMYFUNCTION("IF(ISBLANK(B53),"""",IF(ISDATE(B53),TEXT(B53,""yyyy""),""""))"),"")
K54: =IFERROR(__xludf.DUMMYFUNCTION("IF(ISBLANK(B54),"""",IF(ISDATE(B54),""X"",""""))"),"") | L54: =IFERROR(__xludf.DUMMYFUNCTION("IF(ISBLANK(B54),"""",IF(Or(I54=""Em Aberto"",ISBLANK(I54),NOT(ISDATE(B54))),"""",H54))"),"") | M54: =IFERROR(__xludf.DUMMYFUNCTION("IF(ISBLANK(B54),"""",IF(ISDATE(B54),TEXT(B54,""m""),""""))"),"") | N54: =IFERROR(__xludf.DUMMYFUNCTION("IF(M54="""","""",QUERY({'Dashboard-Dados'!$Y$2:$AA$13},""Select Col2 Where Col1=""&M54))"),"") | O54: =IFERROR(__xludf.DUMMYFUNCTION("IF(ISBLANK(B54),"""",IF(ISDATE(B54),TEXT(B54,""yyyy""),""""))"),"")
K55: =IFERROR(__xludf.DUMMYFUNCTION("IF(ISBLANK(B55),"""",IF(ISDATE(B55),""X"",""""))"),"") | L55: =IFERROR(__xludf.DUMMYFUNCTION("IF(ISBLANK(B55),"""",IF(Or(I55=""Em Aberto"",ISBLANK(I55),NOT(ISDATE(B55))),"""",H55))"),"") | M55: =IFERROR(__xludf.DUMMYFUNCTION("IF(ISBLANK(B55),"""",IF(ISDATE(B55),TEXT(B55,""m""),""""))"),"") | N55: =IFERROR(__xludf.DUMMYFUNCTION("IF(M55="""","""",QUERY({'Dashboard-Dados'!$Y$2:$AA$13},""Select Col2 Where Col1=""&M55))"),"") | O55: =IFERROR(__xludf.DUMMYFUNCTION("IF(ISBLANK(B55),"""",IF(ISDATE(B55),TEXT(B55,""yyyy""),""""))"),"")
K56: =IFERROR(__xludf.DUMMYFUNCTION("IF(ISBLANK(B56),"""",IF(ISDATE(B56),""X"",""""))"),"") | L56: =IFERROR(__xludf.DUMMYFUNCTION("IF(ISBLANK(B56),"""",IF(Or(I56=""Em Aberto"",ISBLANK(I56),NOT(ISDATE(B56))),"""",H56))"),"") | M56: =IFERROR(__xludf.DUMMYFUNCTION("IF(ISBLANK(B56),"""",IF(ISDATE(B56),TEXT(B56,""m""),""""))"),"") | N56: =IFERROR(__xludf.DUMMYFUNCTION("IF(M56="""","""",QUERY({'Dashboard-Dados'!$Y$2:$AA$13},""Select Col2 Where Col1=""&M56))"),"") | O56: =IFERROR(__xludf.DUMMYFUNCTION("IF(ISBLANK(B56),"""",IF(ISDATE(B56),TEXT(B56,""yyyy""),""""))"),"")
K57: =IFERROR(__xludf.DUMMYFUNCTION("IF(ISBLANK(B57),"""",IF(ISDATE(B57),""X"",""""))"),"") | L57: =IFERROR(__xludf.DUMMYFUNCTION("IF(ISBLANK(B57),"""",IF(Or(I57=""Em Aberto"",ISBLANK(I57),NOT(ISDATE(B57))),"""",H57))"),"") | M57: =IFERROR(__xludf.DUMMYFUNCTION("IF(ISBLANK(B57),"""",IF(ISDATE(B57),TEXT(B57,""m""),""""))"),"") | N57: =IFERROR(__xludf.DUMMYFUNCTION("IF(M57="""","""",QUERY({'Dashboard-Dados'!$Y$2:$AA$13},""Select Col2 Where Col1=""&M57))"),"") | O57: =IFERROR(__xludf.DUMMYFUNCTION("IF(ISBLANK(B57),"""",IF(ISDATE(B57),TEXT(B57,""yyyy""),""""))"),"")
K58: =IFERROR(__xludf.DUMMYFUNCTION("IF(ISBLANK(B58),"""",IF(ISDATE(B58),""X"",""""))"),"") | L58: =IFERROR(__xludf.DUMMYFUNCTION("IF(ISBLANK(B58),"""",IF(Or(I58=""Em Aberto"",ISBLANK(I58),NOT(ISDATE(B58))),"""",H58))"),"") | M58: =IFERROR(__xludf.DUMMYFUNCTION("IF(ISBLANK(B58),"""",IF(ISDATE(B58),TEXT(B58,""m""),""""))"),"") | N58: =IFERROR(__xludf.DUMMYFUNCTION("IF(M58="""","""",QUERY({'Dashboard-Dados'!$Y$2:$AA$13},""Select Col2 Where Col1=""&M58))"),"") | O58: =IFERROR(__xludf.DUMMYFUNCTION("IF(ISBLANK(B58),"""",IF(ISDATE(B58),TEXT(B58,""yyyy""),""""))"),"")
K59: =IFERROR(__xludf.DUMMYFUNCTION("IF(ISBLANK(B59),"""",IF(ISDATE(B59),""X"",""""))"),"") | L59: =IFERROR(__xludf.DUMMYFUNCTION("IF(ISBLANK(B59),"""",IF(Or(I59=""Em Aberto"",ISBLANK(I59),NOT(ISDATE(B59))),"""",H59))"),"") | M59: =IFERROR(__xludf.DUMMYFUNCTION("IF(ISBLANK(B59),"""",IF(ISDATE(B59),TEXT(B59,""m""),""""))"),"") | N59: =IFERROR(__xludf.DUMMYFUNCTION("IF(M59="""","""",QUERY({'Dashboard-Dados'!$Y$2:$AA$13},""Select Col2 Where Col1=""&M59))"),"") | O59: =IFERROR(__xludf.DUMMYFUNCTION("IF(ISBLANK(B59),"""",IF(ISDATE(B59),TEXT(B59,""yyyy""),""""))"),"")
K60: =IFERROR(__xludf.DUMMYFUNCTION("IF(ISBLANK(B60),"""",IF(ISDATE(B60),""X"",""""))"),"") | L60: =IFERROR(__xludf.DUMMYFUNCTION("IF(ISBLANK(B60),"""",IF(Or(I60=""Em Aberto"",ISBLANK(I60),NOT(ISDATE(B60))),"""",H60))"),"") | M60: =IFERROR(__xludf.DUMMYFUNCTION("IF(ISBLANK(B60),"""",IF(ISDATE(B60),TEXT(B60,""m""),""""))"),"") | N60: =IFERROR(__xludf.DUMMYFUNCTION("IF(M60="""","""",QUERY({'Dashboard-Dados'!$Y$2:$AA$13},""Select Col2 Where Col1=""&M60))"),"") | O60: =IFERROR(__xludf.DUMMYFUNCTION("IF(ISBLANK(B60),"""",IF(ISDATE(B60),TEXT(B60,""yyyy""),""""))"),"")
K61: =IFERROR(__xludf.DUMMYFUNCTION("IF(ISBLANK(B61),"""",IF(ISDATE(B61),""X"",""""))"),"") | L61: =IFERROR(__xludf.DUMMYFUNCTION("IF(ISBLANK(B61),"""",IF(Or(I61=""Em Aberto"",ISBLANK(I61),NOT(ISDATE(B61))),"""",H61))"),"") | M61: =IFERROR(__xludf.DUMMYFUNCTION("IF(ISBLANK(B61),"""",IF(ISDATE(B61),TEXT(B61,""m""),""""))"),"") | N61: =IFERROR(__xludf.DUMMYFUNCTION("IF(M61="""","""",QUERY({'Dashboard-Dados'!$Y$2:$AA$13},""Select Col2 Where Col1=""&M61))"),"") | O61: =IFERROR(__xludf.DUMMYFUNCTION("IF(ISBLANK(B61),"""",IF(ISDATE(B61),TEXT(B61,""yyyy""),""""))"),"")
K62: =IFERROR(__xludf.DUMMYFUNCTION("IF(ISBLANK(B62),"""",IF(ISDATE(B62),""X"",""""))"),"") | L62: =IFERROR(__xludf.DUMMYFUNCTION("IF(ISBLANK(B62),"""",IF(Or(I62=""Em Aberto"",ISBLANK(I62),NOT(ISDATE(B62))),"""",H62))"),"") | M62: =IFERROR(__xludf.DUMMYFUNCTION("IF(ISBLANK(B62),"""",IF(ISDATE(B62),TEXT(B62,""m""),""""))"),"") | N62: =IFERROR(__xludf.DUMMYFUNCTION("IF(M62="""","""",QUERY({'Dashboard-Dados'!$Y$2:$AA$13},""Select Col2 Where Col1=""&M62))"),"") | O62: =IFERROR(__xludf.DUMMYFUNCTION("IF(ISBLANK(B62),"""",IF(ISDATE(B62),TEXT(B62,""yyyy""),""""))"),"")
K63: =IFERROR(__xludf.DUMMYFUNCTION("IF(ISBLANK(B63),"""",IF(ISDATE(B63),""X"",""""))"),"") | L63: =IFERROR(__xludf.DUMMYFUNCTION("IF(ISBLANK(B63),"""",IF(Or(I63=""Em Aberto"",ISBLANK(I63),NOT(ISDATE(B63))),"""",H63))"),"") | M63: =IFERROR(__xludf.DUMMYFUNCTION("IF(ISBLANK(B63),"""",IF(ISDATE(B63),TEXT(B63,""m""),""""))"),"") | N63: =IFERROR(__xludf.DUMMYFUNCTION("IF(M63="""","""",QUERY({'Dashboard-Dados'!$Y$2:$AA$13},""Select Col2 Where Col1=""&M63))"),"") | O63: =IFERROR(__xludf.DUMMYFUNCTION("IF(ISBLANK(B63),"""",IF(ISDATE(B63),TEXT(B63,""yyyy""),""""))"),"")
K64: =IFERROR(__xludf.DUMMYFUNCTION("IF(ISBLANK(B64),"""",IF(ISDATE(B64),""X"",""""))"),"") | L64: =IFERROR(__xludf.DUMMYFUNCTION("IF(ISBLANK(B64),"""",IF(Or(I64=""Em Aberto"",ISBLANK(I64),NOT(ISDATE(B64))),"""",H64))"),"") | M64: =IFERROR(__xludf.DUMMYFUNCTION("IF(ISBLANK(B64),"""",IF(ISDATE(B64),TEXT(B64,""m""),""""))"),"") | N64: =IFERROR(__xludf.DUMMYFUNCTION("IF(M64="""","""",QUERY({'Dashboard-Dados'!$Y$2:$AA$13},""Select Col2 Where Col1=""&M64))"),"") | O64: =IFERROR(__xludf.DUMMYFUNCTION("IF(ISBLANK(B64),"""",IF(ISDATE(B64),TEXT(B64,""yyyy""),""""))"),"")
K65: =IFERROR(__xludf.DUMMYFUNCTION("IF(ISBLANK(B65),"""",IF(ISDATE(B65),""X"",""""))"),"") | L65: =IFERROR(__xludf.DUMMYFUNCTION("IF(ISBLANK(B65),"""",IF(Or(I65=""Em Aberto"",ISBLANK(I65),NOT(ISDATE(B65))),"""",H65))"),"") | M65: =IFERROR(__xludf.DUMMYFUNCTION("IF(ISBLANK(B65),"""",IF(ISDATE(B65),TEXT(B65,""m""),""""))"),"") | N65: =IFERROR(__xludf.DUMMYFUNCTION("IF(M65="""","""",QUERY({'Dashboard-Dados'!$Y$2:$AA$13},""Select Col2 Where Col1=""&M65))"),"") | O65: =IFERROR(__xludf.DUMMYFUNCTION("IF(ISBLANK(B65),"""",IF(ISDATE(B65),TEXT(B65,""yyyy""),""""))"),"")
K66: =IFERROR(__xludf.DUMMYFUNCTION("IF(ISBLANK(B66),"""",IF(ISDATE(B66),""X"",""""))"),"") | L66: =IFERROR(__xludf.DUMMYFUNCTION("IF(ISBLANK(B66),"""",IF(Or(I66=""Em Aberto"",ISBLANK(I66),NOT(ISDATE(B66))),"""",H66))"),"") | M66: =IFERROR(__xludf.DUMMYFUNCTION("IF(ISBLANK(B66),"""",IF(ISDATE(B66),TEXT(B66,""m""),""""))"),"") | N66: =IFERROR(__xludf.DUMMYFUNCTION("IF(M66="""","""",QUERY({'Dashboard-Dados'!$Y$2:$AA$13},""Select Col2 Where Col1=""&M66))"),"") | O66: =IFERROR(__xludf.DUMMYFUNCTION("IF(ISBLANK(B66),"""",IF(ISDATE(B66),TEXT(B66,""yyyy""),""""))"),"")
K67: =IFERROR(__xludf.DUMMYFUNCTION("IF(ISBLANK(B67),"""",IF(ISDATE(B67),""X"",""""))"),"") | L67: =IFERROR(__xludf.DUMMYFUNCTION("IF(ISBLANK(B67),"""",IF(Or(I67=""Em Aberto"",ISBLANK(I67),NOT(ISDATE(B67))),"""",H67))"),"") | M67: =IFERROR(__xludf.DUMMYFUNCTION("IF(ISBLANK(B67),"""",IF(ISDATE(B67),TEXT(B67,""m""),""""))"),"") | N67: =IFERROR(__xludf.DUMMYFUNCTION("IF(M67="""","""",QUERY({'Dashboard-Dados'!$Y$2:$AA$13},""Select Col2 Where Col1=""&M67))"),"") | O67: =IFERROR(__xludf.DUMMYFUNCTION("IF(ISBLANK(B67),"""",IF(ISDATE(B67),TEXT(B67,""yyyy""),""""))"),"")
K68: =IFERROR(__xludf.DUMMYFUNCTION("IF(ISBLANK(B68),"""",IF(ISDATE(B68),""X"",""""))"),"") | L68: =IFERROR(__xludf.DUMMYFUNCTION("IF(ISBLANK(B68),"""",IF(Or(I68=""Em Aberto"",ISBLANK(I68),NOT(ISDATE(B68))),"""",H68))"),"") | M68: =IFERROR(__xludf.DUMMYFUNCTION("IF(ISBLANK(B68),"""",IF(ISDATE(B68),TEXT(B68,""m""),""""))"),"") | N68: =IFERROR(__xludf.DUMMYFUNCTION("IF(M68="""","""",QUERY({'Dashboard-Dados'!$Y$2:$AA$13},""Select Col2 Where Col1=""&M68))"),"") | O68: =IFERROR(__xludf.DUMMYFUNCTION("IF(ISBLANK(B68),"""",IF(ISDATE(B68),TEXT(B68,""yyyy""),""""))"),"")
K69: =IFERROR(__xludf.DUMMYFUNCTION("IF(ISBLANK(B69),"""",IF(ISDATE(B69),""X"",""""))"),"") | L69: =IFERROR(__xludf.DUMMYFUNCTION("IF(ISBLANK(B69),"""",IF(Or(I69=""Em Aberto"",ISBLANK(I69),NOT(ISDATE(B69))),"""",H69))"),"") | M69: =IFERROR(__xludf.DUMMYFUNCTION("IF(ISBLANK(B69),"""",IF(ISDATE(B69),TEXT(B69,""m""),""""))"),"") | N69: =IFERROR(__xludf.DUMMYFUNCTION("IF(M69="""","""",QUERY({'Dashboard-Dados'!$Y$2:$AA$13},""Select Col2 Where Col1=""&M69))"),"") | O69: =IFERROR(__xludf.DUMMYFUNCTION("IF(ISBLANK(B69),"""",IF(ISDATE(B69),TEXT(B69,""yyyy""),""""))"),"")
K70: =IFERROR(__xludf.DUMMYFUNCTION("IF(ISBLANK(B70),"""",IF(ISDATE(B70),""X"",""""))"),"") | L70: =IFERROR(__xludf.DUMMYFUNCTION("IF(ISBLANK(B70),"""",IF(Or(I70=""Em Aberto"",ISBLANK(I70),NOT(ISDATE(B70))),"""",H70))"),"") | M70: =IFERROR(__xludf.DUMMYFUNCTION("IF(ISBLANK(B70),"""",IF(ISDATE(B70),TEXT(B70,""m""),""""))"),"") | N70: =IFERROR(__xludf.DUMMYFUNCTION("IF(M70="""","""",QUERY({'Dashboard-Dados'!$Y$2:$AA$13},""Select Col2 Where Col1=""&M70))"),"") | O70: =IFERROR(__xludf.DUMMYFUNCTION("IF(ISBLANK(B70),"""",IF(ISDATE(B70),TEXT(B70,""yyyy""),""""))"),"")
K71: =IFERROR(__xludf.DUMMYFUNCTION("IF(ISBLANK(B71),"""",IF(ISDATE(B71),""X"",""""))"),"") | L71: =IFERROR(__xludf.DUMMYFUNCTION("IF(ISBLANK(B71),"""",IF(Or(I71=""Em Aberto"",ISBLANK(I71),NOT(ISDATE(B71))),"""",H71))"),"") | M71: =IFERROR(__xludf.DUMMYFUNCTION("IF(ISBLANK(B71),"""",IF(ISDATE(B71),TEXT(B71,""m""),""""))"),"") | N71: =IFERROR(__xludf.DUMMYFUNCTION("IF(M71="""","""",QUERY({'Dashboard-Dados'!$Y$2:$AA$13},""Select Col2 Where Col1=""&M71))"),"") | O71: =IFERROR(__xludf.DUMMYFUNCTION("IF(ISBLANK(B71),"""",IF(ISDATE(B71),TEXT(B71,""yyyy""),""""))"),"")
K72: =IFERROR(__xludf.DUMMYFUNCTION("IF(ISBLANK(B72),"""",IF(ISDATE(B72),""X"",""""))"),"") | L72: =IFERROR(__xludf.DUMMYFUNCTION("IF(ISBLANK(B72),"""",IF(Or(I72=""Em Aberto"",ISBLANK(I72),NOT(ISDATE(B72))),"""",H72))"),"") | M72: =IFERROR(__xludf.DUMMYFUNCTION("IF(ISBLANK(B72),"""",IF(ISDATE(B72),TEXT(B72,""m""),""""))"),"") | N72: =IFERROR(__xludf.DUMMYFUNCTION("IF(M72="""","""",QUERY({'Dashboard-Dados'!$Y$2:$AA$13},""Select Col2 Where Col1=""&M72))"),"") | O72: =IFERROR(__xludf.DUMMYFUNCTION("IF(ISBLANK(B72),"""",IF(ISDATE(B72),TEXT(B72,""yyyy""),""""))"),"")
K73: =IFERROR(__xludf.DUMMYFUNCTION("IF(ISBLANK(B73),"""",IF(ISDATE(B73),""X"",""""))"),"") | L73: =IFERROR(__xludf.DUMMYFUNCTION("IF(ISBLANK(B73),"""",IF(Or(I73=""Em Aberto"",ISBLANK(I73),NOT(ISDATE(B73))),"""",H73))"),"") | M73: =IFERROR(__xludf.DUMMYFUNCTION("IF(ISBLANK(B73),"""",IF(ISDATE(B73),TEXT(B73,""m""),""""))"),"") | N73: =IFERROR(__xludf.DUMMYFUNCTION("IF(M73="""","""",QUERY({'Dashboard-Dados'!$Y$2:$AA$13},""Select Col2 Where Col1=""&M73))"),"") | O73: =IFERROR(__xludf.DUMMYFUNCTION("IF(ISBLANK(B73),"""",IF(ISDATE(B73),TEXT(B73,""yyyy""),""""))"),"")
K74: =IFERROR(__xludf.DUMMYFUNCTION("IF(ISBLANK(B74),"""",IF(ISDATE(B74),""X"",""""))"),"") | L74: =IFERROR(__xludf.DUMMYFUNCTION("IF(ISBLANK(B74),"""",IF(Or(I74=""Em Aberto"",ISBLANK(I74),NOT(ISDATE(B74))),"""",H74))"),"") | M74: =IFERROR(__xludf.DUMMYFUNCTION("IF(ISBLANK(B74),"""",IF(ISDATE(B74),TEXT(B74,""m""),""""))"),"") | N74: =IFERROR(__xludf.DUMMYFUNCTION("IF(M74="""","""",QUERY({'Dashboard-Dados'!$Y$2:$AA$13},""Select Col2 Where Col1=""&M74))"),"") | O74: =IFERROR(__xludf.DUMMYFUNCTION("IF(ISBLANK(B74),"""",IF(ISDATE(B74),TEXT(B74,""yyyy""),""""))"),"")
K75: =IFERROR(__xludf.DUMMYFUNCTION("IF(ISBLANK(B75),"""",IF(ISDATE(B75),""X"",""""))"),"") | L75: =IFERROR(__xludf.DUMMYFUNCTION("IF(ISBLANK(B75),"""",IF(Or(I75=""Em Aberto"",ISBLANK(I75),NOT(ISDATE(B75))),"""",H75))"),"") | M75: =IFERROR(__xludf.DUMMYFUNCTION("IF(ISBLANK(B75),"""",IF(ISDATE(B75),TEXT(B75,""m""),""""))"),"") | N75: =IFERROR(__xludf.DUMMYFUNCTION("IF(M75="""","""",QUERY({'Dashboard-Dados'!$Y$2:$AA$13},""Select Col2 Where Col1=""&M75))"),"") | O75: =IFERROR(__xludf.DUMMYFUNCTION("IF(ISBLANK(B75),"""",IF(ISDATE(B75),TEXT(B75,""yyyy""),""""))"),"")
K76: =IFERROR(__xludf.DUMMYFUNCTION("IF(ISBLANK(B76),"""",IF(ISDATE(B76),""X"",""""))"),"") | L76: =IFERROR(__xludf.DUMMYFUNCTION("IF(ISBLANK(B76),"""",IF(Or(I76=""Em Aberto"",ISBLANK(I76),NOT(ISDATE(B76))),"""",H76))"),"") | M76: =IFERROR(__xludf.DUMMYFUNCTION("IF(ISBLANK(B76),"""",IF(ISDATE(B76),TEXT(B76,""m""),""""))"),"") | N76: =IFERROR(__xludf.DUMMYFUNCTION("IF(M76="""","""",QUERY({'Dashboard-Dados'!$Y$2:$AA$13},""Select Col2 Where Col1=""&M76))"),"") | O76: =IFERROR(__xludf.DUMMYFUNCTION("IF(ISBLANK(B76),"""",IF(ISDATE(B76),TEXT(B76,""yyyy""),""""))"),"")
K77: =IFERROR(__xludf.DUMMYFUNCTION("IF(ISBLANK(B77),"""",IF(ISDATE(B77),""X"",""""))"),"") | L77: =IFERROR(__xludf.DUMMYFUNCTION("IF(ISBLANK(B77),"""",IF(Or(I77=""Em Aberto"",ISBLANK(I77),NOT(ISDATE(B77))),"""",H77))"),"") | M77: =IFERROR(__xludf.DUMMYFUNCTION("IF(ISBLANK(B77),"""",IF(ISDATE(B77),TEXT(B77,""m""),""""))"),"") | N77: =IFERROR(__xludf.DUMMYFUNCTION("IF(M77="""","""",QUERY({'Dashboard-Dados'!$Y$2:$AA$13},""Select Col2 Where Col1=""&M77))"),"") | O77: =IFERROR(__xludf.DUMMYFUNCTION("IF(ISBLANK(B77),"""",IF(ISDATE(B77),TEXT(B77,""yyyy""),""""))"),"")
K78: =IFERROR(__xludf.DUMMYFUNCTION("IF(ISBLANK(B78),"""",IF(ISDATE(B78),""X"",""""))"),"") | L78: =IFERROR(__xludf.DUMMYFUNCTION("IF(ISBLANK(B78),"""",IF(Or(I78=""Em Aberto"",ISBLANK(I78),NOT(ISDATE(B78))),"""",H78))"),"") | M78: =IFERROR(__xludf.DUMMYFUNCTION("IF(ISBLANK(B78),"""",IF(ISDATE(B78),TEXT(B78,""m""),""""))"),"") | N78: =IFERROR(__xludf.DUMMYFUNCTION("IF(M78="""","""",QUERY({'Dashboard-Dados'!$Y$2:$AA$13},""Select Col2 Where Col1=""&M78))"),"") | O78: =IFERROR(__xludf.DUMMYFUNCTION("IF(ISBLANK(B78),"""",IF(ISDATE(B78),TEXT(B78,""yyyy""),""""))"),"")
K79: =IFERROR(__xludf.DUMMYFUNCTION("IF(ISBLANK(B79),"""",IF(ISDATE(B79),""X"",""""))"),"") | L79: =IFERROR(__xludf.DUMMYFUNCTION("IF(ISBLANK(B79),"""",IF(Or(I79=""Em Aberto"",ISBLANK(I79),NOT(ISDATE(B79))),"""",H79))"),"") | M79: =IFERROR(__xludf.DUMMYFUNCTION("IF(ISBLANK(B79),"""",IF(ISDATE(B79),TEXT(B79,""m""),""""))"),"") | N79: =IFERROR(__xludf.DUMMYFUNCTION("IF(M79="""","""",QUERY({'Dashboard-Dados'!$Y$2:$AA$13},""Select Col2 Where Col1=""&M79))"),"") | O79: =IFERROR(__xludf.DUMMYFUNCTION("IF(ISBLANK(B79),"""",IF(ISDATE(B79),TEXT(B79,""yyyy""),""""))"),"")
K80: =IFERROR(__xludf.DUMMYFUNCTION("IF(ISBLANK(B80),"""",IF(ISDATE(B80),""X"",""""))"),"") | L80: =IFERROR(__xludf.DUMMYFUNCTION("IF(ISBLANK(B80),"""",IF(Or(I80=""Em Aberto"",ISBLANK(I80),NOT(ISDATE(B80))),"""",H80))"),"") | M80: =IFERROR(__xludf.DUMMYFUNCTION("IF(ISBLANK(B80),"""",IF(ISDATE(B80),TEXT(B80,""m""),""""))"),"") | N80: =IFERROR(__xludf.DUMMYFUNCTION("IF(M80="""","""",QUERY({'Dashboard-Dados'!$Y$2:$AA$13},""Select Col2 Where Col1=""&M80))"),"") | O80: =IFERROR(__xludf.DUMMYFUNCTION("IF(ISBLANK(B80),"""",IF(ISDATE(B80),TEXT(B80,""yyyy""),""""))"),"")
K81: =IFERROR(__xludf.DUMMYFUNCTION("IF(ISBLANK(B81),"""",IF(ISDATE(B81),""X"",""""))"),"") | L81: =IFERROR(__xludf.DUMMYFUNCTION("IF(ISBLANK(B81),"""",IF(Or(I81=""Em Aberto"",ISBLANK(I81),NOT(ISDATE(B81))),"""",H81))"),"") | M81: =IFERROR(__xludf.DUMMYFUNCTION("IF(ISBLANK(B81),"""",IF(ISDATE(B81),TEXT(B81,""m""),""""))"),"") | N81: =IFERROR(__xludf.DUMMYFUNCTION("IF(M81="""","""",QUERY({'Dashboard-Dados'!$Y$2:$AA$13},""Select Col2 Where Col1=""&M81))"),"") | O81: =IFERROR(__xludf.DUMMYFUNCTION("IF(ISBLANK(B81),"""",IF(ISDATE(B81),TEXT(B81,""yyyy""),""""))"),"")
K82: =IFERROR(__xludf.DUMMYFUNCTION("IF(ISBLANK(B82),"""",IF(ISDATE(B82),""X"",""""))"),"") | L82: =IFERROR(__xludf.DUMMYFUNCTION("IF(ISBLANK(B82),"""",IF(Or(I82=""Em Aberto"",ISBLANK(I82),NOT(ISDATE(B82))),"""",H82))"),"") | M82: =IFERROR(__xludf.DUMMYFUNCTION("IF(ISBLANK(B82),"""",IF(ISDATE(B82),TEXT(B82,""m""),""""))"),"") | N82: =IFERROR(__xludf.DUMMYFUNCTION("IF(M82="""","""",QUERY({'Dashboard-Dados'!$Y$2:$AA$13},""Select Col2 Where Col1=""&M82))"),"") | O82: =IFERROR(__xludf.DUMMYFUNCTION("IF(ISBLANK(B82),"""",IF(ISDATE(B82),TEXT(B82,""yyyy""),""""))"),"")
K83: =IFERROR(__xludf.DUMMYFUNCTION("IF(ISBLANK(B83),"""",IF(ISDATE(B83),""X"",""""))"),"") | L83: =IFERROR(__xludf.DUMMYFUNCTION("IF(ISBLANK(B83),"""",IF(Or(I83=""Em Aberto"",ISBLANK(I83),NOT(ISDATE(B83))),"""",H83))"),"") | M83: =IFERROR(__xludf.DUMMYFUNCTION("IF(ISBLANK(B83),"""",IF(ISDATE(B83),TEXT(B83,""m""),""""))"),"") | N83: =IFERROR(__xludf.DUMMYFUNCTION("IF(M83="""","""",QUERY({'Dashboard-Dados'!$Y$2:$AA$13},""Select Col2 Where Col1=""&M83))"),"") | O83: =IFERROR(__xludf.DUMMYFUNCTION("IF(ISBLANK(B83),"""",IF(ISDATE(B83),TEXT(B83,""yyyy""),""""))"),"")
K84: =IFERROR(__xludf.DUMMYFUNCTION("IF(ISBLANK(B84),"""",IF(ISDATE(B84),""X"",""""))"),"") | L84: =IFERROR(__xludf.DUMMYFUNCTION("IF(ISBLANK(B84),"""",IF(Or(I84=""Em Aberto"",ISBLANK(I84),NOT(ISDATE(B84))),"""",H84))"),"") | M84: =IFERROR(__xludf.DUMMYFUNCTION("IF(ISBLANK(B84),"""",IF(ISDATE(B84),TEXT(B84,""m""),""""))"),"") | N84: =IFERROR(__xludf.DUMMYFUNCTION("IF(M84="""","""",QUERY({'Dashboard-Dados'!$Y$2:$AA$13},""Select Col2 Where Col1=""&M84))"),"") | O84: =IFERROR(__xludf.DUMMYFUNCTION("IF(ISBLANK(B84),"""",IF(ISDATE(B84),TEXT(B84,""yyyy""),""""))"),"")
K85: =IFERROR(__xludf.DUMMYFUNCTION("IF(ISBLANK(B85),"""",IF(ISDATE(B85),""X"",""""))"),"") | L85: =IFERROR(__xludf.DUMMYFUNCTION("IF(ISBLANK(B85),"""",IF(Or(I85=""Em Aberto"",ISBLANK(I85),NOT(ISDATE(B85))),"""",H85))"),"") | M85: =IFERROR(__xludf.DUMMYFUNCTION("IF(ISBLANK(B85),"""",IF(ISDATE(B85),TEXT(B85,""m""),""""))"),"") | N85: =IFERROR(__xludf.DUMMYFUNCTION("IF(M85="""","""",QUERY({'Dashboard-Dados'!$Y$2:$AA$13},""Select Col2 Where Col1=""&M85))"),"") | O85: =IFERROR(__xludf.DUMMYFUNCTION("IF(ISBLANK(B85),"""",IF(ISDATE(B85),TEXT(B85,""yyyy""),""""))"),"")
K86: =IFERROR(__xludf.DUMMYFUNCTION("IF(ISBLANK(B86),"""",IF(ISDATE(B86),""X"",""""))"),"") | L86: =IFERROR(__xludf.DUMMYFUNCTION("IF(ISBLANK(B86),"""",IF(Or(I86=""Em Aberto"",ISBLANK(I86),NOT(ISDATE(B86))),"""",H86))"),"") | M86: =IFERROR(__xludf.DUMMYFUNCTION("IF(ISBLANK(B86),"""",IF(ISDATE(B86),TEXT(B86,""m""),""""))"),"") | N86: =IFERROR(__xludf.DUMMYFUNCTION("IF(M86="""","""",QUERY({'Dashboard-Dados'!$Y$2:$AA$13},""Select Col2 Where Col1=""&M86))"),"") | O86: =IFERROR(__xludf.DUMMYFUNCTION("IF(ISBLANK(B86),"""",IF(ISDATE(B86),TEXT(B86,""yyyy""),""""))"),"")
K87: =IFERROR(__xludf.DUMMYFUNCTION("IF(ISBLANK(B87),"""",IF(ISDATE(B87),""X"",""""))"),"") | L87: =IFERROR(__xludf.DUMMYFUNCTION("IF(ISBLANK(B87),"""",IF(Or(I87=""Em Aberto"",ISBLANK(I87),NOT(ISDATE(B87))),"""",H87))"),"") | M87: =IFERROR(__xludf.DUMMYFUNCTION("IF(ISBLANK(B87),"""",IF(ISDATE(B87),TEXT(B87,""m""),""""))"),"") | N87: =IFERROR(__xludf.DUMMYFUNCTION("IF(M87="""","""",QUERY({'Dashboard-Dados'!$Y$2:$AA$13},""Select Col2 Where Col1=""&M87))"),"") | O87: =IFERROR(__xludf.DUMMYFUNCTION("IF(ISBLANK(B87),"""",IF(ISDATE(B87),TEXT(B87,""yyyy""),""""))"),"")
K88: =IFERROR(__xludf.DUMMYFUNCTION("IF(ISBLANK(B88),"""",IF(ISDATE(B88),""X"",""""))"),"") | L88: =IFERROR(__xludf.DUMMYFUNCTION("IF(ISBLANK(B88),"""",IF(Or(I88=""Em Aberto"",ISBLANK(I88),NOT(ISDATE(B88))),"""",H88))"),"") | M88: =IFERROR(__xludf.DUMMYFUNCTION("IF(ISBLANK(B88),"""",IF(ISDATE(B88),TEXT(B88,""m""),""""))"),"") | N88: =IFERROR(__xludf.DUMMYFUNCTION("IF(M88="""","""",QUERY({'Dashboard-Dados'!$Y$2:$AA$13},""Select Col2 Where Col1=""&M88))"),"") | O88: =IFERROR(__xludf.DUMMYFUNCTION("IF(ISBLANK(B88),"""",IF(ISDATE(B88),TEXT(B88,""yyyy""),""""))"),"")
K89: =IFERROR(__xludf.DUMMYFUNCTION("IF(ISBLANK(B89),"""",IF(ISDATE(B89),""X"",""""))"),"") | L89: =IFERROR(__xludf.DUMMYFUNCTION("IF(ISBLANK(B89),"""",IF(Or(I89=""Em Aberto"",ISBLANK(I89),NOT(ISDATE(B89))),"""",H89))"),"") | M89: =IFERROR(__xludf.DUMMYFUNCTION("IF(ISBLANK(B89),"""",IF(ISDATE(B89),TEXT(B89,""m""),""""))"),"") | N89: =IFERROR(__xludf.DUMMYFUNCTION("IF(M89="""","""",QUERY({'Dashboard-Dados'!$Y$2:$AA$13},""Select Col2 Where Col1=""&M89))"),"") | O89: =IFERROR(__xludf.DUMMYFUNCTION("IF(ISBLANK(B89),"""",IF(ISDATE(B89),TEXT(B89,""yyyy""),""""))"),"")
K90: =IFERROR(__xludf.DUMMYFUNCTION("IF(ISBLANK(B90),"""",IF(ISDATE(B90),""X"",""""))"),"") | L90: =IFERROR(__xludf.DUMMYFUNCTION("IF(ISBLANK(B90),"""",IF(Or(I90=""Em Aberto"",ISBLANK(I90),NOT(ISDATE(B90))),"""",H90))"),"") | M90: =IFERROR(__xludf.DUMMYFUNCTION("IF(ISBLANK(B90),"""",IF(ISDATE(B90),TEXT(B90,""m""),""""))"),"") | N90: =IFERROR(__xludf.DUMMYFUNCTION("IF(M90="""","""",QUERY({'Dashboard-Dados'!$Y$2:$AA$13},""Select Col2 Where Col1=""&M90))"),"") | O90: =IFERROR(__xludf.DUMMYFUNCTION("IF(ISBLANK(B90),"""",IF(ISDATE(B90),TEXT(B90,""yyyy""),""""))"),"")
K91: =IFERROR(__xludf.DUMMYFUNCTION("IF(ISBLANK(B91),"""",IF(ISDATE(B91),""X"",""""))"),"") | L91: =IFERROR(__xludf.DUMMYFUNCTION("IF(ISBLANK(B91),"""",IF(Or(I91=""Em Aberto"",ISBLANK(I91),NOT(ISDATE(B91))),"""",H91))"),"") | M91: =IFERROR(__xludf.DUMMYFUNCTION("IF(ISBLANK(B91),"""",IF(ISDATE(B91),TEXT(B91,""m""),""""))"),"") | N91: =IFERROR(__xludf.DUMMYFUNCTION("IF(M91="""","""",QUERY({'Dashboard-Dados'!$Y$2:$AA$13},""Select Col2 Where Col1=""&M91))"),"") | O91: =IFERROR(__xludf.DUMMYFUNCTION("IF(ISBLANK(B91),"""",IF(ISDATE(B91),TEXT(B91,""yyyy""),""""))"),"")
K92: =IFERROR(__xludf.DUMMYFUNCTION("IF(ISBLANK(B92),"""",IF(ISDATE(B92),""X"",""""))"),"") | L92: =IFERROR(__xludf.DUMMYFUNCTION("IF(ISBLANK(B92),"""",IF(Or(I92=""Em Aberto"",ISBLANK(I92),NOT(ISDATE(B92))),"""",H92))"),"") | M92: =IFERROR(__xludf.DUMMYFUNCTION("IF(ISBLANK(B92),"""",IF(ISDATE(B92),TEXT(B92,""m""),""""))"),"") | N92: =IFERROR(__xludf.DUMMYFUNCTION("IF(M92="""","""",QUERY({'Dashboard-Dados'!$Y$2:$AA$13},""Select Col2 Where Col1=""&M92))"),"") | O92: =IFERROR(__xludf.DUMMYFUNCTION("IF(ISBLANK(B92),"""",IF(ISDATE(B92),TEXT(B92,""yyyy""),""""))"),"")
K93: =IFERROR(__xludf.DUMMYFUNCTION("IF(ISBLANK(B93),"""",IF(ISDATE(B93),""X"",""""))"),"") | L93: =IFERROR(__xludf.DUMMYFUNCTION("IF(ISBLANK(B93),"""",IF(Or(I93=""Em Aberto"",ISBLANK(I93),NOT(ISDATE(B93))),"""",H93))"),"") | M93: =IFERROR(__xludf.DUMMYFUNCTION("IF(ISBLANK(B93),"""",IF(ISDATE(B93),TEXT(B93,""m""),""""))"),"") | N93: =IFERROR(__xludf.DUMMYFUNCTION("IF(M93="""","""",QUERY({'Dashboard-Dados'!$Y$2:$AA$13},""Select Col2 Where Col1=""&M93))"),"") | O93: =IFERROR(__xludf.DUMMYFUNCTION("IF(ISBLANK(B93),"""",IF(ISDATE(B93),TEXT(B93,""yyyy""),""""))"),"")
K94: =IFERROR(__xludf.DUMMYFUNCTION("IF(ISBLANK(B94),"""",IF(ISDATE(B94),""X"",""""))"),"") | L94: =IFERROR(__xludf.DUMMYFUNCTION("IF(ISBLANK(B94),"""",IF(Or(I94=""Em Aberto"",ISBLANK(I94),NOT(ISDATE(B94))),"""",H94))"),"") | M94: =IFERROR(__xludf.DUMMYFUNCTION("IF(ISBLANK(B94),"""",IF(ISDATE(B94),TEXT(B94,""m""),""""))"),"") | N94: =IFERROR(__xludf.DUMMYFUNCTION("IF(M94="""","""",QUERY({'Dashboard-Dados'!$Y$2:$AA$13},""Select Col2 Where Col1=""&M94))"),"") | O94: =IFERROR(__xludf.DUMMYFUNCTION("IF(ISBLANK(B94),"""",IF(ISDATE(B94),TEXT(B94,""yyyy""),""""))"),"")
K95: =IFERROR(__xludf.DUMMYFUNCTION("IF(ISBLANK(B95),"""",IF(ISDATE(B95),""X"",""""))"),"") | L95: =IFERROR(__xludf.DUMMYFUNCTION("IF(ISBLANK(B95),"""",IF(Or(I95=""Em Aberto"",ISBLANK(I95),NOT(ISDATE(B95))),"""",H95))"),"") | M95: =IFERROR(__xludf.DUMMYFUNCTION("IF(ISBLANK(B95),"""",IF(ISDATE(B95),TEXT(B95,""m""),""""))"),"") | N95: =IFERROR(__xludf.DUMMYFUNCTION("IF(M95="""","""",QUERY({'Dashboard-Dados'!$Y$2:$AA$13},""Select Col2 Where Col1=""&M95))"),"") | O95: =IFERROR(__xludf.DUMMYFUNCTION("IF(ISBLANK(B95),"""",IF(ISDATE(B95),TEXT(B95,""yyyy""),""""))"),"")
K96: =IFERROR(__xludf.DUMMYFUNCTION("IF(ISBLANK(B96),"""",IF(ISDATE(B96),""X"",""""))"),"") | L96: =IFERROR(__xludf.DUMMYFUNCTION("IF(ISBLANK(B96),"""",IF(Or(I96=""Em Aberto"",ISBLANK(I96),NOT(ISDATE(B96))),"""",H96))"),"") | M96: =IFERROR(__xludf.DUMMYFUNCTION("IF(ISBLANK(B96),"""",IF(ISDATE(B96),TEXT(B96,""m""),""""))"),"") | N96: =IFERROR(__xludf.DUMMYFUNCTION("IF(M96="""","""",QUERY({'Dashboard-Dados'!$Y$2:$AA$13},""Select Col2 Where Col1=""&M96))"),"") | O96: =IFERROR(__xludf.DUMMYFUNCTION("IF(ISBLANK(B96),"""",IF(ISDATE(B96),TEXT(B96,""yyyy""),""""))"),"")
K97: =IFERROR(__xludf.DUMMYFUNCTION("IF(ISBLANK(B97),"""",IF(ISDATE(B97),""X"",""""))"),"") | L97: =IFERROR(__xludf.DUMMYFUNCTION("IF(ISBLANK(B97),"""",IF(Or(I97=""Em Aberto"",ISBLANK(I97),NOT(ISDATE(B97))),"""",H97))"),"") | M97: =IFERROR(__xludf.DUMMYFUNCTION("IF(ISBLANK(B97),"""",IF(ISDATE(B97),TEXT(B97,""m""),""""))"),"") | N97: =IFERROR(__xludf.DUMMYFUNCTION("IF(M97="""","""",QUERY({'Dashboard-Dados'!$Y$2:$AA$13},""Select Col2 Where Col1=""&M97))"),"") | O97: =IFERROR(__xludf.DUMMYFUNCTION("IF(ISBLANK(B97),"""",IF(ISDATE(B97),TEXT(B97,""yyyy""),""""))"),"")
K98: =IFERROR(__xludf.DUMMYFUNCTION("IF(ISBLANK(B98),"""",IF(ISDATE(B98),""X"",""""))"),"") | L98: =IFERROR(__xludf.DUMMYFUNCTION("IF(ISBLANK(B98),"""",IF(Or(I98=""Em Aberto"",ISBLANK(I98),NOT(ISDATE(B98))),"""",H98))"),"") | M98: =IFERROR(__xludf.DUMMYFUNCTION("IF(ISBLANK(B98),"""",IF(ISDATE(B98),TEXT(B98,""m""),""""))"),"") | N98: =IFERROR(__xludf.DUMMYFUNCTION("IF(M98="""","""",QUERY({'Dashboard-Dados'!$Y$2:$AA$13},""Select Col2 Where Col1=""&M98))"),"") | O98: =IFERROR(__xludf.DUMMYFUNCTION("IF(ISBLANK(B98),"""",IF(ISDATE(B98),TEXT(B98,""yyyy""),""""))"),"")
K99: =IFERROR(__xludf.DUMMYFUNCTION("IF(ISBLANK(B99),"""",IF(ISDATE(B99),""X"",""""))"),"") | L99: =IFERROR(__xludf.DUMMYFUNCTION("IF(ISBLANK(B99),"""",IF(Or(I99=""Em Aberto"",ISBLANK(I99),NOT(ISDATE(B99))),"""",H99))"),"") | M99: =IFERROR(__xludf.DUMMYFUNCTION("IF(ISBLANK(B99),"""",IF(ISDATE(B99),TEXT(B99,""m""),""""))"),"") | N99: =IFERROR(__xludf.DUMMYFUNCTION("IF(M99="""","""",QUERY({'Dashboard-Dados'!$Y$2:$AA$13},""Select Col2 Where Col1=""&M99))"),"") | O99: =IFERROR(__xludf.DUMMYFUNCTION("IF(ISBLANK(B99),"""",IF(ISDATE(B99),TEXT(B99,""yyyy""),""""))"),"")
K100: =IFERROR(__xludf.DUMMYFUNCTION("IF(ISBLANK(B100),"""",IF(ISDATE(B100),""X"",""""))"),"") | L100: =IFERROR(__xludf.DUMMYFUNCTION("IF(ISBLANK(B100),"""",IF(Or(I100=""Em Aberto"",ISBLANK(I100),NOT(ISDATE(B100))),"""",H100))"),"") | M100: =IFERROR(__xludf.DUMMYFUNCTION("IF(ISBLANK(B100),"""",IF(ISDATE(B100),TEXT(B100,""m""),""""))"),"") | N100: =IFERROR(__xludf.DUMMYFUNCTION("IF(M100="""","""",QUERY({'Dashboard-Dados'!$Y$2:$AA$13},""Select Col2 Where Col1=""&M100))"),"") | O100: =IFERROR(__xludf.DUMMYFUNCTION("IF(ISBLANK(B100),"""",IF(ISDATE(B100),TEXT(B100,""yyyy""),""""))"),"")
K101: =IFERROR(__xludf.DUMMYFUNCTION("IF(ISBLANK(B101),"""",IF(ISDATE(B101),""X"",""""))"),"") | L101: =IFERROR(__xludf.DUMMYFUNCTION("IF(ISBLANK(B101),"""",IF(Or(I101=""Em Aberto"",ISBLANK(I101),NOT(ISDATE(B101))),"""",H101))"),"") | M101: =IFERROR(__xludf.DUMMYFUNCTION("IF(ISBLANK(B101),"""",IF(ISDATE(B101),TEXT(B101,""m""),""""))"),"") | N101: =IFERROR(__xludf.DUMMYFUNCTION("IF(M101="""","""",QUERY({'Dashboard-Dados'!$Y$2:$AA$13},""Select Col2 Where Col1=""&M101))"),"") | O101: =IFERROR(__xludf.DUMMYFUNCTION("IF(ISBLANK(B101),"""",IF(ISDATE(B101),TEXT(B101,""yyyy""),""""))"),"")
...

Sheet Gastos
B1: CONTROLE DE GASTOS DE IMAGENS VETERINÁRIOS
B3: Data Pagamento | C3: Despesa ou Investimento | D3: Descrição | H3: Valor Pagamento | J3: Gasto | K3: Valor Despesa | L3: Mês-N | M3: Mês | N3: Ano
C4: Despesa | D4: gel | H4: xxxx | J4: =IFERROR(__xludf.DUMMYFUNCTION("IF(ISBLANK(B4),"""",IF(ISDATE(B4),""X"",""""))"),"") | K4: =IFERROR(__xludf.DUMMYFUNCTION("IF(ISBLANK(B4),"""",IF(ISDATE(B4),H4,""""))"),"") | L4: =IFERROR(__xludf.DUMMYFUNCTION("IF(ISBLANK(B4),"""",IF(ISDATE(B4),TEXT(B4,""m""),""""))"),"") | M4: =IFERROR(__xludf.DUMMYFUNCTION("IF(L4="""","""",QUERY({'Dashboard-Dados'!$Y$2:$AA$13},""Select Col2 Where Col1=""&L4))"),"") | N4: =IFERROR(__xludf.DUMMYFUNCTION("IF(ISBLANK(B4),"""",IF(ISDATE(B4),TEXT(B4,""yyyy""),""""))"),"")
C5: Investimento | J5: =IFERROR(__xludf.DUMMYFUNCTION("IF(ISBLANK(B5),"""",IF(ISDATE(B5),""X"",""""))"),"") | K5: =IFERROR(__xludf.DUMMYFUNCTION("IF(ISBLANK(B5),"""",IF(ISDATE(B5),H5,""""))"),"") | L5: =IFERROR(__xludf.DUMMYFUNCTION("IF(ISBLANK(B5),"""",IF(ISDATE(B5),TEXT(B5,""M""),""""))"),"") | M5: =IFERROR(__xludf.DUMMYFUNCTION("IF(L5="""","""",QUERY({'Dashboard-Dados'!$Y$2:$AA$13},""Select Col2 Where Col1=""&L5))"),"") | N5: =IFERROR(__xludf.DUMMYFUNCTION("IF(ISBLANK(B5),"""",IF(ISDATE(B5),TEXT(B5,""yyyy""),""""))"),"")
J6: =IFERROR(__xludf.DUMMYFUNCTION("IF(ISBLANK(B6),"""",IF(ISDATE(B6),""X"",""""))"),"") | K6: =IFERROR(__xludf.DUMMYFUNCTION("IF(ISBLANK(B6),"""",IF(ISDATE(B6),H6,""""))"),"") | L6: =IFERROR(__xludf.DUMMYFUNCTION("IF(ISBLANK(B6),"""",IF(ISDATE(B6),TEXT(B6,""M""),""""))"),"") | M6: =IFERROR(__xludf.DUMMYFUNCTION("IF(L6="""","""",QUERY({'Dashboard-Dados'!$Y$2:$AA$13},""Select Col2 Where Col1=""&L6))"),"") | N6: =IFERROR(__xludf.DUMMYFUNCTION("IF(ISBLANK(B6),"""",IF(ISDATE(B6),TEXT(B6,""yyyy""),""""))"),"")
J7: =IFERROR(__xludf.DUMMYFUNCTION("IF(ISBLANK(B7),"""",IF(ISDATE(B7),""X"",""""))"),"") | K7: =IFERROR(__xludf.DUMMYFUNCTION("IF(ISBLANK(B7),"""",IF(ISDATE(B7),H7,""""))"),"") | L7: =IFERROR(__xludf.DUMMYFUNCTION("IF(ISBLANK(B7),"""",IF(ISDATE(B7),TEXT(B7,""M""),""""))"),"") | M7: =IFERROR(__xludf.DUMMYFUNCTION("IF(L7="""","""",QUERY({'Dashboard-Dados'!$Y$2:$AA$13},""Select Col2 Where Col1=""&L7))"),"") | N7: =IFERROR(__xludf.DUMMYFUNCTION("IF(ISBLANK(B7),"""",IF(ISDATE(B7),TEXT(B7,""yyyy""),""""))"),"")
J8: =IFERROR(__xludf.DUMMYFUNCTION("IF(ISBLANK(B8),"""",IF(ISDATE(B8),""X"",""""))"),"") | K8: =IFERROR(__xludf.DUMMYFUNCTION("IF(ISBLANK(B8),"""",IF(ISDATE(B8),H8,""""))"),"") | L8: =IFERROR(__xludf.DUMMYFUNCTION("IF(ISBLANK(B8),"""",IF(ISDATE(B8),TEXT(B8,""M""),""""))"),"") | M8: =IFERROR(__xludf.DUMMYFUNCTION("IF(L8="""","""",QUERY({'Dashboard-Dados'!$Y$2:$AA$13},""Select Col2 Where Col1=""&L8))"),"") | N8: =IFERROR(__xludf.DUMMYFUNCTION("IF(ISBLANK(B8),"""",IF(ISDATE(B8),TEXT(B8,""yyyy""),""""))"),"")
J9: =IFERROR(__xludf.DUMMYFUNCTION("IF(ISBLANK(B9),"""",IF(ISDATE(B9),""X"",""""))"),"") | K9: =IFERROR(__xludf.DUMMYFUNCTION("IF(ISBLANK(B9),"""",IF(ISDATE(B9),H9,""""))"),"") | L9: =IFERROR(__xludf.DUMMYFUNCTION("IF(ISBLANK(B9),"""",IF(ISDATE(B9),TEXT(B9,""M""),""""))"),"") | M9: =IFERROR(__xludf.DUMMYFUNCTION("IF(L9="""","""",QUERY({'Dashboard-Dados'!$Y$2:$AA$13},""Select Col2 Where Col1=""&L9))"),"") | N9: =IFERROR(__xludf.DUMMYFUNCTION("IF(ISBLANK(B9),"""",IF(ISDATE(B9),TEXT(B9,""yyyy""),""""))"),"")
J10: =IFERROR(__xludf.DUMMYFUNCTION("IF(ISBLANK(B10),"""",IF(ISDATE(B10),""X"",""""))"),"") | K10: =IFERROR(__xludf.DUMMYFUNCTION("IF(ISBLANK(B10),"""",IF(ISDATE(B10),H10,""""))"),"") | L10: =IFERROR(__xludf.DUMMYFUNCTION("IF(ISBLANK(B10),"""",IF(ISDATE(B10),TEXT(B10,""M""),""""))"),"") | M10: =IFERROR(__xludf.DUMMYFUNCTION("IF(L10="""","""",QUERY({'Dashboard-Dados'!$Y$2:$AA$13},""Select Col2 Where Col1=""&L10))"),"") | N10: =IFERROR(__xludf.DUMMYFUNCTION("IF(ISBLANK(B10),"""",IF(ISDATE(B10),TEXT(B10,""yyyy""),""""))"),"")
J11: =IFERROR(__xludf.DUMMYFUNCTION("IF(ISBLANK(B11),"""",IF(ISDATE(B11),""X"",""""))"),"") | K11: =IFERROR(__xludf.DUMMYFUNCTION("IF(ISBLANK(B11),"""",IF(ISDATE(B11),H11,""""))"),"") | L11: =IFERROR(__xludf.DUMMYFUNCTION("IF(ISBLANK(B11),"""",IF(ISDATE(B11),TEXT(B11,""M""),""""))"),"") | M11: =IFERROR(__xludf.DUMMYFUNCTION("IF(L11="""","""",QUERY({'Dashboard-Dados'!$Y$2:$AA$13},""Select Col2 Where Col1=""&L11))"),"") | N11: =IFERROR(__xludf.DUMMYFUNCTION("IF(ISBLANK(B11),"""",IF(ISDATE(B11),TEXT(B11,""yyyy""),""""))"),"")
J12: =IFERROR(__xludf.DUMMYFUNCTION("IF(ISBLANK(B12),"""",IF(ISDATE(B12),""X"",""""))"),"") | K12: =IFERROR(__xludf.DUMMYFUNCTION("IF(ISBLANK(B12),"""",IF(ISDATE(B12),H12,""""))"),"") | L12: =IFERROR(__xludf.DUMMYFUNCTION("IF(ISBLANK(B12),"""",IF(ISDATE(B12),TEXT(B12,""M""),""""))"),"") | M12: =IFERROR(__xludf.DUMMYFUNCTION("IF(L12="""","""",QUERY({'Dashboard-Dados'!$Y$2:$AA$13},""Select Col2 Where Col1=""&L12))"),"") | N12: =IFERROR(__xludf.DUMMYFUNCTION("IF(ISBLANK(B12),"""",IF(ISDATE(B12),TEXT(B12,""yyyy""),""""))"),"")
J13: =IFERROR(__xludf.DUMMYFUNCTION("IF(ISBLANK(B13),"""",IF(ISDATE(B13),""X"",""""))"),"") | K13: =IFERROR(__xludf.DUMMYFUNCTION("IF(ISBLANK(B13),"""",IF(ISDATE(B13),H13,""""))"),"") | L13: =IFERROR(__xludf.DUMMYFUNCTION("IF(ISBLANK(B13),"""",IF(ISDATE(B13),TEXT(B13,""M""),""""))"),"") | M13: =IFERROR(__xludf.DUMMYFUNCTION("IF(L13="""","""",QUERY({'Dashboard-Dados'!$Y$2:$AA$13},""Select Col2 Where Col1=""&L13))"),"") | N13: =IFERROR(__xludf.DUMMYFUNCTION("IF(ISBLANK(B13),"""",IF(ISDATE(B13),TEXT(B13,""yyyy""),""""))"),"")
J14: =IFERROR(__xludf.DUMMYFUNCTION("IF(ISBLANK(B14),"""",IF(ISDATE(B14),""X"",""""))"),"") | K14: =IFERROR(__xludf.DUMMYFUNCTION("IF(ISBLANK(B14),"""",IF(ISDATE(B14),H14,""""))"),"") | L14: =IFERROR(__xludf.DUMMYFUNCTION("IF(ISBLANK(B14),"""",IF(ISDATE(B14),TEXT(B14,""M""),""""))"),"") | M14: =IFERROR(__xludf.DUMMYFUNCTION("IF(L14="""","""",QUERY({'Dashboard-Dados'!$Y$2:$AA$13},""Select Col2 Where Col1=""&L14))"),"") | N14: =IFERROR(__xludf.DUMMYFUNCTION("IF(ISBLANK(B14),"""",IF(ISDATE(B14),TEXT(B14,""yyyy""),""""))"),"")
J15: =IFERROR(__xludf.DUMMYFUNCTION("IF(ISBLANK(B15),"""",IF(ISDATE(B15),""X"",""""))"),"") | K15: =IFERROR(__xludf.DUMMYFUNCTION("IF(ISBLANK(B15),"""",IF(ISDATE(B15),H15,""""))"),"") | L15: =IFERROR(__xludf.DUMMYFUNCTION("IF(ISBLANK(B15),"""",IF(ISDATE(B15),TEXT(B15,""M""),""""))"),"") | M15: =IFERROR(__xludf.DUMMYFUNCTION("IF(L15="""","""",QUERY({'Dashboard-Dados'!$Y$2:$AA$13},""Select Col2 Where Col1=""&L15))"),"") | N15: =IFERROR(__xludf.DUMMYFUNCTION("IF(ISBLANK(B15),"""",IF(ISDATE(B15),TEXT(B15,""yyyy""),""""))"),"")
J16: =IFERROR(__xludf.DUMMYFUNCTION("IF(ISBLANK(B16),"""",IF(ISDATE(B16),""X"",""""))"),"") | K16: =IFERROR(__xludf.DUMMYFUNCTION("IF(ISBLANK(B16),"""",IF(ISDATE(B16),H16,""""))"),"") | L16: =IFERROR(__xludf.DUMMYFUNCTION("IF(ISBLANK(B16),"""",IF(ISDATE(B16),TEXT(B16,""M""),""""))"),"") | M16: =IFERROR(__xludf.DUMMYFUNCTION("IF(L16="""","""",QUERY({'Dashboard-Dados'!$Y$2:$AA$13},""Select Col2 Where Col1=""&L16))"),"") | N16: =IFERROR(__xludf.DUMMYFUNCTION("IF(ISBLANK(B16),"""",IF(ISDATE(B16),TEXT(B16,""yyyy""),""""))"),"")
J17: =IFERROR(__xludf.DUMMYFUNCTION("IF(ISBLANK(B17),"""",IF(ISDATE(B17),""X"",""""))"),"") | K17: =IFERROR(__xludf.DUMMYFUNCTION("IF(ISBLANK(B17),"""",IF(ISDATE(B17),H17,""""))"),"") | L17: =IFERROR(__xludf.DUMMYFUNCTION("IF(ISBLANK(B17),"""",IF(ISDATE(B17),TEXT(B17,""M""),""""))"),"") | M17: =IFERROR(__xludf.DUMMYFUNCTION("IF(L17="""","""",QUERY({'Dashboard-Dados'!$Y$2:$AA$13},""Select Col2 Where Col1=""&L17))"),"") | N17: =IFERROR(__xludf.DUMMYFUNCTION("IF(ISBLANK(B17),"""",IF(ISDATE(B17),TEXT(B17,""yyyy""),""""))"),"")
J18: =IFERROR(__xludf.DUMMYFUNCTION("IF(ISBLANK(B18),"""",IF(ISDATE(B18),""X"",""""))"),"") | K18: =IFERROR(__xludf.DUMMYFUNCTION("IF(ISBLANK(B18),"""",IF(ISDATE(B18),H18,""""))"),"") | L18: =IFERROR(__xludf.DUMMYFUNCTION("IF(ISBLANK(B18),"""",IF(ISDATE(B18),TEXT(B18,""M""),""""))"),"") | M18: =IFERROR(__xludf.DUMMYFUNCTION("IF(L18="""","""",QUERY({'Dashboard-Dados'!$Y$2:$AA$13},""Select Col2 Where Col1=""&L18))"),"") | N18: =IFERROR(__xludf.DUMMYFUNCTION("IF(ISBLANK(B18),"""",IF(ISDATE(B18),TEXT(B18,""yyyy""),""""))"),"")
J19: =IFERROR(__xludf.DUMMYFUNCTION("IF(ISBLANK(B19),"""",IF(ISDATE(B19),""X"",""""))"),"") | K19: =IFERROR(__xludf.DUMMYFUNCTION("IF(ISBLANK(B19),"""",IF(ISDATE(B19),H19,""""))"),"") | L19: =IFERROR(__xludf.DUMMYFUNCTION("IF(ISBLANK(B19),"""",IF(ISDATE(B19),TEXT(B19,""M""),""""))"),"") | M19: =IFERROR(__xludf.DUMMYFUNCTION("IF(L19="""","""",QUERY({'Dashboard-Dados'!$Y$2:$AA$13},""Select Col2 Where Col1=""&L19))"),"") | N19: =IFERROR(__xludf.DUMMYFUNCTION("IF(ISBLANK(B19),"""",IF(ISDATE(B19),TEXT(B19,""yyyy""),""""))"),"")
J20: =IFERROR(__xludf.DUMMYFUNCTION("IF(ISBLANK(B20),"""",IF(ISDATE(B20),""X"",""""))"),"") | K20: =IFERROR(__xludf.DUMMYFUNCTION("IF(ISBLANK(B20),"""",IF(ISDATE(B20),H20,""""))"),"") | L20: =IFERROR(__xludf.DUMMYFUNCTION("IF(ISBLANK(B20),"""",IF(ISDATE(B20),TEXT(B20,""M""),""""))"),"") | M20: =IFERROR(__xludf.DUMMYFUNCTION("IF(L20="""","""",QUERY({'Dashboard-Dados'!$Y$2:$AA$13},""Select Col2 Where Col1=""&L20))"),"") | N20: =IFERROR(__xludf.DUMMYFUNCTION("IF(ISBLANK(B20),"""",IF(ISDATE(B20),TEXT(B20,""yyyy""),""""))"),"")
J21: =IFERROR(__xludf.DUMMYFUNCTION("IF(ISBLANK(B21),"""",IF(ISDATE(B21),""X"",""""))"),"") | K21: =IFERROR(__xludf.DUMMYFUNCTION("IF(ISBLANK(B21),"""",IF(ISDATE(B21),H21,""""))"),"") | L21: =IFERROR(__xludf.DUMMYFUNCTION("IF(ISBLANK(B21),"""",IF(ISDATE(B21),TEXT(B21,""M""),""""))"),"") | M21: =IFERROR(__xludf.DUMMYFUNCTION("IF(L21="""","""",QUERY({'Dashboard-Dados'!$Y$2:$AA$13},""Select Col2 Where Col1=""&L21))"),"") | N21: =IFERROR(__xludf.DUMMYFUNCTION("IF(ISBLANK(B21),"""",IF(ISDATE(B21),TEXT(B21,""yyyy""),""""))"),"")
J22: =IFERROR(__xludf.DUMMYFUNCTION("IF(ISBLANK(B22),"""",IF(ISDATE(B22),""X"",""""))"),"") | K22: =IFERROR(__xludf.DUMMYFUNCTION("IF(ISBLANK(B22),"""",IF(ISDATE(B22),H22,""""))"),"") | L22: =IFERROR(__xludf.DUMMYFUNCTION("IF(ISBLANK(B22),"""",IF(ISDATE(B22),TEXT(B22,""M""),""""))"),"") | M22: =IFERROR(__xludf.DUMMYFUNCTION("IF(L22="""","""",QUERY({'Dashboard-Dados'!$Y$2:$AA$13},""Select Col2 Where Col1=""&L22))"),"") | N22: =IFERROR(__xludf.DUMMYFUNCTION("IF(ISBLANK(B22),"""",IF(ISDATE(B22),TEXT(B22,""yyyy""),""""))"),"")
J23: =IFERROR(__xludf.DUMMYFUNCTION("IF(ISBLANK(B23),"""",IF(ISDATE(B23),""X"",""""))"),"") | K23: =IFERROR(__xludf.DUMMYFUNCTION("IF(ISBLANK(B23),"""",IF(ISDATE(B23),H23,""""))"),"") | L23: =IFERROR(__xludf.DUMMYFUNCTION("IF(ISBLANK(B23),"""",IF(ISDATE(B23),TEXT(B23,""M""),""""))"),"") | M23: =IFERROR(__xludf.DUMMYFUNCTION("IF(L23="""","""",QUERY({'Dashboard-Dados'!$Y$2:$AA$13},""Select Col2 Where Col1=""&L23))"),"") | N23: =IFERROR(__xludf.DUMMYFUNCTION("IF(ISBLANK(B23),"""",IF(ISDATE(B23),TEXT(B23,""yyyy""),""""))"),"")
J24: =IFERROR(__xludf.DUMMYFUNCTION("IF(ISBLANK(B24),"""",IF(ISDATE(B24),""X"",""""))"),"") | K24: =IFERROR(__xludf.DUMMYFUNCTION("IF(ISBLANK(B24),"""",IF(ISDATE(B24),H24,""""))"),"") | L24: =IFERROR(__xludf.DUMMYFUNCTION("IF(ISBLANK(B24),"""",IF(ISDATE(B24),TEXT(B24,""M""),""""))"),"") | M24: =IFERROR(__xludf.DUMMYFUNCTION("IF(L24="""","""",QUERY({'Dashboard-Dados'!$Y$2:$AA$13},""Select Col2 Where Col1=""&L24))"),"") | N24: =IFERROR(__xludf.DUMMYFUNCTION("IF(ISBLANK(B24),"""",IF(ISDATE(B24),TEXT(B24,""yyyy""),""""))"),"")
J25: =IFERROR(__xludf.DUMMYFUNCTION("IF(ISBLANK(B25),"""",IF(ISDATE(B25),""X"",""""))"),"") | K25: =IFERROR(__xludf.DUMMYFUNCTION("IF(ISBLANK(B25),"""",IF(ISDATE(B25),H25,""""))"),"") | L25: =IFERROR(__xludf.DUMMYFUNCTION("IF(ISBLANK(B25),"""",IF(ISDATE(B25),TEXT(B25,""M""),""""))"),"") | M25: =IFERROR(__xludf.DUMMYFUNCTION("IF(L25="""","""",QUERY({'Dashboard-Dados'!$Y$2:$AA$13},""Select Col2 Where Col1=""&L25))"),"") | N25: =IFERROR(__xludf.DUMMYFUNCTION("IF(ISBLANK(B25),"""",IF(ISDATE(B25),TEXT(B25,""yyyy""),""""))"),"")
J26: =IFERROR(__xludf.DUMMYFUNCTION("IF(ISBLANK(B26),"""",IF(ISDATE(B26),""X"",""""))"),"") | K26: =IFERROR(__xludf.DUMMYFUNCTION("IF(ISBLANK(B26),"""",IF(ISDATE(B26),H26,""""))"),"") | L26: =IFERROR(__xludf.DUMMYFUNCTION("IF(ISBLANK(B26),"""",IF(ISDATE(B26),TEXT(B26,""M""),""""))"),"") | M26: =IFERROR(__xludf.DUMMYFUNCTION("IF(L26="""","""",QUERY({'Dashboard-Dados'!$Y$2:$AA$13},""Select Col2 Where Col1=""&L26))"),"") | N26: =IFERROR(__xludf.DUMMYFUNCTION("IF(ISBLANK(B26),"""",IF(ISDATE(B26),TEXT(B26,""yyyy""),""""))"),"")
J27: =IFERROR(__xludf.DUMMYFUNCTION("IF(ISBLANK(B27),"""",IF(ISDATE(B27),""X"",""""))"),"") | K27: =IFERROR(__xludf.DUMMYFUNCTION("IF(ISBLANK(B27),"""",IF(ISDATE(B27),H27,""""))"),"") | L27: =IFERROR(__xludf.DUMMYFUNCTION("IF(ISBLANK(B27),"""",IF(ISDATE(B27),TEXT(B27,""M""),""""))"),"") | M27: =IFERROR(__xludf.DUMMYFUNCTION("IF(L27="""","""",QUERY({'Dashboard-Dados'!$Y$2:$AA$13},""Select Col2 Where Col1=""&L27))"),"") | N27: =IFERROR(__xludf.DUMMYFUNCTION("IF(ISBLANK(B27),"""",IF(ISDATE(B27),TEXT(B27,""yyyy""),""""))"),"")
J28: =IFERROR(__xludf.DUMMYFUNCTION("IF(ISBLANK(B28),"""",IF(ISDATE(B28),""X"",""""))"),"") | K28: =IFERROR(__xludf.DUMMYFUNCTION("IF(ISBLANK(B28),"""",IF(ISDATE(B28),H28,""""))"),"") | L28: =IFERROR(__xludf.DUMMYFUNCTION("IF(ISBLANK(B28),"""",IF(ISDATE(B28),TEXT(B28,""M""),""""))"),"") | M28: =IFERROR(__xludf.DUMMYFUNCTION("IF(L28="""","""",QUERY({'Dashboard-Dados'!$Y$2:$AA$13},""Select Col2 Where Col1=""&L28))"),"") | N28: =IFERROR(__xludf.DUMMYFUNCTION("IF(ISBLANK(B28),"""",IF(ISDATE(B28),TEXT(B28,""yyyy""),""""))"),"")
J29: =IFERROR(__xludf.DUMMYFUNCTION("IF(ISBLANK(B29),"""",IF(ISDATE(B29),""X"",""""))"),"") | K29: =IFERROR(__xludf.DUMMYFUNCTION("IF(ISBLANK(B29),"""",IF(ISDATE(B29),H29,""""))"),"") | L29: =IFERROR(__xludf.DUMMYFUNCTION("IF(ISBLANK(B29),"""",IF(ISDATE(B29),TEXT(B29,""M""),""""))"),"") | M29: =IFERROR(__xludf.DUMMYFUNCTION("IF(L29="""","""",QUERY({'Dashboard-Dados'!$Y$2:$AA$13},""Select Col2 Where Col1=""&L29))"),"") | N29: =IFERROR(__xludf.DUMMYFUNCTION("IF(ISBLANK(B29),"""",IF(ISDATE(B29),TEXT(B29,""yyyy""),""""))"),"")
J30: =IFERROR(__xludf.DUMMYFUNCTION("IF(ISBLANK(B30),"""",IF(ISDATE(B30),""X"",""""))"),"") | K30: =IFERROR(__xludf.DUMMYFUNCTION("IF(ISBLANK(B30),"""",IF(ISDATE(B30),H30,""""))"),"") | L30: =IFERROR(__xludf.DUMMYFUNCTION("IF(ISBLANK(B30),"""",IF(ISDATE(B30),TEXT(B30,""M""),""""))"),"") | M30: =IFERROR(__xludf.DUMMYFUNCTION("IF(L30="""","""",QUERY({'Dashboard-Dados'!$Y$2:$AA$13},""Select Col2 Where Col1=""&L30))"),"") | N30: =IFERROR(__xludf.DUMMYFUNCTION("IF(ISBLANK(B30),"""",IF(ISDATE(B30),TEXT(B30,""yyyy""),""""))"),"")
J31: =IFERROR(__xludf.DUMMYFUNCTION("IF(ISBLANK(B31),"""",IF(ISDATE(B31),""X"",""""))"),"") | K31: =IFERROR(__xludf.DUMMYFUNCTION("IF(ISBLANK(B31),"""",IF(ISDATE(B31),H31,""""))"),"") | L31: =IFERROR(__xludf.DUMMYFUNCTION("IF(ISBLANK(B31),"""",IF(ISDATE(B31),TEXT(B31,""M""),""""))"),"") | M31: =IFERROR(__xludf.DUMMYFUNCTION("IF(L31="""","""",QUERY({'Dashboard-Dados'!$Y$2:$AA$13},""Select Col2 Where Col1=""&L31))"),"") | N31: =IFERROR(__xludf.DUMMYFUNCTION("IF(ISBLANK(B31),"""",IF(ISDATE(B31),TEXT(B31,""yyyy""),""""))"),"")
J32: =IFERROR(__xludf.DUMMYFUNCTION("IF(ISBLANK(B32),"""",IF(ISDATE(B32),""X"",""""))"),"") | K32: =IFERROR(__xludf.DUMMYFUNCTION("IF(ISBLANK(B32),"""",IF(ISDATE(B32),H32,""""))"),"") | L32: =IFERROR(__xludf.DUMMYFUNCTION("IF(ISBLANK(B32),"""",IF(ISDATE(B32),TEXT(B32,""M""),""""))"),"") | M32: =IFERROR(__xludf.DUMMYFUNCTION("IF(L32="""","""",QUERY({'Dashboard-Dados'!$Y$2:$AA$13},""Select Col2 Where Col1=""&L32))"),"") | N32: =IFERROR(__xludf.DUMMYFUNCTION("IF(ISBLANK(B32),"""",IF(ISDATE(B32),TEXT(B32,""yyyy""),""""))"),"")
J33: =IFERROR(__xludf.DUMMYFUNCTION("IF(ISBLANK(B33),"""",IF(ISDATE(B33),""X"",""""))"),"") | K33: =IFERROR(__xludf.DUMMYFUNCTION("IF(ISBLANK(B33),"""",IF(ISDATE(B33),H33,""""))"),"") | L33: =IFERROR(__xludf.DUMMYFUNCTION("IF(ISBLANK(B33),"""",IF(ISDATE(B33),TEXT(B33,""M""),""""))"),"") | M33: =IFERROR(__xludf.DUMMYFUNCTION("IF(L33="""","""",QUERY({'Dashboard-Dados'!$Y$2:$AA$13},""Select Col2 Where Col1=""&L33))"),"") | N33: =IFERROR(__xludf.DUMMYFUNCTION("IF(ISBLANK(B33),"""",IF(ISDATE(B33),TEXT(B33,""yyyy""),""""))"),"")
J34: =IFERROR(__xludf.DUMMYFUNCTION("IF(ISBLANK(B34),"""",IF(ISDATE(B34),""X"",""""))"),"") | K34: =IFERROR(__xludf.DUMMYFUNCTION("IF(ISBLANK(B34),"""",IF(ISDATE(B34),H34,""""))"),"") | L34: =IFERROR(__xludf.DUMMYFUNCTION("IF(ISBLANK(B34),"""",IF(ISDATE(B34),TEXT(B34,""M""),""""))"),"") | M34: =IFERROR(__xludf.DUMMYFUNCTION("IF(L34="""","""",QUERY({'Dashboard-Dados'!$Y$2:$AA$13},""Select Col2 Where Col1=""&L34))"),"") | N34: =IFERROR(__xludf.DUMMYFUNCTION("IF(ISBLANK(B34),"""",IF(ISDATE(B34),TEXT(B34,""yyyy""),""""))"),"")
J35: =IFERROR(__xludf.DUMMYFUNCTION("IF(ISBLANK(B35),"""",IF(ISDATE(B35),""X"",""""))"),"") | K35: =IFERROR(__xludf.DUMMYFUNCTION("IF(ISBLANK(B35),"""",IF(ISDATE(B35),H35,""""))"),"") | L35: =IFERROR(__xludf.DUMMYFUNCTION("IF(ISBLANK(B35),"""",IF(ISDATE(B35),TEXT(B35,""M""),""""))"),"") | M35: =IFERROR(__xludf.DUMMYFUNCTION("IF(L35="""","""",QUERY({'Dashboard-Dados'!$Y$2:$AA$13},""Select Col2 Where Col1=""&L35))"),"") | N35: =IFERROR(__xludf.DUMMYFUNCTION("IF(ISBLANK(B35),"""",IF(ISDATE(B35),TEXT(B35,""yyyy""),""""))"),"")
J36: =IFERROR(__xludf.DUMMYFUNCTION("IF(ISBLANK(B36),"""",IF(ISDATE(B36),""X"",""""))"),"") | K36: =IFERROR(__xludf.DUMMYFUNCTION("IF(ISBLANK(B36),"""",IF(ISDATE(B36),H36,""""))"),"") | L36: =IFERROR(__xludf.DUMMYFUNCTION("IF(ISBLANK(B36),"""",IF(ISDATE(B36),TEXT(B36,""M""),""""))"),"") | M36: =IFERROR(__xludf.DUMMYFUNCTION("IF(L36="""","""",QUERY({'Dashboard-Dados'!$Y$2:$AA$13},""Select Col2 Where Col1=""&L36))"),"") | N36: =IFERROR(__xludf.DUMMYFUNCTION("IF(ISBLANK(B36),"""",IF(ISDATE(B36),TEXT(B36,""yyyy""),""""))"),"")
J37: =IFERROR(__xludf.DUMMYFUNCTION("IF(ISBLANK(B37),"""",IF(ISDATE(B37),""X"",""""))"),"") | K37: =IFERROR(__xludf.DUMMYFUNCTION("IF(ISBLANK(B37),"""",IF(ISDATE(B37),H37,""""))"),"") | L37: =IFERROR(__xludf.DUMMYFUNCTION("IF(ISBLANK(B37),"""",IF(ISDATE(B37),TEXT(B37,""M""),""""))"),"") | M37: =IFERROR(__xludf.DUMMYFUNCTION("IF(L37="""","""",QUERY({'Dashboard-Dados'!$Y$2:$AA$13},""Select Col2 Where Col1=""&L37))"),"") | N37: =IFERROR(__xludf.DUMMYFUNCTION("IF(ISBLANK(B37),"""",IF(ISDATE(B37),TEXT(B37,""yyyy""),""""))"),"")
J38: =IFERROR(__xludf.DUMMYFUNCTION("IF(ISBLANK(B38),"""",IF(ISDATE(B38),""X"",""""))"),"") | K38: =IFERROR(__xludf.DUMMYFUNCTION("IF(ISBLANK(B38),"""",IF(ISDATE(B38),H38,""""))"),"") | L38: =IFERROR(__xludf.DUMMYFUNCTION("IF(ISBLANK(B38),"""",IF(ISDATE(B38),TEXT(B38,""M""),""""))"),"") | M38: =IFERROR(__xludf.DUMMYFUNCTION("IF(L38="""","""",QUERY({'Dashboard-Dados'!$Y$2:$AA$13},""Select Col2 Where Col1=""&L38))"),"") | N38: =IFERROR(__xludf.DUMMYFUNCTION("IF(ISBLANK(B38),"""",IF(ISDATE(B38),TEXT(B38,""yyyy""),""""))"),"")
J39: =IFERROR(__xludf.DUMMYFUNCTION("IF(ISBLANK(B39),"""",IF(ISDATE(B39),""X"",""""))"),"") | K39: =IFERROR(__xludf.DUMMYFUNCTION("IF(ISBLANK(B39),"""",IF(ISDATE(B39),H39,""""))"),"") | L39: =IFERROR(__xludf.DUMMYFUNCTION("IF(ISBLANK(B39),"""",IF(ISDATE(B39),TEXT(B39,""M""),""""))"),"") | M39: =IFERROR(__xludf.DUMMYFUNCTION("IF(L39="""","""",QUERY({'Dashboard-Dados'!$Y$2:$AA$13},""Select Col2 Where Col1=""&L39))"),"") | N39: =IFERROR(__xludf.DUMMYFUNCTION("IF(ISBLANK(B39),"""",IF(ISDATE(B39),TEXT(B39,""yyyy""),""""))"),"")
J40: =IFERROR(__xludf.DUMMYFUNCTION("IF(ISBLANK(B40),"""",IF(ISDATE(B40),""X"",""""))"),"") | K40: =IFERROR(__xludf.DUMMYFUNCTION("IF(ISBLANK(B40),"""",IF(ISDATE(B40),H40,""""))"),"") | L40: =IFERROR(__xludf.DUMMYFUNCTION("IF(ISBLANK(B40),"""",IF(ISDATE(B40),TEXT(B40,""M""),""""))"),"") | M40: =IFERROR(__xludf.DUMMYFUNCTION("IF(L40="""","""",QUERY({'Dashboard-Dados'!$Y$2:$AA$13},""Select Col2 Where Col1=""&L40))"),"") | N40: =IFERROR(__xludf.DUMMYFUNCTION("IF(ISBLANK(B40),"""",IF(ISDATE(B40),TEXT(B40,""yyyy""),""""))"),"")
J41: =IFERROR(__xludf.DUMMYFUNCTION("IF(ISBLANK(B41),"""",IF(ISDATE(B41),""X"",""""))"),"") | K41: =IFERROR(__xludf.DUMMYFUNCTION("IF(ISBLANK(B41),"""",IF(ISDATE(B41),H41,""""))"),"") | L41: =IFERROR(__xludf.DUMMYFUNCTION("IF(ISBLANK(B41),"""",IF(ISDATE(B41),TEXT(B41,""M""),""""))"),"") | M41: =IFERROR(__xludf.DUMMYFUNCTION("IF(L41="""","""",QUERY({'Dashboard-Dados'!$Y$2:$AA$13},""Select Col2 Where Col1=""&L41))"),"") | N41: =IFERROR(__xludf.DUMMYFUNCTION("IF(ISBLANK(B41),"""",IF(ISDATE(B41),TEXT(B41,""yyyy""),""""))"),"")
J42: =IFERROR(__xludf.DUMMYFUNCTION("IF(ISBLANK(B42),"""",IF(ISDATE(B42),""X"",""""))"),"") | K42: =IFERROR(__xludf.DUMMYFUNCTION("IF(ISBLANK(B42),"""",IF(ISDATE(B42),H42,""""))"),"") | L42: =IFERROR(__xludf.DUMMYFUNCTION("IF(ISBLANK(B42),"""",IF(ISDATE(B42),TEXT(B42,""M""),""""))"),"") | M42: =IFERROR(__xludf.DUMMYFUNCTION("IF(L42="""","""",QUERY({'Dashboard-Dados'!$Y$2:$AA$13},""Select Col2 Where Col1=""&L42))"),"") | N42: =IFERROR(__xludf.DUMMYFUNCTION("IF(ISBLANK(B42),"""",IF(ISDATE(B42),TEXT(B42,""yyyy""),""""))"),"")
J43: =IFERROR(__xludf.DUMMYFUNCTION("IF(ISBLANK(B43),"""",IF(ISDATE(B43),""X"",""""))"),"") | K43: =IFERROR(__xludf.DUMMYFUNCTION("IF(ISBLANK(B43),"""",IF(ISDATE(B43),H43,""""))"),"") | L43: =IFERROR(__xludf.DUMMYFUNCTION("IF(ISBLANK(B43),"""",IF(ISDATE(B43),TEXT(B43,""M""),""""))"),"") | M43: =IFERROR(__xludf.DUMMYFUNCTION("IF(L43="""","""",QUERY({'Dashboard-Dados'!$Y$2:$AA$13},""Select Col2 Where Col1=""&L43))"),"") | N43: =IFERROR(__xludf.DUMMYFUNCTION("IF(ISBLANK(B43),"""",IF(ISDATE(B43),TEXT(B43,""yyyy""),""""))"),"")
J44: =IFERROR(__xludf.DUMMYFUNCTION("IF(ISBLANK(B44),"""",IF(ISDATE(B44),""X"",""""))"),"") | K44: =IFERROR(__xludf.DUMMYFUNCTION("IF(ISBLANK(B44),"""",IF(ISDATE(B44),H44,""""))"),"") | L44: =IFERROR(__xludf.DUMMYFUNCTION("IF(ISBLANK(B44),"""",IF(ISDATE(B44),TEXT(B44,""M""),""""))"),"") | M44: =IFERROR(__xludf.DUMMYFUNCTION("IF(L44="""","""",QUERY({'Dashboard-Dados'!$Y$2:$AA$13},""Select Col2 Where Col1=""&L44))"),"") | N44: =IFERROR(__xludf.DUMMYFUNCTION("IF(ISBLANK(B44),"""",IF(ISDATE(B44),TEXT(B44,""yyyy""),""""))"),"")
J45: =IFERROR(__xludf.DUMMYFUNCTION("IF(ISBLANK(B45),"""",IF(ISDATE(B45),""X"",""""))"),"") | K45: =IFERROR(__xludf.DUMMYFUNCTION("IF(ISBLANK(B45),"""",IF(ISDATE(B45),H45,""""))"),"") | L45: =IFERROR(__xludf.DUMMYFUNCTION("IF(ISBLANK(B45),"""",IF(ISDATE(B45),TEXT(B45,""M""),""""))"),"") | M45: =IFERROR(__xludf.DUMMYFUNCTION("IF(L45="""","""",QUERY({'Dashboard-Dados'!$Y$2:$AA$13},""Select Col2 Where Col1=""&L45))"),"") | N45: =IFERROR(__xludf.DUMMYFUNCTION("IF(ISBLANK(B45),"""",IF(ISDATE(B45),TEXT(B45,""yyyy""),""""))"),"")
J46: =IFERROR(__xludf.DUMMYFUNCTION("IF(ISBLANK(B46),"""",IF(ISDATE(B46),""X"",""""))"),"") | K46: =IFERROR(__xludf.DUMMYFUNCTION("IF(ISBLANK(B46),"""",IF(ISDATE(B46),H46,""""))"),"") | L46: =IFERROR(__xludf.DUMMYFUNCTION("IF(ISBLANK(B46),"""",IF(ISDATE(B46),TEXT(B46,""M""),""""))"),"") | M46: =IFERROR(__xludf.DUMMYFUNCTION("IF(L46="""","""",QUERY({'Dashboard-Dados'!$Y$2:$AA$13},""Select Col2 Where Col1=""&L46))"),"") | N46: =IFERROR(__xludf.DUMMYFUNCTION("IF(ISBLANK(B46),"""",IF(ISDATE(B46),TEXT(B46,""yyyy""),""""))"),"")
J47: =IFERROR(__xludf.DUMMYFUNCTION("IF(ISBLANK(B47),"""",IF(ISDATE(B47),""X"",""""))"),"") | K47: =IFERROR(__xludf.DUMMYFUNCTION("IF(ISBLANK(B47),"""",IF(ISDATE(B47),H47,""""))"),"") | L47: =IFERROR(__xludf.DUMMYFUNCTION("IF(ISBLANK(B47),"""",IF(ISDATE(B47),TEXT(B47,""M""),""""))"),"") | M47: =IFERROR(__xludf.DUMMYFUNCTION("IF(L47="""","""",QUERY({'Dashboard-Dados'!$Y$2:$AA$13},""Select Col2 Where Col1=""&L47))"),"") | N47: =IFERROR(__xludf.DUMMYFUNCTION("IF(ISBLANK(B47),"""",IF(ISDATE(B47),TEXT(B47,""yyyy""),""""))"),"")
J48: =IFERROR(__xludf.DUMMYFUNCTION("IF(ISBLANK(B48),"""",IF(ISDATE(B48),""X"",""""))"),"") | K48: =IFERROR(__xludf.DUMMYFUNCTION("IF(ISBLANK(B48),"""",IF(ISDATE(B48),H48,""""))"),"") | L48: =IFERROR(__xludf.DUMMYFUNCTION("IF(ISBLANK(B48),"""",IF(ISDATE(B48),TEXT(B48,""M""),""""))"),"") | M48: =IFERROR(__xludf.DUMMYFUNCTION("IF(L48="""","""",QUERY({'Dashboard-Dados'!$Y$2:$AA$13},""Select Col2 Where Col1=""&L48))"),"") | N48: =IFERROR(__xludf.DUMMYFUNCTION("IF(ISBLANK(B48),"""",IF(ISDATE(B48),TEXT(B48,""yyyy""),""""))"),"")
J49: =IFERROR(__xludf.DUMMYFUNCTION("IF(ISBLANK(B49),"""",IF(ISDATE(B49),""X"",""""))"),"") | K49: =IFERROR(__xludf.DUMMYFUNCTION("IF(ISBLANK(B49),"""",IF(ISDATE(B49),H49,""""))"),"") | L49: =IFERROR(__xludf.DUMMYFUNCTION("IF(ISBLANK(B49),"""",IF(ISDATE(B49),TEXT(B49,""M""),""""))"),"") | M49: =IFERROR(__xludf.DUMMYFUNCTION("IF(L49="""","""",QUERY({'Dashboard-Dados'!$Y$2:$AA$13},""Select Col2 Where Col1=""&L49))"),"") | N49: =IFERROR(__xludf.DUMMYFUNCTION("IF(ISBLANK(B49),"""",IF(ISDATE(B49),TEXT(B49,""yyyy""),""""))"),"")
J50: =IFERROR(__xludf.DUMMYFUNCTION("IF(ISBLANK(B50),"""",IF(ISDATE(B50),""X"",""""))"),"") | K50: =IFERROR(__xludf.DUMMYFUNCTION("IF(ISBLANK(B50),"""",IF(ISDATE(B50),H50,""""))"),"") | L50: =IFERROR(__xludf.DUMMYFUNCTION("IF(ISBLANK(B50),"""",IF(ISDATE(B50),TEXT(B50,""M""),""""))"),"") | M50: =IFERROR(__xludf.DUMMYFUNCTION("IF(L50="""","""",QUERY({'Dashboard-Dados'!$Y$2:$AA$13},""Select Col2 Where Col1=""&L50))"),"") | N50: =IFERROR(__xludf.DUMMYFUNCTION("IF(ISBLANK(B50),"""",IF(ISDATE(B50),TEXT(B50,""yyyy""),""""))"),"")
J51: =IFERROR(__xludf.DUMMYFUNCTION("IF(ISBLANK(B51),"""",IF(ISDATE(B51),""X"",""""))"),"") | K51: =IFERROR(__xludf.DUMMYFUNCTION("IF(ISBLANK(B51),"""",IF(ISDATE(B51),H51,""""))"),"") | L51: =IFERROR(__xludf.DUMMYFUNCTION("IF(ISBLANK(B51),"""",IF(ISDATE(B51),TEXT(B51,""M""),""""))"),"") | M51: =IFERROR(__xludf.DUMMYFUNCTION("IF(L51="""","""",QUERY({'Dashboard-Dados'!$Y$2:$AA$13},""Select Col2 Where Col1=""&L51))"),"") | N51: =IFERROR(__xludf.DUMMYFUNCTION("IF(ISBLANK(B51),"""",IF(ISDATE(B51),TEXT(B51,""yyyy""),""""))"),"")
J52: =IFERROR(__xludf.DUMMYFUNCTION("IF(ISBLANK(B52),"""",IF(ISDATE(B52),""X"",""""))"),"") | K52: =IFERROR(__xludf.DUMMYFUNCTION("IF(ISBLANK(B52),"""",IF(ISDATE(B52),H52,""""))"),"") | L52: =IFERROR(__xludf.DUMMYFUNCTION("IF(ISBLANK(B52),"""",IF(ISDATE(B52),TEXT(B52,""M""),""""))"),"") | M52: =IFERROR(__xludf.DUMMYFUNCTION("IF(L52="""","""",QUERY({'Dashboard-Dados'!$Y$2:$AA$13},""Select Col2 Where Col1=""&L52))"),"") | N52: =IFERROR(__xludf.DUMMYFUNCTION("IF(ISBLANK(B52),"""",IF(ISDATE(B52),TEXT(B52,""yyyy""),""""))"),"")
J53: =IFERROR(__xludf.DUMMYFUNCTION("IF(ISBLANK(B53),"""",IF(ISDATE(B53),""X"",""""))"),"") | K53: =IFERROR(__xludf.DUMMYFUNCTION("IF(ISBLANK(B53),"""",IF(ISDATE(B53),H53,""""))"),"") | L53: =IFERROR(__xludf.DUMMYFUNCTION("IF(ISBLANK(B53),"""",IF(ISDATE(B53),TEXT(B53,""M""),""""))"),"") | M53: =IFERROR(__xludf.DUMMYFUNCTION("IF(L53="""","""",QUERY({'Dashboard-Dados'!$Y$2:$AA$13},""Select Col2 Where Col1=""&L53))"),"") | N53: =IFERROR(__xludf.DUMMYFUNCTION("IF(ISBLANK(B53),"""",IF(ISDATE(B53),TEXT(B53,""yyyy""),""""))"),"")
J54: =IFERROR(__xludf.DUMMYFUNCTION("IF(ISBLANK(B54),"""",IF(ISDATE(B54),""X"",""""))"),"") | K54: =IFERROR(__xludf.DUMMYFUNCTION("IF(ISBLANK(B54),"""",IF(ISDATE(B54),H54,""""))"),"") | L54: =IFERROR(__xludf.DUMMYFUNCTION("IF(ISBLANK(B54),"""",IF(ISDATE(B54),TEXT(B54,""M""),""""))"),"") | M54: =IFERROR(__xludf.DUMMYFUNCTION("IF(L54="""","""",QUERY({'Dashboard-Dados'!$Y$2:$AA$13},""Select Col2 Where Col1=""&L54))"),"") | N54: =IFERROR(__xludf.DUMMYFUNCTION("IF(ISBLANK(B54),"""",IF(ISDATE(B54),TEXT(B54,""yyyy""),""""))"),"")
J55: =IFERROR(__xludf.DUMMYFUNCTION("IF(ISBLANK(B55),"""",IF(ISDATE(B55),""X"",""""))"),"") | K55: =IFERROR(__xludf.DUMMYFUNCTION("IF(ISBLANK(B55),"""",IF(ISDATE(B55),H55,""""))"),"") | L55: =IFERROR(__xludf.DUMMYFUNCTION("IF(ISBLANK(B55),"""",IF(ISDATE(B55),TEXT(B55,""M""),""""))"),"") | M55: =IFERROR(__xludf.DUMMYFUNCTION("IF(L55="""","""",QUERY({'Dashboard-Dados'!$Y$2:$AA$13},""Select Col2 Where Col1=""&L55))"),"") | N55: =IFERROR(__xludf.DUMMYFUNCTION("IF(ISBLANK(B55),"""",IF(ISDATE(B55),TEXT(B55,""yyyy""),""""))"),"")
J56: =IFERROR(__xludf.DUMMYFUNCTION("IF(ISBLANK(B56),"""",IF(ISDATE(B56),""X"",""""))"),"") | K56: =IFERROR(__xludf.DUMMYFUNCTION("IF(ISBLANK(B56),"""",IF(ISDATE(B56),H56,""""))"),"") | L56: =IFERROR(__xludf.DUMMYFUNCTION("IF(ISBLANK(B56),"""",IF(ISDATE(B56),TEXT(B56,""M""),""""))"),"") | M56: =IFERROR(__xludf.DUMMYFUNCTION("IF(L56="""","""",QUERY({'Dashboard-Dados'!$Y$2:$AA$13},""Select Col2 Where Col1=""&L56))"),"") | N56: =IFERROR(__xludf.DUMMYFUNCTION("IF(ISBLANK(B56),"""",IF(ISDATE(B56),TEXT(B56,""yyyy""),""""))"),"")
J57: =IFERROR(__xludf.DUMMYFUNCTION("IF(ISBLANK(B57),"""",IF(ISDATE(B57),""X"",""""))"),"") | K57: =IFERROR(__xludf.DUMMYFUNCTION("IF(ISBLANK(B57),"""",IF(ISDATE(B57),H57,""""))"),"") | L57: =IFERROR(__xludf.DUMMYFUNCTION("IF(ISBLANK(B57),"""",IF(ISDATE(B57),TEXT(B57,""M""),""""))"),"") | M57: =IFERROR(__xludf.DUMMYFUNCTION("IF(L57="""","""",QUERY({'Dashboard-Dados'!$Y$2:$AA$13},""Select Col2 Where Col1=""&L57))"),"") | N57: =IFERROR(__xludf.DUMMYFUNCTION("IF(ISBLANK(B57),"""",IF(ISDATE(B57),TEXT(B57,""yyyy""),""""))"),"")
J58: =IFERROR(__xludf.DUMMYFUNCTION("IF(ISBLANK(B58),"""",IF(ISDATE(B58),""X"",""""))"),"") | K58: =IFERROR(__xludf.DUMMYFUNCTION("IF(ISBLANK(B58),"""",IF(ISDATE(B58),H58,""""))"),"") | L58: =IFERROR(__xludf.DUMMYFUNCTION("IF(ISBLANK(B58),"""",IF(ISDATE(B58),TEXT(B58,""M""),""""))"),"") | M58: =IFERROR(__xludf.DUMMYFUNCTION("IF(L58="""","""",QUERY({'Dashboard-Dados'!$Y$2:$AA$13},""Select Col2 Where Col1=""&L58))"),"") | N58: =IFERROR(__xludf.DUMMYFUNCTION("IF(ISBLANK(B58),"""",IF(ISDATE(B58),TEXT(B58,""yyyy""),""""))"),"")
J59: =IFERROR(__xludf.DUMMYFUNCTION("IF(ISBLANK(B59),"""",IF(ISDATE(B59),""X"",""""))"),"") | K59: =IFERROR(__xludf.DUMMYFUNCTION("IF(ISBLANK(B59),"""",IF(ISDATE(B59),H59,""""))"),"") | L59: =IFERROR(__xludf.DUMMYFUNCTION("IF(ISBLANK(B59),"""",IF(ISDATE(B59),TEXT(B59,""M""),""""))"),"") | M59: =IFERROR(__xludf.DUMMYFUNCTION("IF(L59="""","""",QUERY({'Dashboard-Dados'!$Y$2:$AA$13},""Select Col2 Where Col1=""&L59))"),"") | N59: =IFERROR(__xludf.DUMMYFUNCTION("IF(ISBLANK(B59),"""",IF(ISDATE(B59),TEXT(B59,""yyyy""),""""))"),"")
J60: =IFERROR(__xludf.DUMMYFUNCTION("IF(ISBLANK(B60),"""",IF(ISDATE(B60),""X"",""""))"),"") | K60: =IFERROR(__xludf.DUMMYFUNCTION("IF(ISBLANK(B60),"""",IF(ISDATE(B60),H60,""""))"),"") | L60: =IFERROR(__xludf.DUMMYFUNCTION("IF(ISBLANK(B60),"""",IF(ISDATE(B60),TEXT(B60,""M""),""""))"),"") | M60: =IFERROR(__xludf.DUMMYFUNCTION("IF(L60="""","""",QUERY({'Dashboard-Dados'!$Y$2:$AA$13},""Select Col2 Where Col1=""&L60))"),"") | N60: =IFERROR(__xludf.DUMMYFUNCTION("IF(ISBLANK(B60),"""",IF(ISDATE(B60),TEXT(B60,""yyyy""),""""))"),"")
J61: =IFERROR(__xludf.DUMMYFUNCTION("IF(ISBLANK(B61),"""",IF(ISDATE(B61),""X"",""""))"),"") | K61: =IFERROR(__xludf.DUMMYFUNCTION("IF(ISBLANK(B61),"""",IF(ISDATE(B61),H61,""""))"),"") | L61: =IFERROR(__xludf.DUMMYFUNCTION("IF(ISBLANK(B61),"""",IF(ISDATE(B61),TEXT(B61,""M""),""""))"),"") | M61: =IFERROR(__xludf.DUMMYFUNCTION("IF(L61="""","""",QUERY({'Dashboard-Dados'!$Y$2:$AA$13},""Select Col2 Where Col1=""&L61))"),"") | N61: =IFERROR(__xludf.DUMMYFUNCTION("IF(ISBLANK(B61),"""",IF(ISDATE(B61),TEXT(B61,""yyyy""),""""))"),"")
J62: =IFERROR(__xludf.DUMMYFUNCTION("IF(ISBLANK(B62),"""",IF(ISDATE(B62),""X"",""""))"),"") | K62: =IFERROR(__xludf.DUMMYFUNCTION("IF(ISBLANK(B62),"""",IF(ISDATE(B62),H62,""""))"),"") | L62: =IFERROR(__xludf.DUMMYFUNCTION("IF(ISBLANK(B62),"""",IF(ISDATE(B62),TEXT(B62,""M""),""""))"),"") | M62: =IFERROR(__xludf.DUMMYFUNCTION("IF(L62="""","""",QUERY({'Dashboard-Dados'!$Y$2:$AA$13},""Select Col2 Where Col1=""&L62))"),"") | N62: =IFERROR(__xludf.DUMMYFUNCTION("IF(ISBLANK(B62),"""",IF(ISDATE(B62),TEXT(B62,""yyyy""),""""))"),"")
J63: =IFERROR(__xludf.DUMMYFUNCTION("IF(ISBLANK(B63),"""",IF(ISDATE(B63),""X"",""""))"),"") | K63: =IFERROR(__xludf.DUMMYFUNCTION("IF(ISBLANK(B63),"""",IF(ISDATE(B63),H63,""""))"),"") | L63: =IFERROR(__xludf.DUMMYFUNCTION("IF(ISBLANK(B63),"""",IF(ISDATE(B63),TEXT(B63,""M""),""""))"),"") | M63: =IFERROR(__xludf.DUMMYFUNCTION("IF(L63="""","""",QUERY({'Dashboard-Dados'!$Y$2:$AA$13},""Select Col2 Where Col1=""&L63))"),"") | N63: =IFERROR(__xludf.DUMMYFUNCTION("IF(ISBLANK(B63),"""",IF(ISDATE(B63),TEXT(B63,""yyyy""),""""))"),"")
J64: =IFERROR(__xludf.DUMMYFUNCTION("IF(ISBLANK(B64),"""",IF(ISDATE(B64),""X"",""""))"),"") | K64: =IFERROR(__xludf.DUMMYFUNCTION("IF(ISBLANK(B64),"""",IF(ISDATE(B64),H64,""""))"),"") | L64: =IFERROR(__xludf.DUMMYFUNCTION("IF(ISBLANK(B64),"""",IF(ISDATE(B64),TEXT(B64,""M""),""""))"),"") | M64: =IFERROR(__xludf.DUMMYFUNCTION("IF(L64="""","""",QUERY({'Dashboard-Dados'!$Y$2:$AA$13},""Select Col2 Where Col1=""&L64))"),"") | N64: =IFERROR(__xludf.DUMMYFUNCTION("IF(ISBLANK(B64),"""",IF(ISDATE(B64),TEXT(B64,""yyyy""),""""))"),"")
J65: =IFERROR(__xludf.DUMMYFUNCTION("IF(ISBLANK(B65),"""",IF(ISDATE(B65),""X"",""""))"),"") | K65: =IFERROR(__xludf.DUMMYFUNCTION("IF(ISBLANK(B65),"""",IF(ISDATE(B65),H65,""""))"),"") | L65: =IFERROR(__xludf.DUMMYFUNCTION("IF(ISBLANK(B65),"""",IF(ISDATE(B65),TEXT(B65,""M""),""""))"),"") | M65: =IFERROR(__xludf.DUMMYFUNCTION("IF(L65="""","""",QUERY({'Dashboard-Dados'!$Y$2:$AA$13},""Select Col2 Where Col1=""&L65))"),"") | N65: =IFERROR(__xludf.DUMMYFUNCTION("IF(ISBLANK(B65),"""",IF(ISDATE(B65),TEXT(B65,""yyyy""),""""))"),"")
J66: =IFERROR(__xludf.DUMMYFUNCTION("IF(ISBLANK(B66),"""",IF(ISDATE(B66),""X"",""""))"),"") | K66: =IFERROR(__xludf.DUMMYFUNCTION("IF(ISBLANK(B66),"""",IF(ISDATE(B66),H66,""""))"),"") | L66: =IFERROR(__xludf.DUMMYFUNCTION("IF(ISBLANK(B66),"""",IF(ISDATE(B66),TEXT(B66,""M""),""""))"),"") | M66: =IFERROR(__xludf.DUMMYFUNCTION("IF(L66="""","""",QUERY({'Dashboard-Dados'!$Y$2:$AA$13},""Select Col2 Where Col1=""&L66))"),"") | N66: =IFERROR(__xludf.DUMMYFUNCTION("IF(ISBLANK(B66),"""",IF(ISDATE(B66),TEXT(B66,""yyyy""),""""))"),"")
J67: =IFERROR(__xludf.DUMMYFUNCTION("IF(ISBLANK(B67),"""",IF(ISDATE(B67),""X"",""""))"),"") | K67: =IFERROR(__xludf.DUMMYFUNCTION("IF(ISBLANK(B67),"""",IF(ISDATE(B67),H67,""""))"),"") | L67: =IFERROR(__xludf.DUMMYFUNCTION("IF(ISBLANK(B67),"""",IF(ISDATE(B67),TEXT(B67,""M""),""""))"),"") | M67: =IFERROR(__xludf.DUMMYFUNCTION("IF(L67="""","""",QUERY({'Dashboard-Dados'!$Y$2:$AA$13},""Select Col2 Where Col1=""&L67))"),"") | N67: =IFERROR(__xludf.DUMMYFUNCTION("IF(ISBLANK(B67),"""",IF(ISDATE(B67),TEXT(B67,""yyyy""),""""))"),"")
J68: =IFERROR(__xludf.DUMMYFUNCTION("IF(ISBLANK(B68),"""",IF(ISDATE(B68),""X"",""""))"),"") | K68: =IFERROR(__xludf.DUMMYFUNCTION("IF(ISBLANK(B68),"""",IF(ISDATE(B68),H68,""""))"),"") | L68: =IFERROR(__xludf.DUMMYFUNCTION("IF(ISBLANK(B68),"""",IF(ISDATE(B68),TEXT(B68,""M""),""""))"),"") | M68: =IFERROR(__xludf.DUMMYFUNCTION("IF(L68="""","""",QUERY({'Dashboard-Dados'!$Y$2:$AA$13},""Select Col2 Where Col1=""&L68))"),"") | N68: =IFERROR(__xludf.DUMMYFUNCTION("IF(ISBLANK(B68),"""",IF(ISDATE(B68),TEXT(B68,""yyyy""),""""))"),"")
J69: =IFERROR(__xludf.DUMMYFUNCTION("IF(ISBLANK(B69),"""",IF(ISDATE(B69),""X"",""""))"),"") | K69: =IFERROR(__xludf.DUMMYFUNCTION("IF(ISBLANK(B69),"""",IF(ISDATE(B69),H69,""""))"),"") | L69: =IFERROR(__xludf.DUMMYFUNCTION("IF(ISBLANK(B69),"""",IF(ISDATE(B69),TEXT(B69,""M""),""""))"),"") | M69: =IFERROR(__xludf.DUMMYFUNCTION("IF(L69="""","""",QUERY({'Dashboard-Dados'!$Y$2:$AA$13},""Select Col2 Where Col1=""&L69))"),"") | N69: =IFERROR(__xludf.DUMMYFUNCTION("IF(ISBLANK(B69),"""",IF(ISDATE(B69),TEXT(B69,""yyyy""),""""))"),"")
J70: =IFERROR(__xludf.DUMMYFUNCTION("IF(ISBLANK(B70),"""",IF(ISDATE(B70),""X"",""""))"),"") | K70: =IFERROR(__xludf.DUMMYFUNCTION("IF(ISBLANK(B70),"""",IF(ISDATE(B70),H70,""""))"),"") | L70: =IFERROR(__xludf.DUMMYFUNCTION("IF(ISBLANK(B70),"""",IF(ISDATE(B70),TEXT(B70,""M""),""""))"),"") | M70: =IFERROR(__xludf.DUMMYFUNCTION("IF(L70="""","""",QUERY({'Dashboard-Dados'!$Y$2:$AA$13},""Select Col2 Where Col1=""&L70))"),"") | N70: =IFERROR(__xludf.DUMMYFUNCTION("IF(ISBLANK(B70),"""",IF(ISDATE(B70),TEXT(B70,""yyyy""),""""))"),"")
J71: =IFERROR(__xludf.DUMMYFUNCTION("IF(ISBLANK(B71),"""",IF(ISDATE(B71),""X"",""""))"),"") | K71: =IFERROR(__xludf.DUMMYFUNCTION("IF(ISBLANK(B71),"""",IF(ISDATE(B71),H71,""""))"),"") | L71: =IFERROR(__xludf.DUMMYFUNCTION("IF(ISBLANK(B71),"""",IF(ISDATE(B71),TEXT(B71,""M""),""""))"),"") | M71: =IFERROR(__xludf.DUMMYFUNCTION("IF(L71="""","""",QUERY({'Dashboard-Dados'!$Y$2:$AA$13},""Select Col2 Where Col1=""&L71))"),"") | N71: =IFERROR(__xludf.DUMMYFUNCTION("IF(ISBLANK(B71),"""",IF(ISDATE(B71),TEXT(B71,""yyyy""),""""))"),"")
J72: =IFERROR(__xludf.DUMMYFUNCTION("IF(ISBLANK(B72),"""",IF(ISDATE(B72),""X"",""""))"),"") | K72: =IFERROR(__xludf.DUMMYFUNCTION("IF(ISBLANK(B72),"""",IF(ISDATE(B72),H72,""""))"),"") | L72: =IFERROR(__xludf.DUMMYFUNCTION("IF(ISBLANK(B72),"""",IF(ISDATE(B72),TEXT(B72,""M""),""""))"),"") | M72: =IFERROR(__xludf.DUMMYFUNCTION("IF(L72="""","""",QUERY({'Dashboard-Dados'!$Y$2:$AA$13},""Select Col2 Where Col1=""&L72))"),"") | N72: =IFERROR(__xludf.DUMMYFUNCTION("IF(ISBLANK(B72),"""",IF(ISDATE(B72),TEXT(B72,""yyyy""),""""))"),"")
J73: =IFERROR(__xludf.DUMMYFUNCTION("IF(ISBLANK(B73),"""",IF(ISDATE(B73),""X"",""""))"),"") | K73: =IFERROR(__xludf.DUMMYFUNCTION("IF(ISBLANK(B73),"""",IF(ISDATE(B73),H73,""""))"),"") | L73: =IFERROR(__xludf.DUMMYFUNCTION("IF(ISBLANK(B73),"""",IF(ISDATE(B73),TEXT(B73,""M""),""""))"),"") | M73: =IFERROR(__xludf.DUMMYFUNCTION("IF(L73="""","""",QUERY({'Dashboard-Dados'!$Y$2:$AA$13},""Select Col2 Where Col1=""&L73))"),"") | N73: =IFERROR(__xludf.DUMMYFUNCTION("IF(ISBLANK(B73),"""",IF(ISDATE(B73),TEXT(B73,""yyyy""),""""))"),"")
J74: =IFERROR(__xludf.DUMMYFUNCTION("IF(ISBLANK(B74),"""",IF(ISDATE(B74),""X"",""""))"),"") | K74: =IFERROR(__xludf.DUMMYFUNCTION("IF(ISBLANK(B74),"""",IF(ISDATE(B74),H74,""""))"),"") | L74: =IFERROR(__xludf.DUMMYFUNCTION("IF(ISBLANK(B74),"""",IF(ISDATE(B74),TEXT(B74,""M""),""""))"),"") | M74: =IFERROR(__xludf.DUMMYFUNCTION("IF(L74="""","""",QUERY({'Dashboard-Dados'!$Y$2:$AA$13},""Select Col2 Where Col1=""&L74))"),"") | N74: =IFERROR(__xludf.DUMMYFUNCTION("IF(ISBLANK(B74),"""",IF(ISDATE(B74),TEXT(B74,""yyyy""),""""))"),"")
J75: =IFERROR(__xludf.DUMMYFUNCTION("IF(ISBLANK(B75),"""",IF(ISDATE(B75),""X"",""""))"),"") | K75: =IFERROR(__xludf.DUMMYFUNCTION("IF(ISBLANK(B75),"""",IF(ISDATE(B75),H75,""""))"),"") | L75: =IFERROR(__xludf.DUMMYFUNCTION("IF(ISBLANK(B75),"""",IF(ISDATE(B75),TEXT(B75,""M""),""""))"),"") | M75: =IFERROR(__xludf.DUMMYFUNCTION("IF(L75="""","""",QUERY({'Dashboard-Dados'!$Y$2:$AA$13},""Select Col2 Where Col1=""&L75))"),"") | N75: =IFERROR(__xludf.DUMMYFUNCTION("IF(ISBLANK(B75),"""",IF(ISDATE(B75),TEXT(B75,""yyyy""),""""))"),"")
J76: =IFERROR(__xludf.DUMMYFUNCTION("IF(ISBLANK(B76),"""",IF(ISDATE(B76),""X"",""""))"),"") | K76: =IFERROR(__xludf.DUMMYFUNCTION("IF(ISBLANK(B76),"""",IF(ISDATE(B76),H76,""""))"),"") | L76: =IFERROR(__xludf.DUMMYFUNCTION("IF(ISBLANK(B76),"""",IF(ISDATE(B76),TEXT(B76,""M""),""""))"),"") | M76: =IFERROR(__xludf.DUMMYFUNCTION("IF(L76="""","""",QUERY({'Dashboard-Dados'!$Y$2:$AA$13},""Select Col2 Where Col1=""&L76))"),"") | N76: =IFERROR(__xludf.DUMMYFUNCTION("IF(ISBLANK(B76),"""",IF(ISDATE(B76),TEXT(B76,""yyyy""),""""))"),"")
J77: =IFERROR(__xludf.DUMMYFUNCTION("IF(ISBLANK(B77),"""",IF(ISDATE(B77),""X"",""""))"),"") | K77: =IFERROR(__xludf.DUMMYFUNCTION("IF(ISBLANK(B77),"""",IF(ISDATE(B77),H77,""""))"),"") | L77: =IFERROR(__xludf.DUMMYFUNCTION("IF(ISBLANK(B77),"""",IF(ISDATE(B77),TEXT(B77,""M""),""""))"),"") | M77: =IFERROR(__xludf.DUMMYFUNCTION("IF(L77="""","""",QUERY({'Dashboard-Dados'!$Y$2:$AA$13},""Select Col2 Where Col1=""&L77))"),"") | N77: =IFERROR(__xludf.DUMMYFUNCTION("IF(ISBLANK(B77),"""",IF(ISDATE(B77),TEXT(B77,""yyyy""),""""))"),"")
J78: =IFERROR(__xludf.DUMMYFUNCTION("IF(ISBLANK(B78),"""",IF(ISDATE(B78),""X"",""""))"),"") | K78: =IFERROR(__xludf.DUMMYFUNCTION("IF(ISBLANK(B78),"""",IF(ISDATE(B78),H78,""""))"),"") | L78: =IFERROR(__xludf.DUMMYFUNCTION("IF(ISBLANK(B78),"""",IF(ISDATE(B78),TEXT(B78,""M""),""""))"),"") | M78: =IFERROR(__xludf.DUMMYFUNCTION("IF(L78="""","""",QUERY({'Dashboard-Dados'!$Y$2:$AA$13},""Select Col2 Where Col1=""&L78))"),"") | N78: =IFERROR(__xludf.DUMMYFUNCTION("IF(ISBLANK(B78),"""",IF(ISDATE(B78),TEXT(B78,""yyyy""),""""))"),"")
J79: =IFERROR(__xludf.DUMMYFUNCTION("IF(ISBLANK(B79),"""",IF(ISDATE(B79),""X"",""""))"),"") | K79: =IFERROR(__xludf.DUMMYFUNCTION("IF(ISBLANK(B79),"""",IF(ISDATE(B79),H79,""""))"),"") | L79: =IFERROR(__xludf.DUMMYFUNCTION("IF(ISBLANK(B79),"""",IF(ISDATE(B79),TEXT(B79,""M""),""""))"),"") | M79: =IFERROR(__xludf.DUMMYFUNCTION("IF(L79="""","""",QUERY({'Dashboard-Dados'!$Y$2:$AA$13},""Select Col2 Where Col1=""&L79))"),"") | N79: =IFERROR(__xludf.DUMMYFUNCTION("IF(ISBLANK(B79),"""",IF(ISDATE(B79),TEXT(B79,""yyyy""),""""))"),"")
J80: =IFERROR(__xludf.DUMMYFUNCTION("IF(ISBLANK(B80),"""",IF(ISDATE(B80),""X"",""""))"),"") | K80: =IFERROR(__xludf.DUMMYFUNCTION("IF(ISBLANK(B80),"""",IF(ISDATE(B80),H80,""""))"),"") | L80: =IFERROR(__xludf.DUMMYFUNCTION("IF(ISBLANK(B80),"""",IF(ISDATE(B80),TEXT(B80,""M""),""""))"),"") | M80: =IFERROR(__xludf.DUMMYFUNCTION("IF(L80="""","""",QUERY({'Dashboard-Dados'!$Y$2:$AA$13},""Select Col2 Where Col1=""&L80))"),"") | N80: =IFERROR(__xludf.DUMMYFUNCTION("IF(ISBLANK(B80),"""",IF(ISDATE(B80),TEXT(B80,""yyyy""),""""))"),"")
J81: =IFERROR(__xludf.DUMMYFUNCTION("IF(ISBLANK(B81),"""",IF(ISDATE(B81),""X"",""""))"),"") | K81: =IFERROR(__xludf.DUMMYFUNCTION("IF(ISBLANK(B81),"""",IF(ISDATE(B81),H81,""""))"),"") | L81: =IFERROR(__xludf.DUMMYFUNCTION("IF(ISBLANK(B81),"""",IF(ISDATE(B81),TEXT(B81,""M""),""""))"),"") | M81: =IFERROR(__xludf.DUMMYFUNCTION("IF(L81="""","""",QUERY({'Dashboard-Dados'!$Y$2:$AA$13},""Select Col2 Where Col1=""&L81))"),"") | N81: =IFERROR(__xludf.DUMMYFUNCTION("IF(ISBLANK(B81),"""",IF(ISDATE(B81),TEXT(B81,""yyyy""),""""))"),"")
J82: =IFERROR(__xludf.DUMMYFUNCTION("IF(ISBLANK(B82),"""",IF(ISDATE(B82),""X"",""""))"),"") | K82: =IFERROR(__xludf.DUMMYFUNCTION("IF(ISBLANK(B82),"""",IF(ISDATE(B82),H82,""""))"),"") | L82: =IFERROR(__xludf.DUMMYFUNCTION("IF(ISBLANK(B82),"""",IF(ISDATE(B82),TEXT(B82,""M""),""""))"),"") | M82: =IFERROR(__xludf.DUMMYFUNCTION("IF(L82="""","""",QUERY({'Dashboard-Dados'!$Y$2:$AA$13},""Select Col2 Where Col1=""&L82))"),"") | N82: =IFERROR(__xludf.DUMMYFUNCTION("IF(ISBLANK(B82),"""",IF(ISDATE(B82),TEXT(B82,""yyyy""),""""))"),"")
J83: =IFERROR(__xludf.DUMMYFUNCTION("IF(ISBLANK(B83),"""",IF(ISDATE(B83),""X"",""""))"),"") | K83: =IFERROR(__xludf.DUMMYFUNCTION("IF(ISBLANK(B83),"""",IF(ISDATE(B83),H83,""""))"),"") | L83: =IFERROR(__xludf.DUMMYFUNCTION("IF(ISBLANK(B83),"""",IF(ISDATE(B83),TEXT(B83,""M""),""""))"),"") | M83: =IFERROR(__xludf.DUMMYFUNCTION("IF(L83="""","""",QUERY({'Dashboard-Dados'!$Y$2:$AA$13},""Select Col2 Where Col1=""&L83))"),"") | N83: =IFERROR(__xludf.DUMMYFUNCTION("IF(ISBLANK(B83),"""",IF(ISDATE(B83),TEXT(B83,""yyyy""),""""))"),"")
J84: =IFERROR(__xludf.DUMMYFUNCTION("IF(ISBLANK(B84),"""",IF(ISDATE(B84),""X"",""""))"),"") | K84: =IFERROR(__xludf.DUMMYFUNCTION("IF(ISBLANK(B84),"""",IF(ISDATE(B84),H84,""""))"),"") | L84: =IFERROR(__xludf.DUMMYFUNCTION("IF(ISBLANK(B84),"""",IF(ISDATE(B84),TEXT(B84,""M""),""""))"),"") | M84: =IFERROR(__xludf.DUMMYFUNCTION("IF(L84="""","""",QUERY({'Dashboard-Dados'!$Y$2:$AA$13},""Select Col2 Where Col1=""&L84))"),"") | N84: =IFERROR(__xludf.DUMMYFUNCTION("IF(ISBLANK(B84),"""",IF(ISDATE(B84),TEXT(B84,""yyyy""),""""))"),"")
J85: =IFERROR(__xludf.DUMMYFUNCTION("IF(ISBLANK(B85),"""",IF(ISDATE(B85),""X"",""""))"),"") | K85: =IFERROR(__xludf.DUMMYFUNCTION("IF(ISBLANK(B85),"""",IF(ISDATE(B85),H85,""""))"),"") | L85: =IFERROR(__xludf.DUMMYFUNCTION("IF(ISBLANK(B85),"""",IF(ISDATE(B85),TEXT(B85,""M""),""""))"),"") | M85: =IFERROR(__xludf.DUMMYFUNCTION("IF(L85="""","""",QUERY({'Dashboard-Dados'!$Y$2:$AA$13},""Select Col2 Where Col1=""&L85))"),"") | N85: =IFERROR(__xludf.DUMMYFUNCTION("IF(ISBLANK(B85),"""",IF(ISDATE(B85),TEXT(B85,""yyyy""),""""))"),"")
J86: =IFERROR(__xludf.DUMMYFUNCTION("IF(ISBLANK(B86),"""",IF(ISDATE(B86),""X"",""""))"),"") | K86: =IFERROR(__xludf.DUMMYFUNCTION("IF(ISBLANK(B86),"""",IF(ISDATE(B86),H86,""""))"),"") | L86: =IFERROR(__xludf.DUMMYFUNCTION("IF(ISBLANK(B86),"""",IF(ISDATE(B86),TEXT(B86,""M""),""""))"),"") | M86: =IFERROR(__xludf.DUMMYFUNCTION("IF(L86="""","""",QUERY({'Dashboard-Dados'!$Y$2:$AA$13},""Select Col2 Where Col1=""&L86))"),"") | N86: =IFERROR(__xludf.DUMMYFUNCTION("IF(ISBLANK(B86),"""",IF(ISDATE(B86),TEXT(B86,""yyyy""),""""))"),"")
J87: =IFERROR(__xludf.DUMMYFUNCTION("IF(ISBLANK(B87),"""",IF(ISDATE(B87),""X"",""""))"),"") | K87: =IFERROR(__xludf.DUMMYFUNCTION("IF(ISBLANK(B87),"""",IF(ISDATE(B87),H87,""""))"),"") | L87: =IFERROR(__xludf.DUMMYFUNCTION("IF(ISBLANK(B87),"""",IF(ISDATE(B87),TEXT(B87,""M""),""""))"),"") | M87: =IFERROR(__xludf.DUMMYFUNCTION("IF(L87="""","""",QUERY({'Dashboard-Dados'!$Y$2:$AA$13},""Select Col2 Where Col1=""&L87))"),"") | N87: =IFERROR(__xludf.DUMMYFUNCTION("IF(ISBLANK(B87),"""",IF(ISDATE(B87),TEXT(B87,""yyyy""),""""))"),"")
J88: =IFERROR(__xludf.DUMMYFUNCTION("IF(ISBLANK(B88),"""",IF(ISDATE(B88),""X"",""""))"),"") | K88: =IFERROR(__xludf.DUMMYFUNCTION("IF(ISBLANK(B88),"""",IF(ISDATE(B88),H88,""""))"),"") | L88: =IFERROR(__xludf.DUMMYFUNCTION("IF(ISBLANK(B88),"""",IF(ISDATE(B88),TEXT(B88,""M""),""""))"),"") | M88: =IFERROR(__xludf.DUMMYFUNCTION("IF(L88="""","""",QUERY({'Dashboard-Dados'!$Y$2:$AA$13},""Select Col2 Where Col1=""&L88))"),"") | N88: =IFERROR(__xludf.DUMMYFUNCTION("IF(ISBLANK(B88),"""",IF(ISDATE(B88),TEXT(B88,""yyyy""),""""))"),"")
J89: =IFERROR(__xludf.DUMMYFUNCTION("IF(ISBLANK(B89),"""",IF(ISDATE(B89),""X"",""""))"),"") | K89: =IFERROR(__xludf.DUMMYFUNCTION("IF(ISBLANK(B89),"""",IF(ISDATE(B89),H89,""""))"),"") | L89: =IFERROR(__xludf.DUMMYFUNCTION("IF(ISBLANK(B89),"""",IF(ISDATE(B89),TEXT(B89,""M""),""""))"),"") | M89: =IFERROR(__xludf.DUMMYFUNCTION("IF(L89="""","""",QUERY({'Dashboard-Dados'!$Y$2:$AA$13},""Select Col2 Where Col1=""&L89))"),"") | N89: =IFERROR(__xludf.DUMMYFUNCTION("IF(ISBLANK(B89),"""",IF(ISDATE(B89),TEXT(B89,""yyyy""),""""))"),"")
J90: =IFERROR(__xludf.DUMMYFUNCTION("IF(ISBLANK(B90),"""",IF(ISDATE(B90),""X"",""""))"),"") | K90: =IFERROR(__xludf.DUMMYFUNCTION("IF(ISBLANK(B90),"""",IF(ISDATE(B90),H90,""""))"),"") | L90: =IFERROR(__xludf.DUMMYFUNCTION("IF(ISBLANK(B90),"""",IF(ISDATE(B90),TEXT(B90,""M""),""""))"),"") | M90: =IFERROR(__xludf.DUMMYFUNCTION("IF(L90="""","""",QUERY({'Dashboard-Dados'!$Y$2:$AA$13},""Select Col2 Where Col1=""&L90))"),"") | N90: =IFERROR(__xludf.DUMMYFUNCTION("IF(ISBLANK(B90),"""",IF(ISDATE(B90),TEXT(B90,""yyyy""),""""))"),"")
J91: =IFERROR(__xludf.DUMMYFUNCTION("IF(ISBLANK(B91),"""",IF(ISDATE(B91),""X"",""""))"),"") | K91: =IFERROR(__xludf.DUMMYFUNCTION("IF(ISBLANK(B91),"""",IF(ISDATE(B91),H91,""""))"),"") | L91: =IFERROR(__xludf.DUMMYFUNCTION("IF(ISBLANK(B91),"""",IF(ISDATE(B91),TEXT(B91,""M""),""""))"),"") | M91: =IFERROR(__xludf.DUMMYFUNCTION("IF(L91="""","""",QUERY({'Dashboard-Dados'!$Y$2:$AA$13},""Select Col2 Where Col1=""&L91))"),"") | N91: =IFERROR(__xludf.DUMMYFUNCTION("IF(ISBLANK(B91),"""",IF(ISDATE(B91),TEXT(B91,""yyyy""),""""))"),"")
J92: =IFERROR(__xludf.DUMMYFUNCTION("IF(ISBLANK(B92),"""",IF(ISDATE(B92),""X"",""""))"),"") | K92: =IFERROR(__xludf.DUMMYFUNCTION("IF(ISBLANK(B92),"""",IF(ISDATE(B92),H92,""""))"),"") | L92: =IFERROR(__xludf.DUMMYFUNCTION("IF(ISBLANK(B92),"""",IF(ISDATE(B92),TEXT(B92,""M""),""""))"),"") | M92: =IFERROR(__xludf.DUMMYFUNCTION("IF(L92="""","""",QUERY({'Dashboard-Dados'!$Y$2:$AA$13},""Select Col2 Where Col1=""&L92))"),"") | N92: =IFERROR(__xludf.DUMMYFUNCTION("IF(ISBLANK(B92),"""",IF(ISDATE(B92),TEXT(B92,""yyyy""),""""))"),"")
J93: =IFERROR(__xludf.DUMMYFUNCTION("IF(ISBLANK(B93),"""",IF(ISDATE(B93),""X"",""""))"),"") | K93: =IFERROR(__xludf.DUMMYFUNCTION("IF(ISBLANK(B93),"""",IF(ISDATE(B93),H93,""""))"),"") | L93: =IFERROR(__xludf.DUMMYFUNCTION("IF(ISBLANK(B93),"""",IF(ISDATE(B93),TEXT(B93,""M""),""""))"),"") | M93: =IFERROR(__xludf.DUMMYFUNCTION("IF(L93="""","""",QUERY({'Dashboard-Dados'!$Y$2:$AA$13},""Select Col2 Where Col1=""&L93))"),"") | N93: =IFERROR(__xludf.DUMMYFUNCTION("IF(ISBLANK(B93),"""",IF(ISDATE(B93),TEXT(B93,""yyyy""),""""))"),"")
J94: =IFERROR(__xludf.DUMMYFUNCTION("IF(ISBLANK(B94),"""",IF(ISDATE(B94),""X"",""""))"),"") | K94: =IFERROR(__xludf.DUMMYFUNCTION("IF(ISBLANK(B94),"""",IF(ISDATE(B94),H94,""""))"),"") | L94: =IFERROR(__xludf.DUMMYFUNCTION("IF(ISBLANK(B94),"""",IF(ISDATE(B94),TEXT(B94,""M""),""""))"),"") | M94: =IFERROR(__xludf.DUMMYFUNCTION("IF(L94="""","""",QUERY({'Dashboard-Dados'!$Y$2:$AA$13},""Select Col2 Where Col1=""&L94))"),"") | N94: =IFERROR(__xludf.DUMMYFUNCTION("IF(ISBLANK(B94),"""",IF(ISDATE(B94),TEXT(B94,""yyyy""),""""))"),"")
J95: =IFERROR(__xludf.DUMMYFUNCTION("IF(ISBLANK(B95),"""",IF(ISDATE(B95),""X"",""""))"),"") | K95: =IFERROR(__xludf.DUMMYFUNCTION("IF(ISBLANK(B95),"""",IF(ISDATE(B95),H95,""""))"),"") | L95: =IFERROR(__xludf.DUMMYFUNCTION("IF(ISBLANK(B95),"""",IF(ISDATE(B95),TEXT(B95,""M""),""""))"),"") | M95: =IFERROR(__xludf.DUMMYFUNCTION("IF(L95="""","""",QUERY({'Dashboard-Dados'!$Y$2:$AA$13},""Select Col2 Where Col1=""&L95))"),"") | N95: =IFERROR(__xludf.DUMMYFUNCTION("IF(ISBLANK(B95),"""",IF(ISDATE(B95),TEXT(B95,""yyyy""),""""))"),"")
J96: =IFERROR(__xludf.DUMMYFUNCTION("IF(ISBLANK(B96),"""",IF(ISDATE(B96),""X"",""""))"),"") | K96: =IFERROR(__xludf.DUMMYFUNCTION("IF(ISBLANK(B96),"""",IF(ISDATE(B96),H96,""""))"),"") | L96: =IFERROR(__xludf.DUMMYFUNCTION("IF(ISBLANK(B96),"""",IF(ISDATE(B96),TEXT(B96,""M""),""""))"),"") | M96: =IFERROR(__xludf.DUMMYFUNCTION("IF(L96="""","""",QUERY({'Dashboard-Dados'!$Y$2:$AA$13},""Select Col2 Where Col1=""&L96))"),"") | N96: =IFERROR(__xludf.DUMMYFUNCTION("IF(ISBLANK(B96),"""",IF(ISDATE(B96),TEXT(B96,""yyyy""),""""))"),"")
J97: =IFERROR(__xludf.DUMMYFUNCTION("IF(ISBLANK(B97),"""",IF(ISDATE(B97),""X"",""""))"),"") | K97: =IFERROR(__xludf.DUMMYFUNCTION("IF(ISBLANK(B97),"""",IF(ISDATE(B97),H97,""""))"),"") | L97: =IFERROR(__xludf.DUMMYFUNCTION("IF(ISBLANK(B97),"""",IF(ISDATE(B97),TEXT(B97,""M""),""""))"),"") | M97: =IFERROR(__xludf.DUMMYFUNCTION("IF(L97="""","""",QUERY({'Dashboard-Dados'!$Y$2:$AA$13},""Select Col2 Where Col1=""&L97))"),"") | N97: =IFERROR(__xludf.DUMMYFUNCTION("IF(ISBLANK(B97),"""",IF(ISDATE(B97),TEXT(B97,""yyyy""),""""))"),"")
J98: =IFERROR(__xludf.DUMMYFUNCTION("IF(ISBLANK(B98),"""",IF(ISDATE(B98),""X"",""""))"),"") | K98: =IFERROR(__xludf.DUMMYFUNCTION("IF(ISBLANK(B98),"""",IF(ISDATE(B98),H98,""""))"),"") | L98: =IFERROR(__xludf.DUMMYFUNCTION("IF(ISBLANK(B98),"""",IF(ISDATE(B98),TEXT(B98,""M""),""""))"),"") | M98: =IFERROR(__xludf.DUMMYFUNCTION("IF(L98="""","""",QUERY({'Dashboard-Dados'!$Y$2:$AA$13},""Select Col2 Where Col1=""&L98))"),"") | N98: =IFERROR(__xludf.DUMMYFUNCTION("IF(ISBLANK(B98),"""",IF(ISDATE(B98),TEXT(B98,""yyyy""),""""))"),"")
J99: =IFERROR(__xludf.DUMMYFUNCTION("IF(ISBLANK(B99),"""",IF(ISDATE(B99),""X"",""""))"),"") | K99: =IFERROR(__xludf.DUMMYFUNCTION("IF(ISBLANK(B99),"""",IF(ISDATE(B99),H99,""""))"),"") | L99: =IFERROR(__xludf.DUMMYFUNCTION("IF(ISBLANK(B99),"""",IF(ISDATE(B99),TEXT(B99,""M""),""""))"),"") | M99: =IFERROR(__xludf.DUMMYFUNCTION("IF(L99="""","""",QUERY({'Dashboard-Dados'!$Y$2:$AA$13},""Select Col2 Where Col1=""&L99))"),"") | N99: =IFERROR(__xludf.DUMMYFUNCTION("IF(ISBLANK(B99),"""",IF(ISDATE(B99),TEXT(B99,""yyyy""),""""))"),"")
J100: =IFERROR(__xludf.DUMMYFUNCTION("IF(ISBLANK(B100),"""",IF(ISDATE(B100),""X"",""""))"),"") | K100: =IFERROR(__xludf.DUMMYFUNCTION("IF(ISBLANK(B100),"""",IF(ISDATE(B100),H100,""""))"),"") | L100: =IFERROR(__xludf.DUMMYFUNCTION("IF(ISBLANK(B100),"""",IF(ISDATE(B100),TEXT(B100,""M""),""""))"),"") | M100: =IFERROR(__xludf.DUMMYFUNCTION("IF(L100="""","""",QUERY({'Dashboard-Dados'!$Y$2:$AA$13},""Select Col2 Where Col1=""&L100))"),"") | N100: =IFERROR(__xludf.DUMMYFUNCTION("IF(ISBLANK(B100),"""",IF(ISDATE(B100),TEXT(B100,""yyyy""),""""))"),"")
J101: =IFERROR(__xludf.DUMMYFUNCTION("IF(ISBLANK(B101),"""",IF(ISDATE(B101),""X"",""""))"),"") | K101: =IFERROR(__xludf.DUMMYFUNCTION("IF(ISBLANK(B101),"""",IF(ISDATE(B101),H101,""""))"),"") | L101: =IFERROR(__xludf.DUMMYFUNCTION("IF(ISBLANK(B101),"""",IF(ISDATE(B101),TEXT(B101,""M""),""""))"),"") | M101: =IFERROR(__xludf.DUMMYFUNCTION("IF(L101="""","""",QUERY({'Dashboard-Dados'!$Y$2:$AA$13},""Select Col2 Where Col1=""&L101))"),"") | N101: =IFERROR(__xludf.DUMMYFUNCTION("IF(ISBLANK(B101),"""",IF(ISDATE(B101),TEXT(B101,""yyyy""),""""))"),"")
...

Sheet Parâmetros
B1: PARAMETROS PERSONALIZÁVEIS
B3: Ultrassonografia | D3: Cardiologia | F3: RaioX | H3: Tomografia | J3: Outros | L3: Formas de Pagamento
B4: US Abdominal | D4: Ecocardiograma | F4: 1 Projeção | L4: Dinheiro
B5: US Ocular | D5: Eletrocardiograma | F5: 2 Projeções | L5: Cartão de Crédito
B6: US Cervical | D6: Avaliação de pressão | F6: 3 Projeções | L6: Cartão de Débito
B7: Cistocentese | F7: 4 Projeções | L7: Transferencia Bancária
B8: Abdominocentese | F8: 5 Projeções | L8: Pix
B9: Toracocentese | F9: 6 Projeções | L9: PicPay
B10: A-FAST | F10: Projeção Adicional | L10: Cheque
B11: T-FAST | F11: Bula Timpânica | L11: Boleto
B12: Citologia Aspirativa | F12: Seios da Face | L12: Em Aberto
B13: US Crânio | F13: Maxila/Mandibula | L13: Outros
B14: US Articular | F14: Coluna
B15: Drenagem Ecoguiada | F15: Pesqquisa de Metástase
F16: Colapso de Traquéia
F17: Abdominal
F18: Displasia do Cotovelo
F19: Displasia Coxofemoral
F20: Esofagograma
F21: Gastrograma
F22: Urografia Excretora
F23: Cistografia
F24: Uretrocistografia
F25: Enema Baritado
F26: Mielografia

Sheet Parâmetros-Filtros
A1: =COLUMN() -> 1 | B1: =COLUMN() -> 2 | C1: =COLUMN() -> 3 | D1: =COLUMN() -> 4 | E1: =COLUMN() -> 5 | F1: =COLUMN() -> 6 | G1: =COLUMN() -> 7 | H1: =COLUMN() -> 8 | ... ATD1: =COLUMN() -> 1200
A6: {=IFNA(TRANSPOSE(INDEX('Parâmetros'!$B$4:$J3001,,MATCH(Exames!F4,'Parâmetros'!$B$3:$J$3,0))),"")} -> US Abdominal | B6: US Ocular | C6: US Cervical | D6: Cistocentese | E6: Abdominocentese | F6: Toracocentese | G6: A-FAST | H6: T-FAST | I6: Citologia Aspirativa | J6: US Crânio | K6: US Articular | L6: Drenagem Ecoguiada
A7: {=IFNA(TRANSPOSE(INDEX('Parâmetros'!$B$4:$J3001,,MATCH(Exames!F5,'Parâmetros'!$B$3:$J$3,0))),"")}
A8: {=IFNA(TRANSPOSE(INDEX('Parâmetros'!$B$4:$J3001,,MATCH(Exames!F6,'Parâmetros'!$B$3:$J$3,0))),"")}
A9: {=IFNA(TRANSPOSE(INDEX('Parâmetros'!$B$4:$J3001,,MATCH(Exames!F7,'Parâmetros'!$B$3:$J$3,0))),"")}
A10: {=IFNA(TRANSPOSE(INDEX('Parâmetros'!$B$4:$J3001,,MATCH(Exames!F8,'Parâmetros'!$B$3:$J$3,0))),"")}
A11: {=IFNA(TRANSPOSE(INDEX('Parâmetros'!$B$4:$J3001,,MATCH(Exames!F9,'Parâmetros'!$B$3:$J$3,0))),"")}
A12: {=IFNA(TRANSPOSE(INDEX('Parâmetros'!$B$4:$J3001,,MATCH(Exames!F10,'Parâmetros'!$B$3:$J$3,0))),"")}
A13: {=IFNA(TRANSPOSE(INDEX('Parâmetros'!$B$4:$J3001,,MATCH(Exames!F11,'Parâmetros'!$B$3:$J$3,0))),"")}
A14: {=IFNA(TRANSPOSE(INDEX('Parâmetros'!$B$4:$J3001,,MATCH(Exames!F12,'Parâmetros'!$B$3:$J$3,0))),"")}
A15: {=IFNA(TRANSPOSE(INDEX('Parâmetros'!$B$4:$J3001,,MATCH(Exames!F13,'Parâmetros'!$B$3:$J$3,0))),"")}
A16: {=IFNA(TRANSPOSE(INDEX('Parâmetros'!$B$4:$J3001,,MATCH(Exames!F14,'Parâmetros'!$B$3:$J$3,0))),"")}
A17: {=IFNA(TRANSPOSE(INDEX('Parâmetros'!$B$4:$J3001,,MATCH(Exames!F15,'Parâmetros'!$B$3:$J$3,0))),"")}
A18: {=IFNA(TRANSPOSE(INDEX('Parâmetros'!$B$4:$J3001,,MATCH(Exames!F16,'Parâmetros'!$B$3:$J$3,0))),"")}
A19: {=IFNA(TRANSPOSE(INDEX('Parâmetros'!$B$4:$J3001,,MATCH(Exames!F17,'Parâmetros'!$B$3:$J$3,0))),"")}
A20: {=IFNA(TRANSPOSE(INDEX('Parâmetros'!$B$4:$J3001,,MATCH(Exames!F18,'Parâmetros'!$B$3:$J$3,0))),"")}
A21: {=IFNA(TRANSPOSE(INDEX('Parâmetros'!$B$4:$J3001,,MATCH(Exames!F19,'Parâmetros'!$B$3:$J$3,0))),"")}
A22: {=IFNA(TRANSPOSE(INDEX('Parâmetros'!$B$4:$J3001,,MATCH(Exames!F20,'Parâmetros'!$B$3:$J$3,0))),"")}
A23: {=IFNA(TRANSPOSE(INDEX('Parâmetros'!$B$4:$J3001,,MATCH(Exames!F21,'Parâmetros'!$B$3:$J$3,0))),"")}
A24: {=IFNA(TRANSPOSE(INDEX('Parâmetros'!$B$4:$J3001,,MATCH(Exames!F22,'Parâmetros'!$B$3:$J$3,0))),"")}
A25: {=IFNA(TRANSPOSE(INDEX('Parâmetros'!$B$4:$J3001,,MATCH(Exames!F23,'Parâmetros'!$B$3:$J$3,0))),"")}
A26: {=IFNA(TRANSPOSE(INDEX('Parâmetros'!$B$4:$J3001,,MATCH(Exames!F24,'Parâmetros'!$B$3:$J$3,0))),"")}
A27: {=IFNA(TRANSPOSE(INDEX('Parâmetros'!$B$4:$J3001,,MATCH(Exames!F25,'Parâmetros'!$B$3:$J$3,0))),"")}
A28: {=IFNA(TRANSPOSE(INDEX('Parâmetros'!$B$4:$J3001,,MATCH(Exames!F26,'Parâmetros'!$B$3:$J$3,0))),"")}
A29: {=IFNA(TRANSPOSE(INDEX('Parâmetros'!$B$4:$J3001,,MATCH(Exames!F27,'Parâmetros'!$B$3:$J$3,0))),"")}
A30: {=IFNA(TRANSPOSE(INDEX('Parâmetros'!$B$4:$J3001,,MATCH(Exames!F28,'Parâmetros'!$B$3:$J$3,0))),"")}
A31: {=IFNA(TRANSPOSE(INDEX('Parâmetros'!$B$4:$J3001,,MATCH(Exames!F29,'Parâmetros'!$B$3:$J$3,0))),"")}
A32: {=IFNA(TRANSPOSE(INDEX('Parâmetros'!$B$4:$J3001,,MATCH(Exames!F30,'Parâmetros'!$B$3:$J$3,0))),"")}
A33: {=IFNA(TRANSPOSE(INDEX('Parâmetros'!$B$4:$J3001,,MATCH(Exames!F31,'Parâmetros'!$B$3:$J$3,0))),"")}
A34: {=IFNA(TRANSPOSE(INDEX('Parâmetros'!$B$4:$J3001,,MATCH(Exames!F32,'Parâmetros'!$B$3:$J$3,0))),"")}
A35: {=IFNA(TRANSPOSE(INDEX('Parâmetros'!$B$4:$J3001,,MATCH(Exames!F33,'Parâmetros'!$B$3:$J$3,0))),"")}
A36: {=IFNA(TRANSPOSE(INDEX('Parâmetros'!$B$4:$J3001,,MATCH(Exames!F34,'Parâmetros'!$B$3:$J$3,0))),"")}
A37: {=IFNA(TRANSPOSE(INDEX('Parâmetros'!$B$4:$J3001,,MATCH(Exames!F35,'Parâmetros'!$B$3:$J$3,0))),"")}
A38: {=IFNA(TRANSPOSE(INDEX('Parâmetros'!$B$4:$J3001,,MATCH(Exames!F36,'Parâmetros'!$B$3:$J$3,0))),"")}
A39: {=IFNA(TRANSPOSE(INDEX('Parâmetros'!$B$4:$J3001,,MATCH(Exames!F37,'Parâmetros'!$B$3:$J$3,0))),"")}
A40: {=IFNA(TRANSPOSE(INDEX('Parâmetros'!$B$4:$J3001,,MATCH(Exames!F38,'Parâmetros'!$B$3:$J$3,0))),"")}
A41: {=IFNA(TRANSPOSE(INDEX('Parâmetros'!$B$4:$J3001,,MATCH(Exames!F39,'Parâmetros'!$B$3:$J$3,0))),"")}
A42: {=IFNA(TRANSPOSE(INDEX('Parâmetros'!$B$4:$J3001,,MATCH(Exames!F40,'Parâmetros'!$B$3:$J$3,0))),"")}
A43: {=IFNA(TRANSPOSE(INDEX('Parâmetros'!$B$4:$J3001,,MATCH(Exames!F41,'Parâmetros'!$B$3:$J$3,0))),"")}
A44: {=IFNA(TRANSPOSE(INDEX('Parâmetros'!$B$4:$J3001,,MATCH(Exames!F42,'Parâmetros'!$B$3:$J$3,0))),"")}
A45: {=IFNA(TRANSPOSE(INDEX('Parâmetros'!$B$4:$J3001,,MATCH(Exames!F43,'Parâmetros'!$B$3:$J$3,0))),"")}
A46: {=IFNA(TRANSPOSE(INDEX('Parâmetros'!$B$4:$J3001,,MATCH(Exames!F44,'Parâmetros'!$B$3:$J$3,0))),"")}
A47: {=IFNA(TRANSPOSE(INDEX('Parâmetros'!$B$4:$J3001,,MATCH(Exames!F45,'Parâmetros'!$B$3:$J$3,0))),"")}
A48: {=IFNA(TRANSPOSE(INDEX('Parâmetros'!$B$4:$J3001,,MATCH(Exames!F46,'Parâmetros'!$B$3:$J$3,0))),"")}
A49: {=IFNA(TRANSPOSE(INDEX('Parâmetros'!$B$4:$J3001,,MATCH(Exames!F47,'Parâmetros'!$B$3:$J$3,0))),"")}
A50: {=IFNA(TRANSPOSE(INDEX('Parâmetros'!$B$4:$J3001,,MATCH(Exames!F48,'Parâmetros'!$B$3:$J$3,0))),"")}
A51: {=IFNA(TRANSPOSE(INDEX('Parâmetros'!$B$4:$J3001,,MATCH(Exames!F49,'Parâmetros'!$B$3:$J$3,0))),"")}
A52: {=IFNA(TRANSPOSE(INDEX('Parâmetros'!$B$4:$J3001,,MATCH(Exames!F50,'Parâmetros'!$B$3:$J$3,0))),"")}
A53: {=IFNA(TRANSPOSE(INDEX('Parâmetros'!$B$4:$J3001,,MATCH(Exames!F51,'Parâmetros'!$B$3:$J$3,0))),"")}
A54: {=IFNA(TRANSPOSE(INDEX('Parâmetros'!$B$4:$J3001,,MATCH(Exames!F52,'Parâmetros'!$B$3:$J$3,0))),"")}
A55: {=IFNA(TRANSPOSE(INDEX('Parâmetros'!$B$4:$J3001,,MATCH(Exames!F53,'Parâmetros'!$B$3:$J$3,0))),"")}
A56: {=IFNA(TRANSPOSE(INDEX('Parâmetros'!$B$4:$J3001,,MATCH(Exames!F54,'Parâmetros'!$B$3:$J$3,0))),"")}
A57: {=IFNA(TRANSPOSE(INDEX('Parâmetros'!$B$4:$J3001,,MATCH(Exames!F55,'Parâmetros'!$B$3:$J$3,0))),"")}
A58: {=IFNA(TRANSPOSE(INDEX('Parâmetros'!$B$4:$J3001,,MATCH(Exames!F56,'Parâmetros'!$B$3:$J$3,0))),"")}
A59: {=IFNA(TRANSPOSE(INDEX('Parâmetros'!$B$4:$J3001,,MATCH(Exames!F57,'Parâmetros'!$B$3:$J$3,0))),"")}
A60: {=IFNA(TRANSPOSE(INDEX('Parâmetros'!$B$4:$J3001,,MATCH(Exames!F58,'Parâmetros'!$B$3:$J$3,0))),"")}
A61: {=IFNA(TRANSPOSE(INDEX('Parâmetros'!$B$4:$J3001,,MATCH(Exames!F59,'Parâmetros'!$B$3:$J$3,0))),"")}
A62: {=IFNA(TRANSPOSE(INDEX('Parâmetros'!$B$4:$J3001,,MATCH(Exames!F60,'Parâmetros'!$B$3:$J$3,0))),"")}
A63: {=IFNA(TRANSPOSE(INDEX('Parâmetros'!$B$4:$J3001,,MATCH(Exames!F61,'Parâmetros'!$B$3:$J$3,0))),"")}
A64: {=IFNA(TRANSPOSE(INDEX('Parâmetros'!$B$4:$J3001,,MATCH(Exames!F62,'Parâmetros'!$B$3:$J$3,0))),"")}
A65: {=IFNA(TRANSPOSE(INDEX('Parâmetros'!$B$4:$J3001,,MATCH(Exames!F63,'Parâmetros'!$B$3:$J$3,0))),"")}
A66: {=IFNA(TRANSPOSE(INDEX('Parâmetros'!$B$4:$J3001,,MATCH(Exames!F64,'Parâmetros'!$B$3:$J$3,0))),"")}
A67: {=IFNA(TRANSPOSE(INDEX('Parâmetros'!$B$4:$J3001,,MATCH(Exames!F65,'Parâmetros'!$B$3:$J$3,0))),"")}
A68: {=IFNA(TRANSPOSE(INDEX('Parâmetros'!$B$4:$J3001,,MATCH(Exames!F66,'Parâmetros'!$B$3:$J$3,0))),"")}
A69: {=IFNA(TRANSPOSE(INDEX('Parâmetros'!$B$4:$J3001,,MATCH(Exames!F67,'Parâmetros'!$B$3:$J$3,0))),"")}
A70: {=IFNA(TRANSPOSE(INDEX('Parâmetros'!$B$4:$J3001,,MATCH(Exames!F68,'Parâmetros'!$B$3:$J$3,0))),"")}
A71: {=IFNA(TRANSPOSE(INDEX('Parâmetros'!$B$4:$J3001,,MATCH(Exames!F69,'Parâmetros'!$B$3:$J$3,0))),"")}
A72: {=IFNA(TRANSPOSE(INDEX('Parâmetros'!$B$4:$J3001,,MATCH(Exames!F70,'Parâmetros'!$B$3:$J$3,0))),"")}
A73: {=IFNA(TRANSPOSE(INDEX('Parâmetros'!$B$4:$J3001,,MATCH(Exames!F71,'Parâmetros'!$B$3:$J$3,0))),"")}
A74: {=IFNA(TRANSPOSE(INDEX('Parâmetros'!$B$4:$J3001,,MATCH(Exames!F72,'Parâmetros'!$B$3:$J$3,0))),"")}
A75: {=IFNA(TRANSPOSE(INDEX('Parâmetros'!$B$4:$J3001,,MATCH(Exames!F73,'Parâmetros'!$B$3:$J$3,0))),"")}
A76: {=IFNA(TRANSPOSE(INDEX('Parâmetros'!$B$4:$J3001,,MATCH(Exames!F74,'Parâmetros'!$B$3:$J$3,0))),"")}
A77: {=IFNA(TRANSPOSE(INDEX('Parâmetros'!$B$4:$J3001,,MATCH(Exames!F75,'Parâmetros'!$B$3:$J$3,0))),"")}
A78: {=IFNA(TRANSPOSE(INDEX('Parâmetros'!$B$4:$J3001,,MATCH(Exames!F76,'Parâmetros'!$B$3:$J$3,0))),"")}
A79: {=IFNA(TRANSPOSE(INDEX('Parâmetros'!$B$4:$J3001,,MATCH(Exames!F77,'Parâmetros'!$B$3:$J$3,0))),"")}
A80: {=IFNA(TRANSPOSE(INDEX('Parâmetros'!$B$4:$J3001,,MATCH(Exames!F78,'Parâmetros'!$B$3:$J$3,0))),"")}
A81: {=IFNA(TRANSPOSE(INDEX('Parâmetros'!$B$4:$J3001,,MATCH(Exames!F79,'Parâmetros'!$B$3:$J$3,0))),"")}
A82: {=IFNA(TRANSPOSE(INDEX('Parâmetros'!$B$4:$J3001,,MATCH(Exames!F80,'Parâmetros'!$B$3:$J$3,0))),"")}
A83: {=IFNA(TRANSPOSE(INDEX('Parâmetros'!$B$4:$J3001,,MATCH(Exames!F81,'Parâmetros'!$B$3:$J$3,0))),"")}
A84: {=IFNA(TRANSPOSE(INDEX('Parâmetros'!$B$4:$J3001,,MATCH(Exames!F82,'Parâmetros'!$B$3:$J$3,0))),"")}
A85: {=IFNA(TRANSPOSE(INDEX('Parâmetros'!$B$4:$J3001,,MATCH(Exames!F83,'Parâmetros'!$B$3:$J$3,0))),"")}
A86: {=IFNA(TRANSPOSE(INDEX('Parâmetros'!$B$4:$J3001,,MATCH(Exames!F84,'Parâmetros'!$B$3:$J$3,0))),"")}
A87: {=IFNA(TRANSPOSE(INDEX('Parâmetros'!$B$4:$J3001,,MATCH(Exames!F85,'Parâmetros'!$B$3:$J$3,0))),"")}
A88: {=IFNA(TRANSPOSE(INDEX('Parâmetros'!$B$4:$J3001,,MATCH(Exames!F86,'Parâmetros'!$B$3:$J$3,0))),"")}
A89: {=IFNA(TRANSPOSE(INDEX('Parâmetros'!$B$4:$J3001,,MATCH(Exames!F87,'Parâmetros'!$B$3:$J$3,0))),"")}
A90: {=IFNA(TRANSPOSE(INDEX('Parâmetros'!$B$4:$J3001,,MATCH(Exames!F88,'Parâmetros'!$B$3:$J$3,0))),"")}
A91: {=IFNA(TRANSPOSE(INDEX('Parâmetros'!$B$4:$J3001,,MATCH(Exames!F89,'Parâmetros'!$B$3:$J$3,0))),"")}
A92: {=IFNA(TRANSPOSE(INDEX('Parâmetros'!$B$4:$J3001,,MATCH(Exames!F90,'Parâmetros'!$B$3:$J$3,0))),"")}
A93: {=IFNA(TRANSPOSE(INDEX('Parâmetros'!$B$4:$J3001,,MATCH(Exames!F91,'Parâmetros'!$B$3:$J$3,0))),"")}
A94: {=IFNA(TRANSPOSE(INDEX('Parâmetros'!$B$4:$J3001,,MATCH(Exames!F92,'Parâmetros'!$B$3:$J$3,0))),"")}
A95: {=IFNA(TRANSPOSE(INDEX('Parâmetros'!$B$4:$J3001,,MATCH(Exames!F93,'Parâmetros'!$B$3:$J$3,0))),"")}
A96: {=IFNA(TRANSPOSE(INDEX('Parâmetros'!$B$4:$J3001,,MATCH(Exames!F94,'Parâmetros'!$B$3:$J$3,0))),"")}
A97: {=IFNA(TRANSPOSE(INDEX('Parâmetros'!$B$4:$J3001,,MATCH(Exames!F95,'Parâmetros'!$B$3:$J$3,0))),"")}
A98: {=IFNA(TRANSPOSE(INDEX('Parâmetros'!$B$4:$J3001,,MATCH(Exames!F96,'Parâmetros'!$B$3:$J$3,0))),"")}
A99: {=IFNA(TRANSPOSE(INDEX('Parâmetros'!$B$4:$J3001,,MATCH(Exames!F97,'Parâmetros'!$B$3:$J$3,0))),"")}
A100: {=IFNA(TRANSPOSE(INDEX('Parâmetros'!$B$4:$J3001,,MATCH(Exames!F98,'Parâmetros'!$B$3:$J$3,0))),"")}
A101: {=IFNA(TRANSPOSE(INDEX('Parâmetros'!$B$4:$J3001,,MATCH(Exames!F99,'Parâmetros'!$B$3:$J$3,0))),"")}
A102: {=IFNA(TRANSPOSE(INDEX('Parâmetros'!$B$4:$J3001,,MATCH(Exames!F100,'Parâmetros'!$B$3:$J$3,0))),"")}
A103: {=IFNA(TRANSPOSE(INDEX('Parâmetros'!$B$4:$J3001,,MATCH(Exames!F101,'Parâmetros'!$B$3:$J$3,0))),"")}
A104: {=IFNA(TRANSPOSE(INDEX('Parâmetros'!$B$4:$J3001,,MATCH(Exames!F102,'Parâmetros'!$B$3:$J$3,0))),"")}
...

Sheet Dashboard-Dados
A1: Ano | B1: Mês-N | C1: Mês | D1: Receita | E1: Despesa | F1: Lucro | G1: Qtd Exames | H1: Linha | K1: Colunas | Q1: Colunas | U1: =IFERROR(__xludf.DUMMYFUNCTION("QUERY({J1:M1201},""Select Col1 Where Col4 Is Not Null Label Col1 'Ano Receitas'"")"),"Ano Receitas") -> Ano Receitas | V1: =IFERROR(__xludf.DUMMYFUNCTION("QUERY({P1:S1201},""Select Col1 Where Col4 Is Not Null Label Col1 'Ano Despesas'"")"),"Ano Despesas") -> Ano Despesas | W1: Lista Anos | Y1: Mês | Z1: Abrev. | AA1: Descrição | AB1: Exames | AC1: Diferença | AE1: Receitas | AF1: =IFERROR(GETPIVOTDATA("SUM de Receita",Dashboard!$AK$48),0) -> 0
A2: =IFERROR(__xludf.DUMMYFUNCTION("ARRAYFORMULA(SPLIT(FLATTEN(QUERY({W2:W1201},""Select * Where Col1 Is Not Null"") & ""|"" & TRANSPOSE(Y2:Y13)), ""|""))"),"#N/A") -> #N/A | C2: =IFNA(VLOOKUP('Dashboard-Dados'!B2,'Dashboard-Dados'!$Y$2:$AA$13,2),"") | D2: =IFERROR(GETPIVOTDATA("Valor Recebido",'Dashboard-Dados'!$J$1,$A$1,A2,$B$1,B2),0) -> 0 | E2: =IFERROR(GETPIVOTDATA("Valor Despesa",'Dashboard-Dados'!$P$1,$A$1,A2,$B$1,B2),0) -> 0 | F2: =D2-E2 -> 0 | G2: =IFERROR(GETPIVOTDATA("Exame",'Dashboard-Dados'!$J$1,$A$1,A2,$B$1,B2),0) -> 0 | H2: =ROW() -> 2 | J2: Linhas | K2: Valores | P2: Linhas | Q2: Valores | W2: =IFERROR(__xludf.DUMMYFUNCTION("SORT(UNIQUE(TRANSPOSE((IFERROR(SPLIT(TEXTJOIN("","",TRUE, IFERROR(TEXTJOIN("","",TRUE,U2:U1201),""""), IFERROR(TEXTJOIN("","",TRUE,V2:V1201),"""") ),"",""),"""")))),1,TRUE)"),"") | Y2: 1 | Z2: =PROPER(TEXT(DATE(1900,Y2,1),"mmm")) -> Jan. | AA2: =PROPER(TEXT(DATE(1900,Y2,1),"mmMm")) -> Janeiro | AB2: =IFNA(INDIRECT(ADDRESS(Y2+$Z$15,$AB$15)), 0) -> 0 | AC2: =0 -> 0 | AE2: Despesas | AF2: =IFERROR(GETPIVOTDATA("SUM de Despesa",Dashboard!$AK$48),0) -> 0
A3: =IFERROR(__xludf.DUMMYFUNCTION("""COMPUTED_VALUE"""),"#N/A") -> #N/A | C3: =IFNA(VLOOKUP('Dashboard-Dados'!B3,'Dashboard-Dados'!$Y$2:$AA$13,2),"") | D3: =IFERROR(GETPIVOTDATA("Valor Recebido",'Dashboard-Dados'!$J$1,$A$1,A3,$B$1,B3),0) -> 0 | E3: =IFERROR(GETPIVOTDATA("Valor Despesa",'Dashboard-Dados'!$P$1,$A$1,A3,$B$1,B3),0) -> 0 | F3: =D3-E3 -> 0 | G3: =IFERROR(GETPIVOTDATA("Exame",'Dashboard-Dados'!$J$1,$A$1,A3,$B$1,B3),0) -> 0 | H3: =ROW() -> 3 | Y3: =Y2+1 -> 2 | Z3: =PROPER(TEXT(DATE(1900,Y3,1),"mmm")) -> Fev. | AA3: =PROPER(TEXT(DATE(1900,Y3,1),"mmMm")) -> Fevereiro | AB3: =IFNA(INDIRECT(ADDRESS(Y3+$Z$15,$AB$15)), 0) -> 0 | AC3: =AB3-AB2 -> 0 | AE3: Lucro | AF3: =IFERROR(GETPIVOTDATA("SUM de Lucro",Dashboard!$AK$48),0) -> 0
A4: =IFERROR(__xludf.DUMMYFUNCTION("""COMPUTED_VALUE"""),"#N/A") -> #N/A | C4: =IFNA(VLOOKUP('Dashboard-Dados'!B4,'Dashboard-Dados'!$Y$2:$AA$13,2),"") | D4: =IFERROR(GETPIVOTDATA("Valor Recebido",'Dashboard-Dados'!$J$1,$A$1,A4,$B$1,B4),0) -> 0 | E4: =IFERROR(GETPIVOTDATA("Valor Despesa",'Dashboard-Dados'!$P$1,$A$1,A4,$B$1,B4),0) -> 0 | F4: =D4-E4 -> 0 | G4: =IFERROR(GETPIVOTDATA("Exame",'Dashboard-Dados'!$J$1,$A$1,A4,$B$1,B4),0) -> 0 | H4: =ROW() -> 4 | Y4: =Y3+1 -> 3 | Z4: =PROPER(TEXT(DATE(1900,Y4,1),"mmm")) -> Mar. | AA4: =PROPER(TEXT(DATE(1900,Y4,1),"mmMm")) -> Março | AB4: =IFNA(INDIRECT(ADDRESS(Y4+$Z$15,$AB$15)), 0) -> 0 | AC4: =AB4-AB3 -> 0 | AF4: Total | AG4: Max
A5: =IFERROR(__xludf.DUMMYFUNCTION("""COMPUTED_VALUE"""),"#N/A") -> #N/A | C5: =IFNA(VLOOKUP('Dashboard-Dados'!B5,'Dashboard-Dados'!$Y$2:$AA$13,2),"") | D5: =IFERROR(GETPIVOTDATA("Valor Recebido",'Dashboard-Dados'!$J$1,$A$1,A5,$B$1,B5),0) -> 0 | E5: =IFERROR(GETPIVOTDATA("Valor Despesa",'Dashboard-Dados'!$P$1,$A$1,A5,$B$1,B5),0) -> 0 | F5: =D5-E5 -> 0 | G5: =IFERROR(GETPIVOTDATA("Exame",'Dashboard-Dados'!$J$1,$A$1,A5,$B$1,B5),0) -> 0 | H5: =ROW() -> 5 | Y5: =Y4+1 -> 4 | Z5: =PROPER(TEXT(DATE(1900,Y5,1),"mmm")) -> Abr. | AA5: =PROPER(TEXT(DATE(1900,Y5,1),"mmMm")) -> Abril | AB5: =IFNA(INDIRECT(ADDRESS(Y5+$Z$15,$AB$15)), 0) -> 0 | AC5: =AB5-AB4 -> 0 | AE5: Exames | AF5: =IFERROR(GETPIVOTDATA("SUM de Qtd Exames",Dashboard!$AK$48),0) -> 0 | AG5: =IFERROR(GETPIVOTDATA("MAX de Qtd Exames",Dashboard!$AK$48),0) -> 0
A6: =IFERROR(__xludf.DUMMYFUNCTION("""COMPUTED_VALUE"""),"#N/A") -> #N/A | C6: =IFNA(VLOOKUP('Dashboard-Dados'!B6,'Dashboard-Dados'!$Y$2:$AA$13,2),"") | D6: =IFERROR(GETPIVOTDATA("Valor Recebido",'Dashboard-Dados'!$J$1,$A$1,A6,$B$1,B6),0) -> 0 | E6: =IFERROR(GETPIVOTDATA("Valor Despesa",'Dashboard-Dados'!$P$1,$A$1,A6,$B$1,B6),0) -> 0 | F6: =D6-E6 -> 0 | G6: =IFERROR(GETPIVOTDATA("Exame",'Dashboard-Dados'!$J$1,$A$1,A6,$B$1,B6),0) -> 0 | H6: =ROW() -> 6 | Y6: =Y5+1 -> 5 | Z6: =PROPER(TEXT(DATE(1900,Y6,1),"mmm")) -> Mai. | AA6: =PROPER(TEXT(DATE(1900,Y6,1),"mmMm")) -> Maio | AB6: =IFNA(INDIRECT(ADDRESS(Y6+$Z$15,$AB$15)), 0) -> 0 | AC6: =AB6-AB5 -> 0
A7: =IFERROR(__xludf.DUMMYFUNCTION("""COMPUTED_VALUE"""),"#N/A") -> #N/A | C7: =IFNA(VLOOKUP('Dashboard-Dados'!B7,'Dashboard-Dados'!$Y$2:$AA$13,2),"") | D7: =IFERROR(GETPIVOTDATA("Valor Recebido",'Dashboard-Dados'!$J$1,$A$1,A7,$B$1,B7),0) -> 0 | E7: =IFERROR(GETPIVOTDATA("Valor Despesa",'Dashboard-Dados'!$P$1,$A$1,A7,$B$1,B7),0) -> 0 | F7: =D7-E7 -> 0 | G7: =IFERROR(GETPIVOTDATA("Exame",'Dashboard-Dados'!$J$1,$A$1,A7,$B$1,B7),0) -> 0 | H7: =ROW() -> 7 | Y7: =Y6+1 -> 6 | Z7: =PROPER(TEXT(DATE(1900,Y7,1),"mmm")) -> Jun. | AA7: =PROPER(TEXT(DATE(1900,Y7,1),"mmMm")) -> Junho | AB7: =IFNA(INDIRECT(ADDRESS(Y7+$Z$15,$AB$15)), 0) -> 0 | AC7: =AB7-AB6 -> 0 | AE7: Faixas
A8: =IFERROR(__xludf.DUMMYFUNCTION("""COMPUTED_VALUE"""),"#N/A") -> #N/A | C8: =IFNA(VLOOKUP('Dashboard-Dados'!B8,'Dashboard-Dados'!$Y$2:$AA$13,2),"") | D8: =IFERROR(GETPIVOTDATA("Valor Recebido",'Dashboard-Dados'!$J$1,$A$1,A8,$B$1,B8),0) -> 0 | E8: =IFERROR(GETPIVOTDATA("Valor Despesa",'Dashboard-Dados'!$P$1,$A$1,A8,$B$1,B8),0) -> 0 | F8: =D8-E8 -> 0 | G8: =IFERROR(GETPIVOTDATA("Exame",'Dashboard-Dados'!$J$1,$A$1,A8,$B$1,B8),0) -> 0 | H8: =ROW() -> 8 | Y8: =Y7+1 -> 7 | Z8: =PROPER(TEXT(DATE(1900,Y8,1),"mmm")) -> Jul. | AA8: =PROPER(TEXT(DATE(1900,Y8,1),"mmMm")) -> Julho | AB8: =IFNA(INDIRECT(ADDRESS(Y8+$Z$15,$AB$15)), 0) -> 0 | AC8: =AB8-AB7 -> 0 | AE8: Cor | AF8: Intervalo | AG8: HEX Cor | AH8: Linha | AI8: Alvo
A9: =IFERROR(__xludf.DUMMYFUNCTION("""COMPUTED_VALUE"""),"#N/A") -> #N/A | C9: =IFNA(VLOOKUP('Dashboard-Dados'!B9,'Dashboard-Dados'!$Y$2:$AA$13,2),"") | D9: =IFERROR(GETPIVOTDATA("Valor Recebido",'Dashboard-Dados'!$J$1,$A$1,A9,$B$1,B9),0) -> 0 | E9: =IFERROR(GETPIVOTDATA("Valor Despesa",'Dashboard-Dados'!$P$1,$A$1,A9,$B$1,B9),0) -> 0 | F9: =D9-E9 -> 0 | G9: =IFERROR(GETPIVOTDATA("Exame",'Dashboard-Dados'!$J$1,$A$1,A9,$B$1,B9),0) -> 0 | H9: =ROW() -> 9 | Y9: =Y8+1 -> 8 | Z9: =PROPER(TEXT(DATE(1900,Y9,1),"mmm")) -> Ago. | AA9: =PROPER(TEXT(DATE(1900,Y9,1),"mmMm")) -> Agosto | AB9: =IFNA(INDIRECT(ADDRESS(Y9+$Z$15,$AB$15)), 0) -> 0 | AC9: =AB9-AB8 -> 0 | AE9: =COLUMN() -> 31 | AF9: =COLUMN() -> 32 | AG9: =COLUMN() -> 33 | AH9: =COLUMN() -> 34 | AI9: =COLUMN() -> 35
A10: =IFERROR(__xludf.DUMMYFUNCTION("""COMPUTED_VALUE"""),"#N/A") -> #N/A | C10: =IFNA(VLOOKUP('Dashboard-Dados'!B10,'Dashboard-Dados'!$Y$2:$AA$13,2),"") | D10: =IFERROR(GETPIVOTDATA("Valor Recebido",'Dashboard-Dados'!$J$1,$A$1,A10,$B$1,B10),0) -> 0 | E10: =IFERROR(GETPIVOTDATA("Valor Despesa",'Dashboard-Dados'!$P$1,$A$1,A10,$B$1,B10),0) -> 0 | F10: =D10-E10 -> 0 | G10: =IFERROR(GETPIVOTDATA("Exame",'Dashboard-Dados'!$J$1,$A$1,A10,$B$1,B10),0) -> 0 | H10: =ROW() -> 10 | Y10: =Y9+1 -> 9 | Z10: =PROPER(TEXT(DATE(1900,Y10,1),"mmm")) -> Set. | AA10: =PROPER(TEXT(DATE(1900,Y10,1),"mmMm")) -> Setembro | AB10: =IFNA(INDIRECT(ADDRESS(Y10+$Z$15,$AB$15)), 0) -> 0 | AC10: =AB10-AB9 -> 0 | AE10: Branca | AF10: 0 | AG10: #ffffff | AH10: =ROW() -> 10 | AI10: =$AF$17=AE10 -> TRUE
A11: =IFERROR(__xludf.DUMMYFUNCTION("""COMPUTED_VALUE"""),"#N/A") -> #N/A | C11: =IFNA(VLOOKUP('Dashboard-Dados'!B11,'Dashboard-Dados'!$Y$2:$AA$13,2),"") | D11: =IFERROR(GETPIVOTDATA("Valor Recebido",'Dashboard-Dados'!$J$1,$A$1,A11,$B$1,B11),0) -> 0 | E11: =IFERROR(GETPIVOTDATA("Valor Despesa",'Dashboard-Dados'!$P$1,$A$1,A11,$B$1,B11),0) -> 0 | F11: =D11-E11 -> 0 | G11: =IFERROR(GETPIVOTDATA("Exame",'Dashboard-Dados'!$J$1,$A$1,A11,$B$1,B11),0) -> 0 | H11: =ROW() -> 11 | Y11: =Y10+1 -> 10 | Z11: =PROPER(TEXT(DATE(1900,Y11,1),"mmm")) -> Out. | AA11: =PROPER(TEXT(DATE(1900,Y11,1),"mmMm")) -> Outubro | AB11: =IFNA(INDIRECT(ADDRESS(Y11+$Z$15,$AB$15)), 0) -> 0 | AC11: =AB11-AB10 -> 0 | AE11: Amarela | AF11: 1 | AG11: #ffff00 | AH11: =ROW() -> 11 | AI11: =$AF$17=AE11 -> FALSE
A12: =IFERROR(__xludf.DUMMYFUNCTION("""COMPUTED_VALUE"""),"#N/A") -> #N/A | C12: =IFNA(VLOOKUP('Dashboard-Dados'!B12,'Dashboard-Dados'!$Y$2:$AA$13,2),"") | D12: =IFERROR(GETPIVOTDATA("Valor Recebido",'Dashboard-Dados'!$J$1,$A$1,A12,$B$1,B12),0) -> 0 | E12: =IFERROR(GETPIVOTDATA("Valor Despesa",'Dashboard-Dados'!$P$1,$A$1,A12,$B$1,B12),0) -> 0 | F12: =D12-E12 -> 0 | G12: =IFERROR(GETPIVOTDATA("Exame",'Dashboard-Dados'!$J$1,$A$1,A12,$B$1,B12),0) -> 0 | H12: =ROW() -> 12 | Y12: =Y11+1 -> 11 | Z12: =PROPER(TEXT(DATE(1900,Y12,1),"mmm")) -> Nov. | AA12: =PROPER(TEXT(DATE(1900,Y12,1),"mmMm")) -> Novembro | AB12: =IFNA(INDIRECT(ADDRESS(Y12+$Z$15,$AB$15)), 0) -> 0 | AC12: =AB12-AB11 -> 0 | AE12: Roxa | AF12: 71 | AG12: #674ea7 | AH12: =ROW() -> 12 | AI12: =$AF$17=AE12 -> FALSE
A13: =IFERROR(__xludf.DUMMYFUNCTION("""COMPUTED_VALUE"""),"#N/A") -> #N/A | C13: =IFNA(VLOOKUP('Dashboard-Dados'!B13,'Dashboard-Dados'!$Y$2:$AA$13,2),"") | D13: =IFERROR(GETPIVOTDATA("Valor Recebido",'Dashboard-Dados'!$J$1,$A$1,A13,$B$1,B13),0) -> 0 | E13: =IFERROR(GETPIVOTDATA("Valor Despesa",'Dashboard-Dados'!$P$1,$A$1,A13,$B$1,B13),0) -> 0 | F13: =D13-E13 -> 0 | G13: =IFERROR(GETPIVOTDATA("Exame",'Dashboard-Dados'!$J$1,$A$1,A13,$B$1,B13),0) -> 0 | H13: =ROW() -> 13 | Y13: =Y12+1 -> 12 | Z13: =PROPER(TEXT(DATE(1900,Y13,1),"mmm")) -> Dez. | AA13: =PROPER(TEXT(DATE(1900,Y13,1),"mmMm")) -> Dezembro | AB13: =IFNA(INDIRECT(ADDRESS(Y13+$Z$15,$AB$15)), 0) -> 0 | AC13: =AB13-AB12 -> 0 | AE13: Marrom | AF13: 131 | AG13: #783f04 | AH13: =ROW() -> 13 | AI13: =$AF$17=AE13 -> FALSE
C14: =IFNA(VLOOKUP('Dashboard-Dados'!B14,'Dashboard-Dados'!$Y$2:$AA$13,2),"") | D14: =IFERROR(GETPIVOTDATA("Valor Recebido",'Dashboard-Dados'!$J$1,$A$1,A14,$B$1,B14),0) -> 0 | E14: =IFERROR(GETPIVOTDATA("Valor Despesa",'Dashboard-Dados'!$P$1,$A$1,A14,$B$1,B14),0) -> 0 | F14: =D14-E14 -> 0 | G14: =IFERROR(GETPIVOTDATA("Exame",'Dashboard-Dados'!$J$1,$A$1,A14,$B$1,B14),0) -> 0 | H14: =ROW() -> 14 | AA14: Índice Linha | AB14: Indice Qtd. Exames | AE14: Preta | AF14: 201 | AG14: #000000 | AH14: =ROW() -> 14 | AI14: =$AF$17=AE14 -> FALSE
C15: =IFNA(VLOOKUP('Dashboard-Dados'!B15,'Dashboard-Dados'!$Y$2:$AA$13,2),"") | D15: =IFERROR(GETPIVOTDATA("Valor Recebido",'Dashboard-Dados'!$J$1,$A$1,A15,$B$1,B15),0) -> 0 | E15: =IFERROR(GETPIVOTDATA("Valor Despesa",'Dashboard-Dados'!$P$1,$A$1,A15,$B$1,B15),0) -> 0 | F15: =D15-E15 -> 0 | G15: =IFERROR(GETPIVOTDATA("Exame",'Dashboard-Dados'!$J$1,$A$1,A15,$B$1,B15),0) -> 0 | H15: =ROW() -> 15 | Y15: Parâmetros | Z15: =VLOOKUP(Dashboard!X7,'Dashboard-Dados'!A2:H1201,AA15)-12 -> #N/A | AA15: =COLUMN('Dashboard-Dados'!H1) -> 8 | AB15: =COLUMN('Dashboard-Dados'!G1) -> 7
C16: =IFNA(VLOOKUP('Dashboard-Dados'!B16,'Dashboard-Dados'!$Y$2:$AA$13,2),"") | D16: =IFERROR(GETPIVOTDATA("Valor Recebido",'Dashboard-Dados'!$J$1,$A$1,A16,$B$1,B16),0) -> 0 | E16: =IFERROR(GETPIVOTDATA("Valor Despesa",'Dashboard-Dados'!$P$1,$A$1,A16,$B$1,B16),0) -> 0 | F16: =D16-E16 -> 0 | G16: =IFERROR(GETPIVOTDATA("Exame",'Dashboard-Dados'!$J$1,$A$1,A16,$B$1,B16),0) -> 0 | H16: =ROW() -> 16 | AE16: Linha Alvo | AF16: =IF(AG5>=AF14,ROW(AE14),IF(AG5>=AF13,ROW(AE13),IF(AG5>=AF12,ROW(AE12),IF(AG5>=AF11,ROW(AE11),ROW(AE10))))) -> 10
C17: =IFNA(VLOOKUP('Dashboard-Dados'!B17,'Dashboard-Dados'!$Y$2:$AA$13,2),"") | D17: =IFERROR(GETPIVOTDATA("Valor Recebido",'Dashboard-Dados'!$J$1,$A$1,A17,$B$1,B17),0) -> 0 | E17: =IFERROR(GETPIVOTDATA("Valor Despesa",'Dashboard-Dados'!$P$1,$A$1,A17,$B$1,B17),0) -> 0 | F17: =D17-E17 -> 0 | G17: =IFERROR(GETPIVOTDATA("Exame",'Dashboard-Dados'!$J$1,$A$1,A17,$B$1,B17),0) -> 0 | H17: =ROW() -> 17 | AE17: Faixa Alvo | AF17: {=INDIRECT(ADDRESS(AF16,AE9))} -> Branca
C18: =IFNA(VLOOKUP('Dashboard-Dados'!B18,'Dashboard-Dados'!$Y$2:$AA$13,2),"") | D18: =IFERROR(GETPIVOTDATA("Valor Recebido",'Dashboard-Dados'!$J$1,$A$1,A18,$B$1,B18),0) -> 0 | E18: =IFERROR(GETPIVOTDATA("Valor Despesa",'Dashboard-Dados'!$P$1,$A$1,A18,$B$1,B18),0) -> 0 | F18: =D18-E18 -> 0 | G18: =IFERROR(GETPIVOTDATA("Exame",'Dashboard-Dados'!$J$1,$A$1,A18,$B$1,B18),0) -> 0 | H18: =ROW() -> 18 | AE18: Qtd. Próx. Faixa | AF18: {=INDIRECT(ADDRESS(IF(AF16=AH14,AF16,AF16+1),AF9))} -> 1
C19: =IFNA(VLOOKUP('Dashboard-Dados'!B19,'Dashboard-Dados'!$Y$2:$AA$13,2),"") | D19: =IFERROR(GETPIVOTDATA("Valor Recebido",'Dashboard-Dados'!$J$1,$A$1,A19,$B$1,B19),0) -> 0 | E19: =IFERROR(GETPIVOTDATA("Valor Despesa",'Dashboard-Dados'!$P$1,$A$1,A19,$B$1,B19),0) -> 0 | F19: =D19-E19 -> 0 | G19: =IFERROR(GETPIVOTDATA("Exame",'Dashboard-Dados'!$J$1,$A$1,A19,$B$1,B19),0) -> 0 | H19: =ROW() -> 19 | AE19: Máx. Exames | AF19: =AG5 -> 0
C20: =IFNA(VLOOKUP('Dashboard-Dados'!B20,'Dashboard-Dados'!$Y$2:$AA$13,2),"") | D20: =IFERROR(GETPIVOTDATA("Valor Recebido",'Dashboard-Dados'!$J$1,$A$1,A20,$B$1,B20),0) -> 0 | E20: =IFERROR(GETPIVOTDATA("Valor Despesa",'Dashboard-Dados'!$P$1,$A$1,A20,$B$1,B20),0) -> 0 | F20: =D20-E20 -> 0 | G20: =IFERROR(GETPIVOTDATA("Exame",'Dashboard-Dados'!$J$1,$A$1,A20,$B$1,B20),0) -> 0 | H20: =ROW() -> 20 | AE20: Diff Próx. Faixa | AF20: =AF18-AF19 -> 1
C21: =IFNA(VLOOKUP('Dashboard-Dados'!B21,'Dashboard-Dados'!$Y$2:$AA$13,2),"") | D21: =IFERROR(GETPIVOTDATA("Valor Recebido",'Dashboard-Dados'!$J$1,$A$1,A21,$B$1,B21),0) -> 0 | E21: =IFERROR(GETPIVOTDATA("Valor Despesa",'Dashboard-Dados'!$P$1,$A$1,A21,$B$1,B21),0) -> 0 | F21: =D21-E21 -> 0 | G21: =IFERROR(GETPIVOTDATA("Exame",'Dashboard-Dados'!$J$1,$A$1,A21,$B$1,B21),0) -> 0 | H21: =ROW() -> 21 | AE21: Atual | AF21: =AF19/AF18 -> 0
C22: =IFNA(VLOOKUP('Dashboard-Dados'!B22,'Dashboard-Dados'!$Y$2:$AA$13,2),"") | D22: =IFERROR(GETPIVOTDATA("Valor Recebido",'Dashboard-Dados'!$J$1,$A$1,A22,$B$1,B22),0) -> 0 | E22: =IFERROR(GETPIVOTDATA("Valor Despesa",'Dashboard-Dados'!$P$1,$A$1,A22,$B$1,B22),0) -> 0 | F22: =D22-E22 -> 0 | G22: =IFERROR(GETPIVOTDATA("Exame",'Dashboard-Dados'!$J$1,$A$1,A22,$B$1,B22),0) -> 0 | H22: =ROW() -> 22 | AE22: Próxima | AF22: =AF20/AF18 -> 1
C23: =IFNA(VLOOKUP('Dashboard-Dados'!B23,'Dashboard-Dados'!$Y$2:$AA$13,2),"") | D23: =IFERROR(GETPIVOTDATA("Valor Recebido",'Dashboard-Dados'!$J$1,$A$1,A23,$B$1,B23),0) -> 0 | E23: =IFERROR(GETPIVOTDATA("Valor Despesa",'Dashboard-Dados'!$P$1,$A$1,A23,$B$1,B23),0) -> 0 | F23: =D23-E23 -> 0 | G23: =IFERROR(GETPIVOTDATA("Exame",'Dashboard-Dados'!$J$1,$A$1,A23,$B$1,B23),0) -> 0 | H23: =ROW() -> 23
C24: =IFNA(VLOOKUP('Dashboard-Dados'!B24,'Dashboard-Dados'!$Y$2:$AA$13,2),"") | D24: =IFERROR(GETPIVOTDATA("Valor Recebido",'Dashboard-Dados'!$J$1,$A$1,A24,$B$1,B24),0) -> 0 | E24: =IFERROR(GETPIVOTDATA("Valor Despesa",'Dashboard-Dados'!$P$1,$A$1,A24,$B$1,B24),0) -> 0 | F24: =D24-E24 -> 0 | G24: =IFERROR(GETPIVOTDATA("Exame",'Dashboard-Dados'!$J$1,$A$1,A24,$B$1,B24),0) -> 0 | H24: =ROW() -> 24
C25: =IFNA(VLOOKUP('Dashboard-Dados'!B25,'Dashboard-Dados'!$Y$2:$AA$13,2),"") | D25: =IFERROR(GETPIVOTDATA("Valor Recebido",'Dashboard-Dados'!$J$1,$A$1,A25,$B$1,B25),0) -> 0 | E25: =IFERROR(GETPIVOTDATA("Valor Despesa",'Dashboard-Dados'!$P$1,$A$1,A25,$B$1,B25),0) -> 0 | F25: =D25-E25 -> 0 | G25: =IFERROR(GETPIVOTDATA("Exame",'Dashboard-Dados'!$J$1,$A$1,A25,$B$1,B25),0) -> 0 | H25: =ROW() -> 25
C26: =IFNA(VLOOKUP('Dashboard-Dados'!B26,'Dashboard-Dados'!$Y$2:$AA$13,2),"") | D26: =IFERROR(GETPIVOTDATA("Valor Recebido",'Dashboard-Dados'!$J$1,$A$1,A26,$B$1,B26),0) -> 0 | E26: =IFERROR(GETPIVOTDATA("Valor Despesa",'Dashboard-Dados'!$P$1,$A$1,A26,$B$1,B26),0) -> 0 | F26: =D26-E26 -> 0 | G26: =IFERROR(GETPIVOTDATA("Exame",'Dashboard-Dados'!$J$1,$A$1,A26,$B$1,B26),0) -> 0 | H26: =ROW() -> 26
C27: =IFNA(VLOOKUP('Dashboard-Dados'!B27,'Dashboard-Dados'!$Y$2:$AA$13,2),"") | D27: =IFERROR(GETPIVOTDATA("Valor Recebido",'Dashboard-Dados'!$J$1,$A$1,A27,$B$1,B27),0) -> 0 | E27: =IFERROR(GETPIVOTDATA("Valor Despesa",'Dashboard-Dados'!$P$1,$A$1,A27,$B$1,B27),0) -> 0 | F27: =D27-E27 -> 0 | G27: =IFERROR(GETPIVOTDATA("Exame",'Dashboard-Dados'!$J$1,$A$1,A27,$B$1,B27),0) -> 0 | H27: =ROW() -> 27
C28: =IFNA(VLOOKUP('Dashboard-Dados'!B28,'Dashboard-Dados'!$Y$2:$AA$13,2),"") | D28: =IFERROR(GETPIVOTDATA("Valor Recebido",'Dashboard-Dados'!$J$1,$A$1,A28,$B$1,B28),0) -> 0 | E28: =IFERROR(GETPIVOTDATA("Valor Despesa",'Dashboard-Dados'!$P$1,$A$1,A28,$B$1,B28),0) -> 0 | F28: =D28-E28 -> 0 | G28: =IFERROR(GETPIVOTDATA("Exame",'Dashboard-Dados'!$J$1,$A$1,A28,$B$1,B28),0) -> 0 | H28: =ROW() -> 28
C29: =IFNA(VLOOKUP('Dashboard-Dados'!B29,'Dashboard-Dados'!$Y$2:$AA$13,2),"") | D29: =IFERROR(GETPIVOTDATA("Valor Recebido",'Dashboard-Dados'!$J$1,$A$1,A29,$B$1,B29),0) -> 0 | E29: =IFERROR(GETPIVOTDATA("Valor Despesa",'Dashboard-Dados'!$P$1,$A$1,A29,$B$1,B29),0) -> 0 | F29: =D29-E29 -> 0 | G29: =IFERROR(GETPIVOTDATA("Exame",'Dashboard-Dados'!$J$1,$A$1,A29,$B$1,B29),0) -> 0 | H29: =ROW() -> 29
C30: =IFNA(VLOOKUP('Dashboard-Dados'!B30,'Dashboard-Dados'!$Y$2:$AA$13,2),"") | D30: =IFERROR(GETPIVOTDATA("Valor Recebido",'Dashboard-Dados'!$J$1,$A$1,A30,$B$1,B30),0) -> 0 | E30: =IFERROR(GETPIVOTDATA("Valor Despesa",'Dashboard-Dados'!$P$1,$A$1,A30,$B$1,B30),0) -> 0 | F30: =D30-E30 -> 0 | G30: =IFERROR(GETPIVOTDATA("Exame",'Dashboard-Dados'!$J$1,$A$1,A30,$B$1,B30),0) -> 0 | H30: =ROW() -> 30
C31: =IFNA(VLOOKUP('Dashboard-Dados'!B31,'Dashboard-Dados'!$Y$2:$AA$13,2),"") | D31: =IFERROR(GETPIVOTDATA("Valor Recebido",'Dashboard-Dados'!$J$1,$A$1,A31,$B$1,B31),0) -> 0 | E31: =IFERROR(GETPIVOTDATA("Valor Despesa",'Dashboard-Dados'!$P$1,$A$1,A31,$B$1,B31),0) -> 0 | F31: =D31-E31 -> 0 | G31: =IFERROR(GETPIVOTDATA("Exame",'Dashboard-Dados'!$J$1,$A$1,A31,$B$1,B31),0) -> 0 | H31: =ROW() -> 31
C32: =IFNA(VLOOKUP('Dashboard-Dados'!B32,'Dashboard-Dados'!$Y$2:$AA$13,2),"") | D32: =IFERROR(GETPIVOTDATA("Valor Recebido",'Dashboard-Dados'!$J$1,$A$1,A32,$B$1,B32),0) -> 0 | E32: =IFERROR(GETPIVOTDATA("Valor Despesa",'Dashboard-Dados'!$P$1,$A$1,A32,$B$1,B32),0) -> 0 | F32: =D32-E32 -> 0 | G32: =IFERROR(GETPIVOTDATA("Exame",'Dashboard-Dados'!$J$1,$A$1,A32,$B$1,B32),0) -> 0 | H32: =ROW() -> 32
C33: =IFNA(VLOOKUP('Dashboard-Dados'!B33,'Dashboard-Dados'!$Y$2:$AA$13,2),"") | D33: =IFERROR(GETPIVOTDATA("Valor Recebido",'Dashboard-Dados'!$J$1,$A$1,A33,$B$1,B33),0) -> 0 | E33: =IFERROR(GETPIVOTDATA("Valor Despesa",'Dashboard-Dados'!$P$1,$A$1,A33,$B$1,B33),0) -> 0 | F33: =D33-E33 -> 0 | G33: =IFERROR(GETPIVOTDATA("Exame",'Dashboard-Dados'!$J$1,$A$1,A33,$B$1,B33),0) -> 0 | H33: =ROW() -> 33
C34: =IFNA(VLOOKUP('Dashboard-Dados'!B34,'Dashboard-Dados'!$Y$2:$AA$13,2),"") | D34: =IFERROR(GETPIVOTDATA("Valor Recebido",'Dashboard-Dados'!$J$1,$A$1,A34,$B$1,B34),0) -> 0 | E34: =IFERROR(GETPIVOTDATA("Valor Despesa",'Dashboard-Dados'!$P$1,$A$1,A34,$B$1,B34),0) -> 0 | F34: =D34-E34 -> 0 | G34: =IFERROR(GETPIVOTDATA("Exame",'Dashboard-Dados'!$J$1,$A$1,A34,$B$1,B34),0) -> 0 | H34: =ROW() -> 34
... C1201: =IFNA(VLOOKUP('Dashboard-Dados'!B1201,'Dashboard-Dados'!$Y$2:$AA$13,2),"") | D1201: =IFERROR(GETPIVOTDATA("Valor Recebido",'Dashboard-Dados'!$J$1,$A$1,A1201,$B$1,B1201),0) -> 0 | E1201: =IFERROR(GETPIVOTDATA("Valor Despesa",'Dashboard-Dados'!$P$1,$A$1,A1201,$B$1,B1201),0) -> 0 | F1201: =D1201-E1201 -> 0 | G1201: =IFERROR(GETPIVOTDATA("Exame",'Dashboard-Dados'!$J$1,$A$1,A1201,$B$1,B1201),0) -> 0 | H1201: =ROW() -> 1201
